Workbook

Sheet Datos Cfdis
A1: Periodo | B1: Version | C1: UUID | D1: UUIDs relacionados | E1: Tipo relacion | F1: CP Expedicion | G1: Serie | H1: Folio | I1: Tipo | J1: Fecha emision | K1: Fecha certificacion | L1: pacCertifico | M1: Regimen emisor | N1: RFC emisor | O1: Razon emisor | P1: RFC receptor | Q1: Razon receptor | R1: Regimen receptor | S1: Domicilio receptor | T1: Claves de productos | U1: Conceptos | V1: Cuenta Predial | W1: Uso CFDI | X1: Complementos | Y1: Global periodicidad | Z1: Global meses | AA1: Global año | AB1: Condiciones de pago | AC1: Efecto | AD1: Estado | AE1: Fecha proceso cancelacion | AF1: Estado cancelacion | AG1: Estado proceso cancelacion | AH1: Motivo cancelacion | AI1: Folio sustitucion cancelacion | AJ1: Moneda | AK1: Tipo de cambio | AL1: Exportacion | AM1: Metodo pago | AN1: Forma pago | AO1: SubTotalCombustibles | AP1: SubTotal | AQ1: Descuento | AR1: IVA Trasladado | AS1: IVA Exento | AT1: IVA Retenido | AU1: ISR Retenido | AV1: IEPS Trasladado No Desglosado | AW1: IEPS Trasladado | AX1: IEPS Retenido | AY1: Local retenido | AZ1: Local trasladado | BA1: TotalCombustibles | BB1: Total | BC1: Cruce
A2: 11 | B2: 4.0 | C2: 5DE6C776-1B17-5F72-93DB-C4F64D0B109A | F2: 06700 | G2: 301479 | H2: 301479 | I2: P - Pago | J2: 2025-11-01 18:10:42 | K2: 2025-11-01 18:15:43 | L2: CVD110412TF6 | M2: 601 - General de Ley Personas Morales | N2: CFS1808284P2 | O2: COMUNIDAD FELIZ SERVICIOS TI | P2: CAFC880712K61 | Q2: CAROLINA LISETT CHAVEZ FERNANDEZ | R2: 626 - Régimen Simplificado de Confianza | S2: 20040 | T2: 84111506 - Servicios de facturación | U2: Pago | W2: CP01 - Pagos | X2: PAGO | AD2: VIGENTE | AF2: CANCELABLE SIN ACEPTACIÓN | AJ2: XXX | AL2: 01 No aplica | AO2: 0 | AP2: 0 | AQ2: 0 | AR2: 0 | AS2: 0 | AT2: 0 | AU2: 0 | AV2: 0 | AW2: 0 | AX2: 0 | AY2: 0 | AZ2: 0 | BA2: 0 | BB2: 1885 | BC2: =+VLOOKUP(C2,CF!F:F,1,0) -> #N/A
A3: 11 | B3: 4.0 | C3: 04CDE9DC-2227-5AD0-8324-B150D2CE24D2 | F3: 06700 | G3: C118697 | H3: 16745 | I3: I - Ingreso | J3: 2025-11-02 22:01:00 | K3: 2025-11-02 22:06:01 | L3: CVD110412TF6 | M3: 601 - General de Ley Personas Morales | N3: CFS1808284P2 | O3: COMUNIDAD FELIZ SERVICIOS TI | P3: XAXX010101000 | Q3: PUBLICO EN GENERAL | R3: 616 - Sin obligaciones fiscales | S3: 06700 | T3: 81112500 - Servicios de alquiler o arrendamiento de licencias de software de computador | 81112500 - Servicios de alquiler o arrendamiento de licencias de software de computador | U3: Sistema de Transferencias y Pagos 03 de Noviembre de 2025 a 02 de Diciembre de 2 | Licencia de Software 03 de Noviembre de 2025 a 02 de Diciembre de 2025. MONTE VE | W3: S01 - Sin efectos fiscales | Y3: 01 | Z3: 11 Noviembre | AA3: 2025 | AB3: CONDICIONES | AD3: VIGENTE | AF3: NO CANCELABLE | AJ3: MXN | AL3: 01 No aplica | AM3: PPD - Pago en Parcialidades o Diferido | AN3: 99 - Por definir | AO3: 0 | AP3: 4095 | AQ3: 0 | AR3: 655.2 | AS3: 0 | AT3: 0 | AU3: 0 | AV3: 0 | AW3: 0 | AX3: 0 | AY3: 0 | AZ3: 0 | BA3: 0 | BB3: 4750.2 | BC3: =+VLOOKUP(C3,CF!F:F,1,0) -> 04CDE9DC-2227-5AD0-8324-B150D2CE24D2
A4: 11 | B4: 4.0 | C4: E95C5FA2-DC5A-5E57-9447-4AA79B40C0DD | F4: 06700 | G4: C122394 | H4: 16746 | I4: I - Ingreso | J4: 2025-11-03 06:32:04 | K4: 2025-11-03 06:37:05 | L4: CVD110412TF6 | M4: 601 - General de Ley Personas Morales | N4: CFS1808284P2 | O4: COMUNIDAD FELIZ SERVICIOS TI | P4: CAE220831119 | Q4: CONDOMINIO AURA DE ENSENADA | R4: 603 - Personas Morales con Fines no Lucrativos | S4: 22760 | T4: 81112500 - Servicios de alquiler o arrendamiento de licencias de software de computador | 81112500 - Servicios de alquiler o arrendamiento de licencias de software de computador | 81112500 - Servicios de alquiler o arrendamiento de licencias de software de computador | U4: Licencia de Software 29 de Octubre de 2025 a 28 de Noviembre de 2025. CONDOMINIO | Sistema de Transferencias y Pagos 29 de Octubre de 2025 a 28 de Noviembre de 202 | Facturación CFDI 4.0 | W4: G03 - Gastos en general | AB4: CONDICIONES | AD4: VIGENTE | AF4: CANCELABLE CON ACEPTACIÓN | AJ4: MXN | AL4: 01 No aplica | AM4: PPD - Pago en Parcialidades o Diferido | AN4: 99 - Por definir | AO4: 0 | AP4: 1600 | AQ4: 0 | AR4: 256 | AS4: 0 | AT4: 0 | AU4: 0 | AV4: 0 | AW4: 0 | AX4: 0 | AY4: 0 | AZ4: 0 | BA4: 0 | BB4: 1856 | BC4: =+VLOOKUP(C4,CF!F:F,1,0) -> E95C5FA2-DC5A-5E57-9447-4AA79B40C0DD
A5: 11 | B5: 4.0 | C5: A826D0A1-4B15-5CBB-A992-0A10376185FA | F5: 06700 | G5: C119046 | H5: 16747 | I5: I - Ingreso | J5: 2025-11-03 06:32:07 | K5: 2025-11-03 06:37:08 | L5: CVD110412TF6 | M5: 601 - General de Ley Personas Morales | N5: CFS1808284P2 | O5: COMUNIDAD FELIZ SERVICIOS TI | P5: ATI200729JH1 | Q5: ALTITUD 3 INMOBILIARIA | R5: 601 - General de Ley Personas Morales | S5: 21180 | T5: 81112500 - Servicios de alquiler o arrendamiento de licencias de software de computador | 81112500 - Servicios de alquiler o arrendamiento de licencias de software de computador | 81112500 - Servicios de alquiler o arrendamiento de licencias de software de computador | U5: Facturación CFDI 4.0 | Licencia de Software 29 de Octubre de 2025 a 28 de Noviembre de 2025. PUNTO SUR | Sistema de Transferencias y Pagos 29 de Octubre de 2025 a 28 de Noviembre de 202 | W5: G03 - Gastos en general | AB5: CONDICIONES | AD5: VIGENTE | AF5: NO CANCELABLE | AJ5: MXN | AL5: 01 No aplica | AM5: PPD - Pago en Parcialidades o Diferido | AN5: 99 - Por definir | AO5: 0 | AP5: 900 | AQ5: 0 | AR5: 144 | AS5: 0 | AT5: 0 | AU5: 0 | AV5: 0 | AW5: 0 | AX5: 0 | AY5: 0 | AZ5: 0 | BA5: 0 | BB5: 1044 | BC5: =+VLOOKUP(C5,CF!F:F,1,0) -> A826D0A1-4B15-5CBB-A992-0A10376185FA
A6: 11 | B6: 4.0 | C6: 67158668-29BD-5CFB-A008-EE6EEB068C60 | F6: 06700 | G6: C137977 | H6: 16748 | I6: I - Ingreso | J6: 2025-11-03 06:32:26 | K6: 2025-11-03 06:37:26 | L6: CVD110412TF6 | M6: 601 - General de Ley Personas Morales | N6: CFS1808284P2 | O6: COMUNIDAD FELIZ SERVICIOS TI | P6: CPG2410035V2 | Q6: CIMA PARK GREEN RESIDENCES | R6: 603 - Personas Morales con Fines no Lucrativos | S6: 45019 | T6: 81112500 - Servicios de alquiler o arrendamiento de licencias de software de computador | 81112500 - Servicios de alquiler o arrendamiento de licencias de software de computador | 81112500 - Servicios de alquiler o arrendamiento de licencias de software de computador | U6: Sistema de Transferencias y Pagos 22 de Octubre de 2025 a 21 de Noviembre de 202 | Licencia de Software 22 de Octubre de 2025 a 21 de Noviembre de 2025. UC-4 (COND | Facturación CFDI 4.0 | W6: G03 - Gastos en general | AB6: CONDICIONES | AD6: VIGENTE | AF6: CANCELABLE CON ACEPTACIÓN | AJ6: MXN | AL6: 01 No aplica | AM6: PPD - Pago en Parcialidades o Diferido | AN6: 99 - Por definir | AO6: 0 | AP6: 1794 | AQ6: 0 | AR6: 287.04 | AS6: 0 | AT6: 0 | AU6: 0 | AV6: 0 | AW6: 0 | AX6: 0 | AY6: 0 | AZ6: 0 | BA6: 0 | BB6: 2081.04 | BC6: =+VLOOKUP(C6,CF!F:F,1,0) -> 67158668-29BD-5CFB-A008-EE6EEB068C60
A7: 11 | B7: 4.0 | C7: A7ED75F9-3FD0-5313-ABB2-7CC3FC5F3FEC | F7: 06700 | G7: C118980 | H7: 16749 | I7: I - Ingreso | J7: 2025-11-03 06:32:28 | K7: 2025-11-03 06:37:29 | L7: CVD110412TF6 | M7: 601 - General de Ley Personas Morales | N7: CFS1808284P2 | O7: COMUNIDAD FELIZ SERVICIOS TI | P7: ACM240219JL0 | Q7: ASOCIACION DE CONDOMINOS MB TORRE FRESNO | R7: 603 - Personas Morales con Fines no Lucrativos | S7: 53126 | T7: 81112500 - Servicios de alquiler o arrendamiento de licencias de software de computador | 81112500 - Servicios de alquiler o arrendamiento de licencias de software de computador | U7: Licencia de Software 30 de Octubre de 2025 a 29 de Noviembre de 2025. MB TORRE F | Facturación CFDI 4.0 | W7: G03 - Gastos en general | AB7: CONDICIONES | AD7: VIGENTE | AF7: NO CANCELABLE | AJ7: MXN | AL7: 01 No aplica | AM7: PPD - Pago en Parcialidades o Diferido | AN7: 99 - Por definir | AO7: 0 | AP7: 1020 | AQ7: 0 | AR7: 163.2 | AS7: 0 | AT7: 0 | AU7: 0 | AV7: 0 | AW7: 0 | AX7: 0 | AY7: 0 | AZ7: 0 | BA7: 0 | BB7: 1183.2 | BC7: =+VLOOKUP(C7,CF!F:F,1,0) -> A7ED75F9-3FD0-5313-ABB2-7CC3FC5F3FEC
A8: 11 | B8: 4.0 | C8: F4B128DB-06B1-5E2E-B0DA-6C2E3B468BE1 | F8: 06700 | G8: C120348 | H8: 16750 | I8: I - Ingreso | J8: 2025-11-03 06:32:30 | K8: 2025-11-03 06:37:31 | L8: CVD110412TF6 | M8: 601 - General de Ley Personas Morales | N8: CFS1808284P2 | O8: COMUNIDAD FELIZ SERVICIOS TI | P8: CCG080213819 | Q8: CONDOMINOS DEL CONJUNTO GEMELOS DE ORO | R8: 603 - Personas Morales con Fines no Lucrativos | S8: 03720 | T8: 81112500 - Servicios de alquiler o arrendamiento de licencias de software de computador | 81112500 - Servicios de alquiler o arrendamiento de licencias de software de computador | U8: Licencia de Software 30 de Octubre de 2025 a 29 de Noviembre de 2025. CONDÓMINOS | Facturación CFDI 4.0 | W8: G03 - Gastos en general | AB8: CONDICIONES | AD8: VIGENTE | AF8: NO CANCELABLE | AJ8: MXN | AL8: 01 No aplica | AM8: PPD - Pago en Parcialidades o Diferido | AN8: 99 - Por definir | AO8: 0 | AP8: 1931.04 | AQ8: 0 | AR8: 308.96 | AS8: 0 | AT8: 0 | AU8: 0 | AV8: 0 | AW8: 0 | AX8: 0 | AY8: 0 | AZ8: 0 | BA8: 0 | BB8: 2240 | BC8: =+VLOOKUP(C8,CF!F:F,1,0) -> F4B128DB-06B1-5E2E-B0DA-6C2E3B468BE1
A9: 11 | B9: 4.0 | C9: DFC7828C-1270-52EB-841C-D8A7D600B0C8 | F9: 06700 | G9: C109508 | H9: 16756 | I9: I - Ingreso | J9: 2025-11-03 06:32:43 | K9: 2025-11-03 06:37:43 | L9: CVD110412TF6 | M9: 601 - General de Ley Personas Morales | N9: CFS1808284P2 | O9: COMUNIDAD FELIZ SERVICIOS TI | P9: ACC1809242M0 | Q9: ASOCIACION DE CONDOMINOS DEL CONDOMINIO PASEO MONET | R9: 603 - Personas Morales con Fines no Lucrativos | S9: 76269 | T9: 81112500 - Servicios de alquiler o arrendamiento de licencias de software de computador | 81112500 - Servicios de alquiler o arrendamiento de licencias de software de computador | 81112500 - Servicios de alquiler o arrendamiento de licencias de software de computador | U9: Sistema de Transferencias y Pagos 01 de Noviembre de 2025 a 30 de Noviembre de 2 | Facturación CFDI 4.0 | Licencia de Software 01 de Noviembre de 2025 a 30 de Noviembre de 2025. PASEO MO | W9: G03 - Gastos en general | AB9: CONDICIONES | AD9: VIGENTE | AF9: CANCELABLE CON ACEPTACIÓN | AG9: EN PROCESO | AJ9: MXN | AL9: 01 No aplica | AM9: PPD - Pago en Parcialidades o Diferido | AN9: 99 - Por definir | AO9: 0 | AP9: 2633.8 | AQ9: 23.18 | AR9: 417.7 | AS9: 0 | AT9: 0 | AU9: 0 | AV9: 0 | AW9: 0 | AX9: 0 | AY9: 0 | AZ9: 0 | BA9: 0 | BB9: 3028.32 | BC9: Anular
A10: 11 | B10: 4.0 | C10: A4B29CCA-E6F5-5043-AED8-CAA7AAAD8E87 | F10: 06700 | G10: C98822 | H10: 16757 | I10: I - Ingreso | J10: 2025-11-03 06:32:45 | K10: 2025-11-03 06:37:46 | L10: CVD110412TF6 | M10: 601 - General de Ley Personas Morales | N10: CFS1808284P2 | O10: COMUNIDAD FELIZ SERVICIOS TI | P10: CORB730131EX4 | Q10: BENJAMIN CORDOVA RICO | R10: 612 - Personas Físicas con Actividades Empresariales y Profesionales | S10: 62157 | T10: 81112500 - Servicios de alquiler o arrendamiento de licencias de software de computador | 81112500 - Servicios de alquiler o arrendamiento de licencias de software de computador | 81112500 - Servicios de alquiler o arrendamiento de licencias de software de computador | U10: Licencia de Software 01 de Noviembre de 2025 a 30 de Noviembre de 2025. CONDOMIN | Facturación CFDI 4.0 | Sistema de Transferencias y Pagos 01 de Noviembre de 2025 a 30 de Noviembre de 2 | W10: G03 - Gastos en general | AB10: CONDICIONES | AD10: VIGENTE | AF10: NO CANCELABLE | AJ10: MXN | AL10: 01 No aplica | AM10: PPD - Pago en Parcialidades o Diferido | AN10: 99 - Por definir | AO10: 0 | AP10: 1720 | AQ10: 0 | AR10: 275.2 | AS10: 0 | AT10: 0 | AU10: 0 | AV10: 0 | AW10: 0 | AX10: 0 | AY10: 0 | AZ10: 0 | BA10: 0 | BB10: 1995.2 | BC10: =+VLOOKUP(C10,CF!F:F,1,0) -> A4B29CCA-E6F5-5043-AED8-CAA7AAAD8E87
A11: 11 | B11: 4.0 | C11: 59D98271-2DEE-53BD-A0BA-6A4EEB9D4701 | F11: 06700 | G11: C119041 | H11: 16758 | I11: I - Ingreso | J11: 2025-11-03 06:32:47 | K11: 2025-11-03 06:37:48 | L11: CVD110412TF6 | M11: 601 - General de Ley Personas Morales | N11: CFS1808284P2 | O11: COMUNIDAD FELIZ SERVICIOS TI | P11: POLA810310P13 | Q11: ALEJANDRO PORTILLA LEROUX | R11: 612 - Personas Físicas con Actividades Empresariales y Profesionales | S11: 11700 | T11: 81112500 - Servicios de alquiler o arrendamiento de licencias de software de computador | 81112500 - Servicios de alquiler o arrendamiento de licencias de software de computador | 81112500 - Servicios de alquiler o arrendamiento de licencias de software de computador | 81112500 - Servicios de alquiler o arrendamiento de licencias de software de computador | 81112500 - Servicios de alquiler o arrendamiento de licencias de software de computador | 81112500 - Servicios de alquiler o arrendamiento de licencias de software de computador | U11: Licencia de Software 01 de Noviembre de 2025 a 30 de Noviembre de 2025. Centro C | Sistema de Transferencias y Pagos 01 de Noviembre de 2025 a 30 de Noviembre de 2 | Facturación CFDI 4.0 | Licencia de Software 01 de Noviembre de 2025 a 30 de Noviembre de 2025. Centro C | Sistema de Transferencias y Pagos 01 de Noviembre de 2025 a 30 de Noviembre de 2 | Facturación CFDI 4.0 | W11: G03 - Gastos en general | AB11: CONDICIONES | AD11: VIGENTE | AF11: CANCELABLE CON ACEPTACIÓN | AJ11: MXN | AL11: 01 No aplica | AM11: PPD - Pago en Parcialidades o Diferido | AN11: 99 - Por definir | AO11: 0 | AP11: 1482.36 | AQ11: 0 | AR11: 237.17 | AS11: 0 | AT11: 0 | AU11: 0 | AV11: 0 | AW11: 0 | AX11: 0 | AY11: 0 | AZ11: 0 | BA11: 0 | BB11: 1719.53 | BC11: =+VLOOKUP(C11,CF!F:F,1,0) -> 59D98271-2DEE-53BD-A0BA-6A4EEB9D4701
A12: 11 | B12: 4.0 | C12: BB0A4DFE-84F1-5751-A626-EF5B0BEFA37C | F12: 06700 | G12: C152985 | H12: 16759 | I12: I - Ingreso | J12: 2025-11-03 06:32:49 | K12: 2025-11-03 06:37:50 | L12: CVD110412TF6 | M12: 601 - General de Ley Personas Morales | N12: CFS1808284P2 | O12: COMUNIDAD FELIZ SERVICIOS TI | P12: LGJ990329DK2 | Q12: LAS LOMAS DE GRAN JARDIN | R12: 601 - General de Ley Personas Morales | S12: 37160 | T12: 81112500 - Servicios de alquiler o arrendamiento de licencias de software de computador | 81112500 - Servicios de alquiler o arrendamiento de licencias de software de computador | 81112500 - Servicios de alquiler o arrendamiento de licencias de software de computador | U12: Licencia de Software 01 de Noviembre de 2025 a 30 de Noviembre de 2025. Condomin | Sistema de Transferencias y Pagos 01 de Noviembre de 2025 a 30 de Noviembre de 2 | Facturación CFDI 4.0 | W12: G03 - Gastos en general | AB12: CONDICIONES | AD12: VIGENTE | AF12: CANCELABLE CON ACEPTACIÓN | AJ12: MXN | AL12: 01 No aplica | AM12: PPD - Pago en Parcialidades o Diferido | AN12: 99 - Por definir | AO12: 0 | AP12: 1840 | AQ12: 0 | AR12: 294.4 | AS12: 0 | AT12: 0 | AU12: 0 | AV12: 0 | AW12: 0 | AX12: 0 | AY12: 0 | AZ12: 0 | BA12: 0 | BB12: 2134.4 | BC12: =+VLOOKUP(C12,CF!F:F,1,0) -> BB0A4DFE-84F1-5751-A626-EF5B0BEFA37C
A13: 11 | B13: 4.0 | C13: 038E673F-CF74-5A98-8B1A-D6626B30C40A | F13: 06700 | G13: C119113 | H13: 16760 | I13: I - Ingreso | J13: 2025-11-03 06:32:51 | K13: 2025-11-03 06:37:52 | L13: CVD110412TF6 | M13: 601 - General de Ley Personas Morales | N13: CFS1808284P2 | O13: COMUNIDAD FELIZ SERVICIOS TI | P13: ARD1703276G0 | Q13: DII INMOBILIARIA 916 | R13: 601 - General de Ley Personas Morales | S13: 64710 | T13: 81112500 - Servicios de alquiler o arrendamiento de licencias de software de computador | 81112500 - Servicios de alquiler o arrendamiento de licencias de software de computador | 81112500 - Servicios de alquiler o arrendamiento de licencias de software de computador | U13: Sistema de Transferencias y Pagos 01 de Noviembre de 2025 a 30 de Noviembre de 2 | Licencia de Software 01 de Noviembre de 2025 a 30 de Noviembre de 2025. Highpark | Facturación CFDI 4.0 | W13: G03 - Gastos en general | AB13: CONDICIONES | AD13: VIGENTE | AF13: NO CANCELABLE | AJ13: MXN | AL13: 01 No aplica | AM13: PPD - Pago en Parcialidades o Diferido | AN13: 99 - Por definir | AO13: 0 | AP13: 1330 | AQ13: 0 | AR13: 212.8 | AS13: 0 | AT13: 0 | AU13: 0 | AV13: 0 | AW13: 0 | AX13: 0 | AY13: 0 | AZ13: 0 | BA13: 0 | BB13: 1542.8 | BC13: =+VLOOKUP(C13,CF!F:F,1,0) -> 038E673F-CF74-5A98-8B1A-D6626B30C40A
A14: 11 | B14: 4.0 | C14: 05E85140-CEA1-574A-B411-3DC82526EF85 | F14: 06700 | G14: C155823 | H14: 16761 | I14: I - Ingreso | J14: 2025-11-03 06:32:53 | K14: 2025-11-03 06:37:54 | L14: CVD110412TF6 | M14: 601 - General de Ley Personas Morales | N14: CFS1808284P2 | O14: COMUNIDAD FELIZ SERVICIOS TI | P14: XAXX010101000 | Q14: PUBLICO EN GENERAL | R14: 616 - Sin obligaciones fiscales | S14: 06700 | T14: 81112500 - Servicios de alquiler o arrendamiento de licencias de software de computador | 81112500 - Servicios de alquiler o arrendamiento de licencias de software de computador | 81112500 - Servicios de alquiler o arrendamiento de licencias de software de computador | U14: Facturación CFDI 4.0 | Sistema de Transferencias y Pagos 01 de Noviembre de 2025 a 30 de Noviembre de 2 | Licencia de Software 01 de Noviembre de 2025 a 30 de Noviembre de 2025. Ribera d | W14: S01 - Sin efectos fiscales | Y14: 01 | Z14: 11 Noviembre | AA14: 2025 | AB14: CONDICIONES | AD14: VIGENTE | AF14: CANCELABLE SIN ACEPTACIÓN | AJ14: MXN | AL14: 01 No aplica | AM14: PPD - Pago en Parcialidades o Diferido | AN14: 99 - Por definir | AO14: 0 | AP14: 197.65 | AQ14: 0 | AR14: 31.62 | AS14: 0 | AT14: 0 | AU14: 0 | AV14: 0 | AW14: 0 | AX14: 0 | AY14: 0 | AZ14: 0 | BA14: 0 | BB14: 229.27 | BC14: =+VLOOKUP(C14,CF!F:F,1,0) -> 05E85140-CEA1-574A-B411-3DC82526EF85
A15: 11 | B15: 4.0 | C15: C0B992A4-C260-59A4-A8C7-8E4E20F5B67C | F15: 06700 | G15: C45948 | H15: 16762 | I15: I - Ingreso | J15: 2025-11-03 06:32:55 | K15: 2025-11-03 06:37:56 | L15: CVD110412TF6 | M15: 601 - General de Ley Personas Morales | N15: CFS1808284P2 | O15: COMUNIDAD FELIZ SERVICIOS TI | P15: MAY070912T36 | Q15: MAYR | R15: 601 - General de Ley Personas Morales | S15: 76137 | T15: 81112500 - Servicios de alquiler o arrendamiento de licencias de software de computador | 81112500 - Servicios de alquiler o arrendamiento de licencias de software de computador | U15: Licencia de Software 01 de Noviembre de 2025 a 31 de Octubre de 2026. Complejo e | Facturación CFDI 4.0 | W15: G03 - Gastos en general | AB15: CONDICIONES | AD15: VIGENTE | AF15: NO CANCELABLE | AJ15: MXN | AL15: 01 No aplica | AM15: PPD - Pago en Parcialidades o Diferido | AN15: 99 - Por definir | AO15: 0 | AP15: 9360.75 | AQ15: 0 | AR15: 1497.72 | AS15: 0 | AT15: 0 | AU15: 0 | AV15: 0 | AW15: 0 | AX15: 0 | AY15: 0 | AZ15: 0 | BA15: 0 | BB15: 10858.47 | BC15: =+VLOOKUP(C15,CF!F:F,1,0) -> C0B992A4-C260-59A4-A8C7-8E4E20F5B67C
A16: 11 | B16: 4.0 | C16: 9068D9EC-E8BA-5D02-AD49-FE3CE4E2770D | F16: 06700 | G16: C54353 | H16: 16763 | I16: I - Ingreso | J16: 2025-11-03 06:32:57 | K16: 2025-11-03 06:37:58 | L16: CVD110412TF6 | M16: 601 - General de Ley Personas Morales | N16: CFS1808284P2 | O16: COMUNIDAD FELIZ SERVICIOS TI | P16: CLM220218643 | Q16: CONDOMINIO LOMAS DEL MOLINO III | R16: 603 - Personas Morales con Fines no Lucrativos | S16: 37138 | T16: 81112500 - Servicios de alquiler o arrendamiento de licencias de software de computador | 81112500 - Servicios de alquiler o arrendamiento de licencias de software de computador | U16: Facturación CFDI 4.0 | Licencia de Software 01 de Noviembre de 2025 a 30 de Noviembre de 2025. Condomin | W16: G03 - Gastos en general | AB16: CONDICIONES | AD16: VIGENTE | AF16: NO CANCELABLE | AJ16: MXN | AL16: 01 No aplica | AM16: PPD - Pago en Parcialidades o Diferido | AN16: 99 - Por definir | AO16: 0 | AP16: 2242.14 | AQ16: 0 | AR16: 358.74 | AS16: 0 | AT16: 0 | AU16: 0 | AV16: 0 | AW16: 0 | AX16: 0 | AY16: 0 | AZ16: 0 | BA16: 0 | BB16: 2600.88 | BC16: =+VLOOKUP(C16,CF!F:F,1,0) -> 9068D9EC-E8BA-5D02-AD49-FE3CE4E2770D
A17: 11 | B17: 4.0 | C17: DA183D36-FF93-592F-A5AC-3B0AE9B06D5E | F17: 06700 | G17: C117679 | H17: 16764 | I17: I - Ingreso | J17: 2025-11-03 06:32:59 | K17: 2025-11-03 06:38:00 | L17: CVD110412TF6 | M17: 601 - General de Ley Personas Morales | N17: CFS1808284P2 | O17: COMUNIDAD FELIZ SERVICIOS TI | P17: ACR230920CW0 | Q17: ADMINISTRACION DEL CONDOMINIO RESIDENCIAL LAZARO CARDENAS 2225 | R17: 603 - Personas Morales con Fines no Lucrativos | S17: 66260 | T17: 81112500 - Servicios de alquiler o arrendamiento de licencias de software de computador | 81112500 - Servicios de alquiler o arrendamiento de licencias de software de computador | 81112500 - Servicios de alquiler o arrendamiento de licencias de software de computador | U17: Sistema de Transferencias y Pagos 01 de Noviembre de 2025 a 30 de Noviembre de 2 | Facturación CFDI 4.0 | Licencia de Software 01 de Noviembre de 2025 a 30 de Noviembre de 2025. San Pedr | W17: G03 - Gastos en general | AB17: CONDICIONES | AD17: VIGENTE | AF17: CANCELABLE CON ACEPTACIÓN | AJ17: MXN | AL17: 01 No aplica | AM17: PPD - Pago en Parcialidades o Diferido | AN17: 99 - Por definir | AO17: 0 | AP17: 4199 | AQ17: 0 | AR17: 671.84 | AS17: 0 | AT17: 0 | AU17: 0 | AV17: 0 | AW17: 0 | AX17: 0 | AY17: 0 | AZ17: 0 | BA17: 0 | BB17: 4870.84 | BC17: =+VLOOKUP(C17,CF!F:F,1,0) -> DA183D36-FF93-592F-A5AC-3B0AE9B06D5E
A18: 11 | B18: 4.0 | C18: 96B60C05-EE8B-572F-B9FE-D7E80B4C83A5 | F18: 06700 | G18: C117681 | H18: 16765 | I18: I - Ingreso | J18: 2025-11-03 06:33:01 | K18: 2025-11-03 06:38:02 | L18: CVD110412TF6 | M18: 601 - General de Ley Personas Morales | N18: CFS1808284P2 | O18: COMUNIDAD FELIZ SERVICIOS TI | P18: ACR230920TD8 | Q18: ADMINISTRACION DEL CONDOMINIO RESIDENCIAL AV. GARZA SADA 1892 | R18: 603 - Personas Morales con Fines no Lucrativos | S18: 64860 | T18: 81112500 - Servicios de alquiler o arrendamiento de licencias de software de computador | 81112500 - Servicios de alquiler o arrendamiento de licencias de software de computador | 81112500 - Servicios de alquiler o arrendamiento de licencias de software de computador | U18: Facturación CFDI 4.0 | Licencia de Software 01 de Noviembre de 2025 a 30 de Noviembre de 2025. Garza Sa | Sistema de Transferencias y Pagos 01 de Noviembre de 2025 a 30 de Noviembre de 2 | W18: G03 - Gastos en general | AB18: CONDICIONES | AD18: VIGENTE | AF18: CANCELABLE CON ACEPTACIÓN | AJ18: MXN | AL18: 01 No aplica | AM18: PPD - Pago en Parcialidades o Diferido | AN18: 99 - Por definir | AO18: 0 | AP18: 6409 | AQ18: 0 | AR18: 1025.44 | AS18: 0 | AT18: 0 | AU18: 0 | AV18: 0 | AW18: 0 | AX18: 0 | AY18: 0 | AZ18: 0 | BA18: 0 | BB18: 7434.44 | BC18: =+VLOOKUP(C18,CF!F:F,1,0) -> 96B60C05-EE8B-572F-B9FE-D7E80B4C83A5
A19: 11 | B19: 4.0 | C19: 29162AA3-7A58-5440-95F4-A895F9F07441 | F19: 06700 | G19: C66213 | H19: 16766 | I19: I - Ingreso | J19: 2025-11-03 06:33:03 | K19: 2025-11-03 06:38:04 | L19: CVD110412TF6 | M19: 601 - General de Ley Personas Morales | N19: CFS1808284P2 | O19: COMUNIDAD FELIZ SERVICIOS TI | P19: SBC220201FJ7 | Q19: SIE7E BY COSMOPOLITAN | R19: 603 - Personas Morales con Fines no Lucrativos | S19: 22000 | T19: 81112500 - Servicios de alquiler o arrendamiento de licencias de software de computador | 81112500 - Servicios de alquiler o arrendamiento de licencias de software de computador | U19: Licencia de Software 02 de Noviembre de 2025 a 01 de Diciembre de 2025. SIE7E BY | Facturación CFDI 4.0 | W19: G03 - Gastos en general | AB19: CONDICIONES | AD19: VIGENTE | AF19: NO CANCELABLE | AJ19: MXN | AL19: 01 No aplica | AM19: PPD - Pago en Parcialidades o Diferido | AN19: 99 - Por definir | AO19: 0 | AP19: 1529.85 | AQ19: 0 | AR19: 244.78 | AS19: 0 | AT19: 0 | AU19: 0 | AV19: 0 | AW19: 0 | AX19: 0 | AY19: 0 | AZ19: 0 | BA19: 0 | BB19: 1774.63 | BC19: =+VLOOKUP(C19,CF!F:F,1,0) -> 29162AA3-7A58-5440-95F4-A895F9F07441
A20: 11 | B20: 4.0 | C20: 87A23CEB-A666-5942-932C-AD91492B4A95 | F20: 06700 | G20: C66779 | H20: 16767 | I20: I - Ingreso | J20: 2025-11-03 06:33:05 | K20: 2025-11-03 06:38:06 | L20: CVD110412TF6 | M20: 601 - General de Ley Personas Morales | N20: CFS1808284P2 | O20: COMUNIDAD FELIZ SERVICIOS TI | P20: LRE2206222U5 | Q20: LOFT REVOLUCION | R20: 603 - Personas Morales con Fines no Lucrativos | S20: 22000 | T20: 81112500 - Servicios de alquiler o arrendamiento de licencias de software de computador | 81112500 - Servicios de alquiler o arrendamiento de licencias de software de computador | U20: Licencia de Software 02 de Noviembre de 2025 a 01 de Diciembre de 2025. LOFT BY | Facturación CFDI 4.0 | W20: G03 - Gastos en general | AB20: CONDICIONES | AD20: VIGENTE | AF20: CANCELABLE SIN ACEPTACIÓN | AJ20: MXN | AL20: 01 No aplica | AM20: PPD - Pago en Parcialidades o Diferido | AN20: 99 - Por definir | AO20: 0 | AP20: 677.25 | AQ20: 0 | AR20: 108.36 | AS20: 0 | AT20: 0 | AU20: 0 | AV20: 0 | AW20: 0 | AX20: 0 | AY20: 0 | AZ20: 0 | BA20: 0 | BB20: 785.61 | BC20: =+VLOOKUP(C20,CF!F:F,1,0) -> 87A23CEB-A666-5942-932C-AD91492B4A95
A21: 11 | B21: 4.0 | C21: 034EEC38-021D-53D6-B7D3-C1EC7FA40ACF | F21: 06700 | G21: C129225 | H21: 16768 | I21: I - Ingreso | J21: 2025-11-03 06:33:07 | K21: 2025-11-03 06:38:08 | L21: CVD110412TF6 | M21: 601 - General de Ley Personas Morales | N21: CFS1808284P2 | O21: COMUNIDAD FELIZ SERVICIOS TI | P21: VPF2401291U6 | Q21: VALKIRIA PFM | R21: 601 - General de Ley Personas Morales | S21: 64989 | T21: 81112500 - Servicios de alquiler o arrendamiento de licencias de software de computador | 81112500 - Servicios de alquiler o arrendamiento de licencias de software de computador | U21: Licencia de Software 03 de Noviembre de 2025 a 02 de Diciembre de 2025. Parque I | Sistema de Transferencias y Pagos 03 de Noviembre de 2025 a 02 de Diciembre de 2 | W21: G03 - Gastos en general | AB21: CONDICIONES | AD21: VIGENTE | AF21: NO CANCELABLE | AJ21: MXN | AL21: 01 No aplica | AM21: PPD - Pago en Parcialidades o Diferido | AN21: 99 - Por definir | AO21: 0 | AP21: 525 | AQ21: 0 | AR21: 84 | AS21: 0 | AT21: 0 | AU21: 0 | AV21: 0 | AW21: 0 | AX21: 0 | AY21: 0 | AZ21: 0 | BA21: 0 | BB21: 609 | BC21: =+VLOOKUP(C21,CF!F:F,1,0) -> 034EEC38-021D-53D6-B7D3-C1EC7FA40ACF
A22: 11 | B22: 4.0 | C22: 826F88E2-5100-516D-966A-E2864A62CAE2 | F22: 06700 | G22: C32781 | H22: 16769 | I22: I - Ingreso | J22: 2025-11-03 06:33:10 | K22: 2025-11-03 06:38:11 | L22: CVD110412TF6 | M22: 601 - General de Ley Personas Morales | N22: CFS1808284P2 | O22: COMUNIDAD FELIZ SERVICIOS TI | P22: FRC2001308N1 | Q22: FRACCIONAMIENTO RESIDENCIAL CAPITAL SUR | R22: 603 - Personas Morales con Fines no Lucrativos | S22: 76240 | T22: 81112500 - Servicios de alquiler o arrendamiento de licencias de software de computador | 81112500 - Servicios de alquiler o arrendamiento de licencias de software de computador | U22: Control de Acceso mes 03 de Noviembre de 2025. Fraccionamiento Residencial Capit | Licencia de Software 03 de Noviembre de 2025 a 02 de Diciembre de 2025. Fraccion | W22: G03 - Gastos en general | AB22: CONDICIONES | AD22: VIGENTE | AF22: NO CANCELABLE | AJ22: MXN | AL22: 01 No aplica | AM22: PPD - Pago en Parcialidades o Diferido | AN22: 99 - Por definir | AO22: 0 | AP22: 3479.44 | AQ22: 0 | AR22: 556.71 | AS22: 0 | AT22: 0 | AU22: 0 | AV22: 0 | AW22: 0 | AX22: 0 | AY22: 0 | AZ22: 0 | BA22: 0 | BB22: 4036.15 | BC22: =+VLOOKUP(C22,CF!F:F,1,0) -> 826F88E2-5100-516D-966A-E2864A62CAE2
A23: 11 | B23: 4.0 | C23: F279E798-063F-52FC-BD76-DDF7F711FB0A | F23: 06700 | G23: C19185 | H23: 16770 | I23: I - Ingreso | J23: 2025-11-03 06:33:12 | K23: 2025-11-03 06:38:13 | L23: CVD110412TF6 | M23: 601 - General de Ley Personas Morales | N23: CFS1808284P2 | O23: COMUNIDAD FELIZ SERVICIOS TI | P23: CAR171002QY8 | Q23: COLONOS ADAMAR RESIDENCIAL | R23: 603 - Personas Morales con Fines no Lucrativos | S23: 45650 | T23: 81112500 - Servicios de alquiler o arrendamiento de licencias de software de computador | 81112500 - Servicios de alquiler o arrendamiento de licencias de software de computador | 81112500 - Servicios de alquiler o arrendamiento de licencias de software de computador | 81112500 - Servicios de alquiler o arrendamiento de licencias de software de computador | 81112500 - Servicios de alquiler o arrendamiento de licencias de software de computador | 81112500 - Servicios de alquiler o arrendamiento de licencias de software de computador | 81112500 - Servicios de alquiler o arrendamiento de licencias de software de computador | 81112500 - Servicios de alquiler o arrendamiento de licencias de software de computador | 81112500 - Servicios de alquiler o arrendamiento de licencias de software de computador | 81112500 - Servicios de alquiler o arrendamiento de licencias de software de computador | U23: Licencia de Software 03 de Noviembre de 2025 a 02 de Diciembre de 2025. Coto Met | Licencia de Software 03 de Noviembre de 2025 a 02 de Diciembre de 2025. Coto Ala | Licencia de Software 03 de Noviembre de 2025 a 02 de Diciembre de 2025. Coto Gue | Licencia de Software 03 de Noviembre de 2025 a 02 de Diciembre de 2025. Coto Teh | Licencia de Software 03 de Noviembre de 2025 a 02 de Diciembre de 2025. Coto Mon | Licencia de Software 03 de Noviembre de 2025 a 02 de Diciembre de 2025. Coto Zap | Licencia de Software 03 de Noviembre de 2025 a 02 de Diciembre de 2025. Coto Mar | Licencia de Software 03 de Noviembre de 2025 a 02 de Diciembre de 2025. Coto Juh | Licencia de Software 03 de Noviembre de 2025 a 02 de Diciembre de 2025. Coto Alc | Licencia de Software 03 de Noviembre de 2025 a 02 de Diciembre de 2025. Coto Yuc | W23: G03 - Gastos en general | AB23: CONDICIONES | AD23: VIGENTE | AF23: CANCELABLE CON ACEPTACIÓN | AJ23: MXN | AL23: 01 No aplica | AM23: PPD - Pago en Parcialidades o Diferido | AN23: 99 - Por definir | AO23: 0 | AP23: 944.73 | AQ23: 0 | AR23: 151.17 | AS23: 0 | AT23: 0 | AU23: 0 | AV23: 0 | AW23: 0 | AX23: 0 | AY23: 0 | AZ23: 0 | BA23: 0 | BB23: 1095.9 | BC23: =+VLOOKUP(C23,CF!F:F,1,0) -> F279E798-063F-52FC-BD76-DDF7F711FB0A
A24: 11 | B24: 4.0 | C24: FB399540-E3CF-596C-8E71-02787010E8D8 | F24: 06700 | G24: C118773 | H24: 16771 | I24: I - Ingreso | J24: 2025-11-03 06:33:14 | K24: 2025-11-03 06:38:15 | L24: CVD110412TF6 | M24: 601 - General de Ley Personas Morales | N24: CFS1808284P2 | O24: COMUNIDAD FELIZ SERVICIOS TI | P24: ACV200702CZ3 | Q24: ASOCIACION CONDOMINOS VILLA DORADA | R24: 603 - Personas Morales con Fines no Lucrativos | S24: 23470 | T24: 81112500 - Servicios de alquiler o arrendamiento de licencias de software de computador | 81112500 - Servicios de alquiler o arrendamiento de licencias de software de computador | U24: Licencia de Software 03 de Noviembre de 2025 a 02 de Diciembre de 2025. ASOCIACI | Facturación CFDI 4.0 | W24: G03 - Gastos en general | AB24: CONDICIONES | AD24: VIGENTE | AF24: NO CANCELABLE | AJ24: MXN | AL24: 01 No aplica | AM24: PPD - Pago en Parcialidades o Diferido | AN24: 99 - Por definir | AO24: 0 | AP24: 1146 | AQ24: 0 | AR24: 183.36 | AS24: 0 | AT24: 0 | AU24: 0 | AV24: 0 | AW24: 0 | AX24: 0 | AY24: 0 | AZ24: 0 | BA24: 0 | BB24: 1329.36 | BC24: =+VLOOKUP(C24,CF!F:F,1,0) -> FB399540-E3CF-596C-8E71-02787010E8D8
A25: 11 | B25: 4.0 | C25: AD73C334-A037-5DD5-9B0C-4A23859FD9ED | F25: 06700 | G25: C104062 | H25: 16772 | I25: I - Ingreso | J25: 2025-11-03 06:33:16 | K25: 2025-11-03 06:38:17 | L25: CVD110412TF6 | M25: 601 - General de Ley Personas Morales | N25: CFS1808284P2 | O25: COMUNIDAD FELIZ SERVICIOS TI | P25: BAI1709011P8 | Q25: BOSQUES AILE | R25: 603 - Personas Morales con Fines no Lucrativos | S25: 52743 | T25: 81112500 - Servicios de alquiler o arrendamiento de licencias de software de computador | 81112500 - Servicios de alquiler o arrendamiento de licencias de software de computador | 81112500 - Servicios de alquiler o arrendamiento de licencias de software de computador | U25: Sistema de Transferencias y Pagos 03 de Noviembre de 2025 a 02 de Diciembre de 2 | Facturación CFDI 4.0 | Licencia de Software 03 de Noviembre de 2025 a 02 de Diciembre de 2025. Bosques | W25: G03 - Gastos en general | AB25: CONDICIONES | AD25: VIGENTE | AF25: CANCELABLE CON ACEPTACIÓN | AJ25: MXN | AL25: 01 No aplica | AM25: PPD - Pago en Parcialidades o Diferido | AN25: 99 - Por definir | AO25: 0 | AP25: 1539.99 | AQ25: 9.83 | AR25: 244.82 | AS25: 0 | AT25: 0 | AU25: 0 | AV25: 0 | AW25: 0 | AX25: 0 | AY25: 0 | AZ25: 0 | BA25: 0 | BB25: 1774.98 | BC25: =+VLOOKUP(C25,CF!F:F,1,0) -> AD73C334-A037-5DD5-9B0C-4A23859FD9ED
A26: 11 | B26: 4.0 | C26: B8447BE6-8512-55C7-9419-24E95B782898 | F26: 06700 | G26: C117938 | H26: 16773 | I26: I - Ingreso | J26: 2025-11-03 06:33:18 | K26: 2025-11-03 06:38:19 | L26: CVD110412TF6 | M26: 601 - General de Ley Personas Morales | N26: CFS1808284P2 | O26: COMUNIDAD FELIZ SERVICIOS TI | P26: PBZ220303FA5 | Q26: PRIVADA BAKTU ZA | R26: 603 - Personas Morales con Fines no Lucrativos | S26: 76269 | T26: 81112500 - Servicios de alquiler o arrendamiento de licencias de software de computador | 81112500 - Servicios de alquiler o arrendamiento de licencias de software de computador | 81112500 - Servicios de alquiler o arrendamiento de licencias de software de computador | U26: Facturación CFDI 4.0 | Licencia de Software 03 de Noviembre de 2025 a 02 de Diciembre de 2025. Bäktü Zä | Sistema de Transferencias y Pagos 03 de Noviembre de 2025 a 02 de Diciembre de 2 | W26: G03 - Gastos en general | AB26: CONDICIONES | AD26: VIGENTE | AF26: NO CANCELABLE | AJ26: MXN | AL26: 01 No aplica | AM26: PPD - Pago en Parcialidades o Diferido | AN26: 99 - Por definir | AO26: 0 | AP26: 1180 | AQ26: 0 | AR26: 188.8 | AS26: 0 | AT26: 0 | AU26: 0 | AV26: 0 | AW26: 0 | AX26: 0 | AY26: 0 | AZ26: 0 | BA26: 0 | BB26: 1368.8 | BC26: =+VLOOKUP(C26,CF!F:F,1,0) -> B8447BE6-8512-55C7-9419-24E95B782898
... A28: 11 | B28: 4.0 | C28: EEDA67CA-DB04-58E8-B7F5-007B08EC1C67 | F28: 06700 | G28: C119091 | H28: 16775 | I28: I - Ingreso | J28: 2025-11-03 06:34:02 | K28: 2025-11-03 06:39:03 | L28: CVD110412TF6 | M28: 601 - General de Ley Personas Morales | N28: CFS1808284P2 | O28: COMUNIDAD FELIZ SERVICIOS TI | P28: CZI190510EQ6 | Q28: COMUNIDAD ZIVALAM | R28: 603 - Personas Morales con Fines no Lucrativos | S28: 77516 | T28: 81112500 - Servicios de alquiler o arrendamiento de licencias de software de computador | U28: Licencia de Software 30 de Octubre de 2025 a 29 de Noviembre de 2025. Residencia | W28: G03 - Gastos en general | AB28: CONDICIONES | AD28: VIGENTE | AF28: NO CANCELABLE | AJ28: MXN | AL28: 01 No aplica | AM28: PPD - Pago en Parcialidades o Diferido | AN28: 99 - Por definir | AO28: 0 | AP28: 1027.16 | AQ28: 0 | AR28: 164.35 | AS28: 0 | AT28: 0 | AU28: 0 | AV28: 0 | AW28: 0 | AX28: 0 | AY28: 0 | AZ28: 0 | BA28: 0 | BB28: 1191.51 | BC28: =+VLOOKUP(C28,CF!F:F,1,0) -> EEDA67CA-DB04-58E8-B7F5-007B08EC1C67
A29: 11 | B29: 4.0 | C29: 96F9E1F9-D094-5AF6-832C-FEBFEEA20DDF | F29: 06700 | G29: C132762 | H29: 16776 | I29: I - Ingreso | J29: 2025-11-03 06:34:04 | K29: 2025-11-03 06:39:05 | L29: CVD110412TF6 | M29: 601 - General de Ley Personas Morales | N29: CFS1808284P2 | O29: COMUNIDAD FELIZ SERVICIOS TI | P29: XAXX010101000 | Q29: PUBLICO EN GENERAL | R29: 616 - Sin obligaciones fiscales | S29: 06700 | T29: 81112500 - Servicios de alquiler o arrendamiento de licencias de software de computador | 81112500 - Servicios de alquiler o arrendamiento de licencias de software de computador | U29: Sistema de Transferencias y Pagos 30 de Octubre de 2025 a 29 de Noviembre de 202 | Licencia de Software 30 de Octubre de 2025 a 29 de Noviembre de 2025. PRIVADAS D | W29: S01 - Sin efectos fiscales | Y29: 01 | Z29: 11 Noviembre | AA29: 2025 | AB29: CONDICIONES | AD29: VIGENTE | AF29: NO CANCELABLE | AJ29: MXN | AL29: 01 No aplica | AM29: PPD - Pago en Parcialidades o Diferido | AN29: 99 - Por definir | AO29: 0 | AP29: 2289 | AQ29: 0 | AR29: 366.24 | AS29: 0 | AT29: 0 | AU29: 0 | AV29: 0 | AW29: 0 | AX29: 0 | AY29: 0 | AZ29: 0 | BA29: 0 | BB29: 2655.24 | BC29: =+VLOOKUP(C29,CF!F:F,1,0) -> 96F9E1F9-D094-5AF6-832C-FEBFEEA20DDF
A30: 11 | B30: 4.0 | C30: 54213A26-8FB2-5034-B557-FCB7FF9257C5 | F30: 06700 | G30: C122857 | H30: 16777 | I30: I - Ingreso | J30: 2025-11-03 06:34:49 | K30: 2025-11-03 06:39:50 | L30: CVD110412TF6 | M30: 601 - General de Ley Personas Morales | N30: CFS1808284P2 | O30: COMUNIDAD FELIZ SERVICIOS TI | P30: QSO240404HN1 | Q30: QUASARX SOLUTIONS | R30: 626 - Régimen Simplificado de Confianza | S30: 06500 | T30: 81112500 - Servicios de alquiler o arrendamiento de licencias de software de computador | 81112500 - Servicios de alquiler o arrendamiento de licencias de software de computador | U30: Sistema de Transferencias y Pagos 01 de Noviembre de 2025 a 30 de Noviembre de 2 | Licencia de Software 01 de Noviembre de 2025 a 30 de Noviembre de 2025. La Quadr | W30: G03 - Gastos en general | AB30: CONDICIONES | AD30: VIGENTE | AF30: CANCELABLE CON ACEPTACIÓN | AJ30: MXN | AL30: 01 No aplica | AM30: PPD - Pago en Parcialidades o Diferido | AN30: 99 - Por definir | AO30: 0 | AP30: 2565 | AQ30: 0 | AR30: 410.4 | AS30: 0 | AT30: 0 | AU30: 0 | AV30: 0 | AW30: 0 | AX30: 0 | AY30: 0 | AZ30: 0 | BA30: 0 | BB30: 2975.4 | BC30: =+VLOOKUP(C30,CF!F:F,1,0) -> 54213A26-8FB2-5034-B557-FCB7FF9257C5
A31: 11 | B31: 4.0 | C31: CF7D568F-85F6-5F1D-8FD0-6AB40F9DF5ED | F31: 06700 | G31: C146451 | H31: 16778 | I31: I - Ingreso | J31: 2025-11-03 06:34:52 | K31: 2025-11-03 06:39:53 | L31: CVD110412TF6 | M31: 601 - General de Ley Personas Morales | N31: CFS1808284P2 | O31: COMUNIDAD FELIZ SERVICIOS TI | P31: XAXX010101000 | Q31: PUBLICO EN GENERAL | R31: 616 - Sin obligaciones fiscales | S31: 06700 | T31: 81112500 - Servicios de alquiler o arrendamiento de licencias de software de computador | 81112500 - Servicios de alquiler o arrendamiento de licencias de software de computador | U31: Licencia de Software 01 de Noviembre de 2025 a 30 de Noviembre de 2025. Condomin | Sistema de Transferencias y Pagos 01 de Noviembre de 2025 a 30 de Noviembre de 2 | W31: S01 - Sin efectos fiscales | Y31: 01 | Z31: 11 Noviembre | AA31: 2025 | AB31: CONDICIONES | AD31: VIGENTE | AF31: NO CANCELABLE | AJ31: MXN | AL31: 01 No aplica | AM31: PPD - Pago en Parcialidades o Diferido | AN31: 99 - Por definir | AO31: 0 | AP31: 1552 | AQ31: 0 | AR31: 248.32 | AS31: 0 | AT31: 0 | AU31: 0 | AV31: 0 | AW31: 0 | AX31: 0 | AY31: 0 | AZ31: 0 | BA31: 0 | BB31: 1800.32 | BC31: =+VLOOKUP(C31,CF!F:F,1,0) -> CF7D568F-85F6-5F1D-8FD0-6AB40F9DF5ED
A32: 11 | B32: 4.0 | C32: 81FA006B-90DC-511B-83E3-C49BB205628A | F32: 06700 | G32: C118581 | H32: 16779 | I32: I - Ingreso | J32: 2025-11-03 06:34:54 | K32: 2025-11-03 06:39:55 | L32: CVD110412TF6 | M32: 601 - General de Ley Personas Morales | N32: CFS1808284P2 | O32: COMUNIDAD FELIZ SERVICIOS TI | P32: MEET72111875A | Q32: TOXCATL RICARDO MEJIA ESTRADA | R32: 626 - Régimen Simplificado de Confianza | S32: 54170 | T32: 81112500 - Servicios de alquiler o arrendamiento de licencias de software de computador | 81112500 - Servicios de alquiler o arrendamiento de licencias de software de computador | U32: Licencia de Software 01 de Noviembre de 2025 a 30 de Noviembre de 2025. Fraccion | Sistema de Transferencias y Pagos 01 de Noviembre de 2025 a 30 de Noviembre de 2 | W32: G03 - Gastos en general | AB32: CONDICIONES | AD32: VIGENTE | AF32: NO CANCELABLE | AJ32: MXN | AL32: 01 No aplica | AM32: PPD - Pago en Parcialidades o Diferido | AN32: 99 - Por definir | AO32: 0 | AP32: 1722 | AQ32: 0 | AR32: 275.52 | AS32: 0 | AT32: 0 | AU32: 0 | AV32: 0 | AW32: 0 | AX32: 0 | AY32: 0 | AZ32: 0 | BA32: 0 | BB32: 1997.52 | BC32: =+VLOOKUP(C32,CF!F:F,1,0) -> 81FA006B-90DC-511B-83E3-C49BB205628A
A33: 11 | B33: 4.0 | C33: AF1A4C94-6D67-51A4-A670-DDD6F38D8849 | F33: 06700 | G33: C117516 | H33: 16780 | I33: I - Ingreso | J33: 2025-11-03 06:34:56 | K33: 2025-11-03 06:39:57 | L33: CVD110412TF6 | M33: 601 - General de Ley Personas Morales | N33: CFS1808284P2 | O33: COMUNIDAD FELIZ SERVICIOS TI | P33: APR2206145N1 | Q33: ASOCIACION DE PROPIETARIOS Y RESIDENTES DE VILLAS DEL SUR 3 | R33: 603 - Personas Morales con Fines no Lucrativos | S33: 58095 | T33: 81112500 - Servicios de alquiler o arrendamiento de licencias de software de computador | 81112500 - Servicios de alquiler o arrendamiento de licencias de software de computador | U33: Sistema de Transferencias y Pagos 01 de Noviembre de 2025 a 30 de Noviembre de 2 | Licencia de Software 01 de Noviembre de 2025 a 30 de Noviembre de 2025. Villas d | W33: G03 - Gastos en general | AB33: CONDICIONES | AD33: VIGENTE | AF33: CANCELABLE CON ACEPTACIÓN | AJ33: MXN | AL33: 01 No aplica | AM33: PPD - Pago en Parcialidades o Diferido | AN33: 99 - Por definir | AO33: 0 | AP33: 2860.68 | AQ33: 0 | AR33: 457.7 | AS33: 0 | AT33: 0 | AU33: 0 | AV33: 0 | AW33: 0 | AX33: 0 | AY33: 0 | AZ33: 0 | BA33: 0 | BB33: 3318.38 | BC33: =+VLOOKUP(C33,CF!F:F,1,0) -> AF1A4C94-6D67-51A4-A670-DDD6F38D8849
A34: 11 | B34: 4.0 | C34: 1997F006-9CD1-561E-855A-A9EDB20DFA99 | F34: 06700 | G34: C87958 | H34: 16781 | I34: I - Ingreso | J34: 2025-11-03 06:34:58 | K34: 2025-11-03 06:39:59 | L34: CVD110412TF6 | M34: 601 - General de Ley Personas Morales | N34: CFS1808284P2 | O34: COMUNIDAD FELIZ SERVICIOS TI | P34: ACC201008E56 | Q34: ASOCIACION DE CONDOMINOS CORONADO | R34: 603 - Personas Morales con Fines no Lucrativos | S34: 23456 | T34: 81112500 - Servicios de alquiler o arrendamiento de licencias de software de computador | 81112500 - Servicios de alquiler o arrendamiento de licencias de software de computador | U34: Sistema de Transferencias y Pagos 01 de Noviembre de 2025 a 30 de Noviembre de 2 | Licencia de Software 01 de Noviembre de 2025 a 30 de Noviembre de 2025. Asociaci | W34: G03 - Gastos en general | AB34: CONDICIONES | AD34: VIGENTE | AF34: CANCELABLE CON ACEPTACIÓN | AJ34: MXN | AL34: 01 No aplica | AM34: PPD - Pago en Parcialidades o Diferido | AN34: 99 - Por definir | AO34: 0 | AP34: 1520 | AQ34: 0 | AR34: 243.2 | AS34: 0 | AT34: 0 | AU34: 0 | AV34: 0 | AW34: 0 | AX34: 0 | AY34: 0 | AZ34: 0 | BA34: 0 | BB34: 1763.2 | BC34: =+VLOOKUP(C34,CF!F:F,1,0) -> 1997F006-9CD1-561E-855A-A9EDB20DFA99
A35: 11 | B35: 4.0 | C35: 05826921-5E3E-5805-BEC0-669263D18065 | F35: 06700 | G35: C116604 | H35: 16782 | I35: I - Ingreso | J35: 2025-11-03 06:35:00 | K35: 2025-11-03 06:40:01 | L35: CVD110412TF6 | M35: 601 - General de Ley Personas Morales | N35: CFS1808284P2 | O35: COMUNIDAD FELIZ SERVICIOS TI | P35: XAXX010101000 | Q35: PUBLICO EN GENERAL | R35: 616 - Sin obligaciones fiscales | S35: 06700 | T35: 81112500 - Servicios de alquiler o arrendamiento de licencias de software de computador | 81112500 - Servicios de alquiler o arrendamiento de licencias de software de computador | U35: Licencia de Software 01 de Noviembre de 2025 a 30 de Noviembre de 2025. DK52 | Sistema de Transferencias y Pagos 01 de Noviembre de 2025 a 30 de Noviembre de 2 | W35: S01 - Sin efectos fiscales | Y35: 01 | Z35: 11 Noviembre | AA35: 2025 | AB35: CONDICIONES | AD35: VIGENTE | AF35: CANCELABLE SIN ACEPTACIÓN | AJ35: MXN | AL35: 01 No aplica | AM35: PPD - Pago en Parcialidades o Diferido | AN35: 99 - Por definir | AO35: 0 | AP35: 1368.1 | AQ35: 0 | AR35: 218.9 | AS35: 0 | AT35: 0 | AU35: 0 | AV35: 0 | AW35: 0 | AX35: 0 | AY35: 0 | AZ35: 0 | BA35: 0 | BB35: 1587 | BC35: =+VLOOKUP(C35,CF!F:F,1,0) -> 05826921-5E3E-5805-BEC0-669263D18065
A36: 11 | B36: 4.0 | C36: 58A4BCD6-FCEB-59DA-BE0E-D0AFAD37A00F | F36: 06700 | G36: C143910 | H36: 16783 | I36: I - Ingreso | J36: 2025-11-03 06:35:02 | K36: 2025-11-03 06:40:03 | L36: CVD110412TF6 | M36: 601 - General de Ley Personas Morales | N36: CFS1808284P2 | O36: COMUNIDAD FELIZ SERVICIOS TI | P36: AABX750519561 | Q36: XOCHITL BERENICE AYALA BARAJAS | R36: 626 - Régimen Simplificado de Confianza | S36: 82124 | T36: 81112500 - Servicios de alquiler o arrendamiento de licencias de software de computador | 81112500 - Servicios de alquiler o arrendamiento de licencias de software de computador | 81112500 - Servicios de alquiler o arrendamiento de licencias de software de computador | 81112500 - Servicios de alquiler o arrendamiento de licencias de software de computador | 81112500 - Servicios de alquiler o arrendamiento de licencias de software de computador | 81112500 - Servicios de alquiler o arrendamiento de licencias de software de computador | U36: Licencia de Software 01 de Noviembre de 2025 a 30 de Noviembre de 2025. Villa Vi | Sistema de Transferencias y Pagos 01 de Noviembre de 2025 a 30 de Noviembre de 2 | Licencia de Software 01 de Noviembre de 2025 a 30 de Noviembre de 2025. GRAN MAR | Sistema de Transferencias y Pagos 01 de Noviembre de 2025 a 30 de Noviembre de 2 | Sistema de Transferencias y Pagos 01 de Noviembre de 2025 a 30 de Noviembre de 2 | Licencia de Software 01 de Noviembre de 2025 a 30 de Noviembre de 2025. LA OSTRA | W36: G03 - Gastos en general | AB36: CONDICIONES | AD36: VIGENTE | AF36: CANCELABLE CON ACEPTACIÓN | AJ36: MXN | AL36: 01 No aplica | AM36: PPD - Pago en Parcialidades o Diferido | AN36: 99 - Por definir | AO36: 0 | AP36: 1659 | AQ36: 0 | AR36: 265.44 | AS36: 0 | AT36: 0 | AU36: 0 | AV36: 0 | AW36: 0 | AX36: 0 | AY36: 0 | AZ36: 0 | BA36: 0 | BB36: 1924.44 | BC36: =+VLOOKUP(C36,CF!F:F,1,0) -> 58A4BCD6-FCEB-59DA-BE0E-D0AFAD37A00F
A37: 11 | B37: 4.0 | C37: 3B9F515C-D57A-5FE4-BDF1-CC162AE19536 | F37: 06700 | G37: C151270 | H37: 16784 | I37: I - Ingreso | J37: 2025-11-03 06:35:23 | K37: 2025-11-03 06:40:24 | L37: CVD110412TF6 | M37: 601 - General de Ley Personas Morales | N37: CFS1808284P2 | O37: COMUNIDAD FELIZ SERVICIOS TI | P37: LUBC891120EN3 | Q37: CRISTOBAL LUDLOW BOSCH | R37: 612 - Personas Físicas con Actividades Empresariales y Profesionales | S37: 05000 | T37: 81112500 - Servicios de alquiler o arrendamiento de licencias de software de computador | U37: Licencia de Software 31 de Octubre de 2025 a 30 de Noviembre de 2025. Temistocle | W37: G03 - Gastos en general | AB37: CONDICIONES | AD37: VIGENTE | AF37: NO CANCELABLE | AJ37: MXN | AL37: 01 No aplica | AM37: PPD - Pago en Parcialidades o Diferido | AN37: 99 - Por definir | AO37: 0 | AP37: 25.86 | AQ37: 0 | AR37: 4.14 | AS37: 0 | AT37: 0 | AU37: 0 | AV37: 0 | AW37: 0 | AX37: 0 | AY37: 0 | AZ37: 0 | BA37: 0 | BB37: 30 | BC37: =+VLOOKUP(C37,CF!F:F,1,0) -> 3B9F515C-D57A-5FE4-BDF1-CC162AE19536
A38: 11 | B38: 4.0 | C38: F382DF82-B277-554A-826C-F3A91F0EDD74 | F38: 06700 | G38: C96911 | H38: 16785 | I38: I - Ingreso | J38: 2025-11-03 06:35:44 | K38: 2025-11-03 06:40:45 | L38: CVD110412TF6 | M38: 601 - General de Ley Personas Morales | N38: CFS1808284P2 | O38: COMUNIDAD FELIZ SERVICIOS TI | P38: SSC220401788 | Q38: SS SERVICIOS DEL CENTRO MEXICO | R38: 626 - Régimen Simplificado de Confianza | S38: 76146 | T38: 81112500 - Servicios de alquiler o arrendamiento de licencias de software de computador | U38: Licencia de Software 01 de Noviembre de 2025 a 30 de Noviembre de 2025. NATURA I | W38: G03 - Gastos en general | AB38: CONDICIONES | AD38: VIGENTE | AF38: CANCELABLE CON ACEPTACIÓN | AJ38: MXN | AL38: 01 No aplica | AM38: PPD - Pago en Parcialidades o Diferido | AN38: 99 - Por definir | AO38: 0 | AP38: 1106.47 | AQ38: 0 | AR38: 177.04 | AS38: 0 | AT38: 0 | AU38: 0 | AV38: 0 | AW38: 0 | AX38: 0 | AY38: 0 | AZ38: 0 | BA38: 0 | BB38: 1283.51 | BC38: =+VLOOKUP(C38,CF!F:F,1,0) -> F382DF82-B277-554A-826C-F3A91F0EDD74
A39: 11 | B39: 4.0 | C39: D7429872-5BB5-5A0F-99CF-447C19139BEF | F39: 06700 | G39: C122922 | H39: 16786 | I39: I - Ingreso | J39: 2025-11-03 06:35:46 | K39: 2025-11-03 06:40:47 | L39: CVD110412TF6 | M39: 601 - General de Ley Personas Morales | N39: CFS1808284P2 | O39: COMUNIDAD FELIZ SERVICIOS TI | P39: PETV5905211U4 | Q39: VIRGINIA PEÑA TENORIO | R39: 626 - Régimen Simplificado de Confianza | S39: 03100 | T39: 81112500 - Servicios de alquiler o arrendamiento de licencias de software de computador | U39: Licencia de Software 01 de Noviembre de 2025 a 30 de Noviembre de 2025. ZACAHUIT | W39: G03 - Gastos en general | AB39: CONDICIONES | AD39: VIGENTE | AF39: CANCELABLE SIN ACEPTACIÓN | AJ39: MXN | AL39: 01 No aplica | AM39: PPD - Pago en Parcialidades o Diferido | AN39: 99 - Por definir | AO39: 0 | AP39: 600 | AQ39: 0 | AR39: 96 | AS39: 0 | AT39: 0 | AU39: 0 | AV39: 0 | AW39: 0 | AX39: 0 | AY39: 0 | AZ39: 0 | BA39: 0 | BB39: 696 | BC39: Anular
A40: 11 | B40: 4.0 | C40: 73975EAB-03D6-54C1-8F47-11443EE5A04B | F40: 06700 | G40: C117678 | H40: 16787 | I40: I - Ingreso | J40: 2025-11-03 06:35:49 | K40: 2025-11-03 06:40:49 | L40: CVD110412TF6 | M40: 601 - General de Ley Personas Morales | N40: CFS1808284P2 | O40: COMUNIDAD FELIZ SERVICIOS TI | P40: ACR23082912A | Q40: ADMINISTRACION DEL CONDOMINIO RESIDENCIAL LAGO ALBERTO 369 | R40: 603 - Personas Morales con Fines no Lucrativos | S40: 11320 | T40: 81112500 - Servicios de alquiler o arrendamiento de licencias de software de computador | U40: Licencia de Software 01 de Noviembre de 2025 a 30 de Noviembre de 2025. Polanco | W40: G03 - Gastos en general | AB40: CONDICIONES | AD40: VIGENTE | AF40: CANCELABLE SIN ACEPTACIÓN | AJ40: MXN | AL40: 01 No aplica | AM40: PPD - Pago en Parcialidades o Diferido | AN40: 99 - Por definir | AO40: 0 | AP40: 623 | AQ40: 0 | AR40: 99.68 | AS40: 0 | AT40: 0 | AU40: 0 | AV40: 0 | AW40: 0 | AX40: 0 | AY40: 0 | AZ40: 0 | BA40: 0 | BB40: 722.68 | BC40: =+VLOOKUP(C40,CF!F:F,1,0) -> 73975EAB-03D6-54C1-8F47-11443EE5A04B
A41: 11 | B41: 4.0 | C41: A81AABF0-BA60-5E3F-A7A1-37815EB71683 | F41: 06700 | G41: C72750 | H41: 16788 | I41: I - Ingreso | J41: 2025-11-03 06:35:51 | K41: 2025-11-03 06:40:52 | L41: CVD110412TF6 | M41: 601 - General de Ley Personas Morales | N41: CFS1808284P2 | O41: COMUNIDAD FELIZ SERVICIOS TI | P41: XAXX010101000 | Q41: PUBLICO EN GENERAL | R41: 616 - Sin obligaciones fiscales | S41: 06700 | T41: 81112500 - Servicios de alquiler o arrendamiento de licencias de software de computador | U41: Licencia de Software 01 de Noviembre de 2025 a 30 de Noviembre de 2025. Mirage I | W41: S01 - Sin efectos fiscales | Y41: 01 | Z41: 11 Noviembre | AA41: 2025 | AB41: CONDICIONES | AD41: VIGENTE | AF41: NO CANCELABLE | AJ41: MXN | AL41: 01 No aplica | AM41: PPD - Pago en Parcialidades o Diferido | AN41: 99 - Por definir | AO41: 0 | AP41: 700 | AQ41: 0 | AR41: 112 | AS41: 0 | AT41: 0 | AU41: 0 | AV41: 0 | AW41: 0 | AX41: 0 | AY41: 0 | AZ41: 0 | BA41: 0 | BB41: 812 | BC41: =+VLOOKUP(C41,CF!F:F,1,0) -> A81AABF0-BA60-5E3F-A7A1-37815EB71683
A42: 11 | B42: 4.0 | C42: 72A80F24-5839-51D0-8DD1-5AEA5D2DB3BD | F42: 06700 | G42: C56926 | H42: 16789 | I42: I - Ingreso | J42: 2025-11-03 06:35:53 | K42: 2025-11-03 06:40:54 | L42: CVD110412TF6 | M42: 601 - General de Ley Personas Morales | N42: CFS1808284P2 | O42: COMUNIDAD FELIZ SERVICIOS TI | P42: ACV130419L90 | Q42: ASOCIACION CIVIL DE VECINOS UNIDOS POR LOS ALMENDROS DE TIZAYUCA | R42: 603 - Personas Morales con Fines no Lucrativos | S42: 43803 | T42: 81112500 - Servicios de alquiler o arrendamiento de licencias de software de computador | U42: Licencia de Software 01 de Noviembre de 2025 a 30 de Noviembre de 2025. Residenc | W42: G03 - Gastos en general | AB42: CONDICIONES | AD42: VIGENTE | AF42: CANCELABLE CON ACEPTACIÓN | AJ42: MXN | AL42: 01 No aplica | AM42: PPD - Pago en Parcialidades o Diferido | AN42: 99 - Por definir | AO42: 0 | AP42: 1673 | AQ42: 0 | AR42: 267.68 | AS42: 0 | AT42: 0 | AU42: 0 | AV42: 0 | AW42: 0 | AX42: 0 | AY42: 0 | AZ42: 0 | BA42: 0 | BB42: 1940.68 | BC42: =+VLOOKUP(C42,CF!F:F,1,0) -> 72A80F24-5839-51D0-8DD1-5AEA5D2DB3BD
A43: 11 | B43: 4.0 | C43: 9026BA63-7662-559C-BEDA-938A6DEB2095 | F43: 06700 | G43: C116179 | H43: 16790 | I43: I - Ingreso | J43: 2025-11-03 06:35:55 | K43: 2025-11-03 06:40:56 | L43: CVD110412TF6 | M43: 601 - General de Ley Personas Morales | N43: CFS1808284P2 | O43: COMUNIDAD FELIZ SERVICIOS TI | P43: RPE960507UQ7 | Q43: ROBOTICA Y PERIFERICOS | R43: 601 - General de Ley Personas Morales | S43: 03400 | T43: 81112500 - Servicios de alquiler o arrendamiento de licencias de software de computador | 81112500 - Servicios de alquiler o arrendamiento de licencias de software de computador | U43: Licencia de Software 01 de Noviembre de 2025 a 30 de Noviembre de 2025. PIRINEOS | Licencia de Software 01 de Noviembre de 2025 a 30 de Noviembre de 2025. Condomin | W43: G03 - Gastos en general | AB43: CONDICIONES | AD43: VIGENTE | AF43: CANCELABLE SIN ACEPTACIÓN | AJ43: MXN | AL43: 01 No aplica | AM43: PPD - Pago en Parcialidades o Diferido | AN43: 99 - Por definir | AO43: 0 | AP43: 533.41 | AQ43: 0 | AR43: 85.35 | AS43: 0 | AT43: 0 | AU43: 0 | AV43: 0 | AW43: 0 | AX43: 0 | AY43: 0 | AZ43: 0 | BA43: 0 | BB43: 618.76 | BC43: =+VLOOKUP(C43,CF!F:F,1,0) -> 9026BA63-7662-559C-BEDA-938A6DEB2095
A44: 11 | B44: 4.0 | C44: 19270D5A-2B35-5E4C-9292-139B4498BAD9 | F44: 06700 | G44: C116845 | H44: 16792 | I44: I - Ingreso | J44: 2025-11-03 06:35:59 | K44: 2025-11-03 06:41:00 | L44: CVD110412TF6 | M44: 601 - General de Ley Personas Morales | N44: CFS1808284P2 | O44: COMUNIDAD FELIZ SERVICIOS TI | P44: DMI210113T87 | Q44: DESARROLLOS MISTICOS | R44: 601 - General de Ley Personas Morales | S44: 77600 | T44: 81112500 - Servicios de alquiler o arrendamiento de licencias de software de computador | U44: Licencia de Software 01 de Noviembre de 2025 a 30 de Noviembre de 2025. Athimar | W44: G03 - Gastos en general | AB44: CONDICIONES | AD44: VIGENTE | AF44: CANCELABLE CON ACEPTACIÓN | AJ44: MXN | AL44: 01 No aplica | AM44: PPD - Pago en Parcialidades o Diferido | AN44: 99 - Por definir | AO44: 0 | AP44: 1000 | AQ44: 0 | AR44: 160 | AS44: 0 | AT44: 0 | AU44: 0 | AV44: 0 | AW44: 0 | AX44: 0 | AY44: 0 | AZ44: 0 | BA44: 0 | BB44: 1160 | BC44: =+VLOOKUP(C44,CF!F:F,1,0) -> 19270D5A-2B35-5E4C-9292-139B4498BAD9
A45: 11 | B45: 4.0 | C45: BD62546E-F77E-5407-B0E9-080F2028965F | F45: 06700 | G45: C103468 | H45: 16794 | I45: I - Ingreso | J45: 2025-11-03 06:36:04 | K45: 2025-11-03 06:41:04 | L45: CVD110412TF6 | M45: 601 - General de Ley Personas Morales | N45: CFS1808284P2 | O45: COMUNIDAD FELIZ SERVICIOS TI | P45: AZE2207192M5 | Q45: AZENT | R45: 603 - Personas Morales con Fines no Lucrativos | S45: 45019 | T45: 81112500 - Servicios de alquiler o arrendamiento de licencias de software de computador | U45: Licencia de Software 01 de Noviembre de 2025 a 30 de Noviembre de 2025. Condomin | W45: G03 - Gastos en general | AB45: CONDICIONES | AD45: VIGENTE | AF45: CANCELABLE SIN ACEPTACIÓN | AJ45: MXN | AL45: 01 No aplica | AM45: PPD - Pago en Parcialidades o Diferido | AN45: 99 - Por definir | AO45: 0 | AP45: 480 | AQ45: 0 | AR45: 76.8 | AS45: 0 | AT45: 0 | AU45: 0 | AV45: 0 | AW45: 0 | AX45: 0 | AY45: 0 | AZ45: 0 | BA45: 0 | BB45: 556.8 | BC45: =+VLOOKUP(C45,CF!F:F,1,0) -> BD62546E-F77E-5407-B0E9-080F2028965F
A46: 11 | B46: 4.0 | C46: 9AB843A1-C3F5-5F7D-9029-FE4F4A859A40 | F46: 06700 | G46: C140988 | H46: 16795 | I46: I - Ingreso | J46: 2025-11-03 06:36:06 | K46: 2025-11-03 06:41:06 | L46: CVD110412TF6 | M46: 601 - General de Ley Personas Morales | N46: CFS1808284P2 | O46: COMUNIDAD FELIZ SERVICIOS TI | P46: XAXX010101000 | Q46: PUBLICO EN GENERAL | R46: 616 - Sin obligaciones fiscales | S46: 06700 | T46: 81112500 - Servicios de alquiler o arrendamiento de licencias de software de computador | U46: Licencia de Software 01 de Noviembre de 2025 a 30 de Noviembre de 2025. Tu Espac | W46: S01 - Sin efectos fiscales | Y46: 01 | Z46: 11 Noviembre | AA46: 2025 | AB46: CONDICIONES | AD46: VIGENTE | AF46: CANCELABLE SIN ACEPTACIÓN | AJ46: MXN | AL46: 01 No aplica | AM46: PPD - Pago en Parcialidades o Diferido | AN46: 99 - Por definir | AO46: 0 | AP46: 2596.04 | AQ46: 0 | AR46: 415.37 | AS46: 0 | AT46: 0 | AU46: 0 | AV46: 0 | AW46: 0 | AX46: 0 | AY46: 0 | AZ46: 0 | BA46: 0 | BB46: 3011.41 | BC46: =+VLOOKUP(C46,CF!F:F,1,0) -> 9AB843A1-C3F5-5F7D-9029-FE4F4A859A40
A47: 11 | B47: 4.0 | C47: 25C130E4-B23C-53D6-992A-A247D00A8B2E | F47: 06700 | G47: C131419 | H47: 16796 | I47: I - Ingreso | J47: 2025-11-03 06:36:08 | K47: 2025-11-03 06:41:08 | L47: CVD110412TF6 | M47: 601 - General de Ley Personas Morales | N47: CFS1808284P2 | O47: COMUNIDAD FELIZ SERVICIOS TI | P47: GUEJ771107DY6 | Q47: JORGE ANTONIO GUILLERMO ESQUERRA | R47: 612 - Personas Físicas con Actividades Empresariales y Profesionales | S47: 01480 | T47: 81112500 - Servicios de alquiler o arrendamiento de licencias de software de computador | 81112500 - Servicios de alquiler o arrendamiento de licencias de software de computador | U47: Licencia de Software 01 de Noviembre de 2025 a 30 de Noviembre de 2025. EL Jardí | Licencia de Software 01 de Noviembre de 2025 a 30 de Noviembre de 2025. Amealco | W47: G03 - Gastos en general | AB47: CONDICIONES | AD47: VIGENTE | AF47: CANCELABLE SIN ACEPTACIÓN | AJ47: MXN | AL47: 01 No aplica | AM47: PPD - Pago en Parcialidades o Diferido | AN47: 99 - Por definir | AO47: 0 | AP47: 500.48 | AQ47: 0 | AR47: 80.08 | AS47: 0 | AT47: 0 | AU47: 0 | AV47: 0 | AW47: 0 | AX47: 0 | AY47: 0 | AZ47: 0 | BA47: 0 | BB47: 580.56 | BC47: =+VLOOKUP(C47,CF!F:F,1,0) -> 25C130E4-B23C-53D6-992A-A247D00A8B2E
A48: 11 | B48: 4.0 | C48: 9F5E60E2-A55C-5666-8BD7-BE82FBBB4943 | F48: 06700 | G48: C79146 | H48: 16797 | I48: I - Ingreso | J48: 2025-11-03 06:36:34 | K48: 2025-11-03 06:41:35 | L48: CVD110412TF6 | M48: 601 - General de Ley Personas Morales | N48: CFS1808284P2 | O48: COMUNIDAD FELIZ SERVICIOS TI | P48: XAXX010101000 | Q48: PUBLICO EN GENERAL | R48: 616 - Sin obligaciones fiscales | S48: 06700 | T48: 81112500 - Servicios de alquiler o arrendamiento de licencias de software de computador | U48: Licencia de Software 01 de Noviembre de 2025 a 31 de Octubre de 2026. Quinta Gua | W48: S01 - Sin efectos fiscales | Y48: 01 | Z48: 11 Noviembre | AA48: 2025 | AB48: CONDICIONES | AD48: VIGENTE | AF48: NO CANCELABLE | AJ48: MXN | AL48: 01 No aplica | AM48: PPD - Pago en Parcialidades o Diferido | AN48: 99 - Por definir | AO48: 0 | AP48: 10000 | AQ48: 0 | AR48: 1600 | AS48: 0 | AT48: 0 | AU48: 0 | AV48: 0 | AW48: 0 | AX48: 0 | AY48: 0 | AZ48: 0 | BA48: 0 | BB48: 11600 | BC48: =+VLOOKUP(C48,CF!F:F,1,0) -> 9F5E60E2-A55C-5666-8BD7-BE82FBBB4943
A49: 11 | B49: 4.0 | C49: C1F9E074-6DDE-52D8-9866-607F36CDA4CC | F49: 06700 | G49: C139422 | H49: 16798 | I49: I - Ingreso | J49: 2025-11-03 06:37:01 | K49: 2025-11-03 06:42:02 | L49: CVD110412TF6 | M49: 601 - General de Ley Personas Morales | N49: CFS1808284P2 | O49: COMUNIDAD FELIZ SERVICIOS TI | P49: TABA700811S24 | Q49: ABRAHAM ANDRES TAMARIZ BARROETA | R49: 612 - Personas Físicas con Actividades Empresariales y Profesionales | S49: 07000 | T49: 81112500 - Servicios de alquiler o arrendamiento de licencias de software de computador | 81112500 - Servicios de alquiler o arrendamiento de licencias de software de computador | U49: Sistema de Transferencias y Pagos 02 de Noviembre de 2025 a 01 de Diciembre de 2 | Licencia de Software 02 de Noviembre de 2025 a 01 de Diciembre de 2025. ASOCIACI | W49: G03 - Gastos en general | AB49: CONDICIONES | AD49: VIGENTE | AF49: CANCELABLE CON ACEPTACIÓN | AJ49: MXN | AL49: 01 No aplica | AM49: PPD - Pago en Parcialidades o Diferido | AN49: 99 - Por definir | AO49: 0 | AP49: 1680 | AQ49: 0 | AR49: 268.8 | AS49: 0 | AT49: 0 | AU49: 0 | AV49: 0 | AW49: 0 | AX49: 0 | AY49: 0 | AZ49: 0 | BA49: 0 | BB49: 1948.8 | BC49: Anular
A50: 11 | B50: 4.0 | C50: FA936785-EFC2-5564-82B0-1265E9B67387 | F50: 06700 | G50: C115867 | H50: 16799 | I50: I - Ingreso | J50: 2025-11-03 06:37:04 | K50: 2025-11-03 06:42:05 | L50: CVD110412TF6 | M50: 601 - General de Ley Personas Morales | N50: CFS1808284P2 | O50: COMUNIDAD FELIZ SERVICIOS TI | P50: XAXX010101000 | Q50: PUBLICO EN GENERAL | R50: 616 - Sin obligaciones fiscales | S50: 06700 | T50: 81112500 - Servicios de alquiler o arrendamiento de licencias de software de computador | 81112500 - Servicios de alquiler o arrendamiento de licencias de software de computador | U50: Licencia de Software 02 de Noviembre de 2025 a 01 de Diciembre de 2025. ALTOS AT | Sistema de Transferencias y Pagos 02 de Noviembre de 2025 a 01 de Diciembre de 2 | W50: S01 - Sin efectos fiscales | Y50: 01 | Z50: 11 Noviembre | AA50: 2025 | AB50: CONDICIONES | AD50: VIGENTE | AF50: CANCELABLE SIN ACEPTACIÓN | AJ50: MXN | AL50: 01 No aplica | AM50: PPD - Pago en Parcialidades o Diferido | AN50: 99 - Por definir | AO50: 0 | AP50: 1839.66 | AQ50: 0 | AR50: 294.35 | AS50: 0 | AT50: 0 | AU50: 0 | AV50: 0 | AW50: 0 | AX50: 0 | AY50: 0 | AZ50: 0 | BA50: 0 | BB50: 2134.01 | BC50: =+VLOOKUP(C50,CF!F:F,1,0) -> FA936785-EFC2-5564-82B0-1265E9B67387
A51: 11 | B51: 4.0 | C51: 7945DE06-5391-5111-84A5-B03C00EED5CB | F51: 06700 | G51: C133648 | H51: 16800 | I51: I - Ingreso | J51: 2025-11-03 06:37:06 | K51: 2025-11-03 06:42:07 | L51: CVD110412TF6 | M51: 601 - General de Ley Personas Morales | N51: CFS1808284P2 | O51: COMUNIDAD FELIZ SERVICIOS TI | P51: XAXX010101000 | Q51: PUBLICO EN GENERAL | R51: 616 - Sin obligaciones fiscales | S51: 06700 | T51: 81112500 - Servicios de alquiler o arrendamiento de licencias de software de computador | 81112500 - Servicios de alquiler o arrendamiento de licencias de software de computador | U51: Licencia de Software 02 de Noviembre de 2025 a 01 de Diciembre de 2025. BOCA CHI | Sistema de Transferencias y Pagos 02 de Noviembre de 2025 a 01 de Diciembre de 2 | W51: S01 - Sin efectos fiscales | Y51: 01 | Z51: 11 Noviembre | AA51: 2025 | AB51: CONDICIONES | AD51: VIGENTE | AF51: CANCELABLE SIN ACEPTACIÓN | AJ51: MXN | AL51: 01 No aplica | AM51: PPD - Pago en Parcialidades o Diferido | AN51: 99 - Por definir | AO51: 0 | AP51: 1680 | AQ51: 0 | AR51: 268.8 | AS51: 0 | AT51: 0 | AU51: 0 | AV51: 0 | AW51: 0 | AX51: 0 | AY51: 0 | AZ51: 0 | BA51: 0 | BB51: 1948.8 | BC51: =+VLOOKUP(C51,CF!F:F,1,0) -> 7945DE06-5391-5111-84A5-B03C00EED5CB
A52: 11 | B52: 4.0 | C52: 1A0DAB75-AC65-5CCB-8944-7A31BF856918 | F52: 06700 | G52: C128169 | H52: 16801 | I52: I - Ingreso | J52: 2025-11-03 06:37:08 | K52: 2025-11-03 06:42:09 | L52: CVD110412TF6 | M52: 601 - General de Ley Personas Morales | N52: CFS1808284P2 | O52: COMUNIDAD FELIZ SERVICIOS TI | P52: SST2310239W5 | Q52: SEREMONIA SELVA TULUM | R52: 603 - Personas Morales con Fines no Lucrativos | S52: 77760 | T52: 81112500 - Servicios de alquiler o arrendamiento de licencias de software de computador | 81112500 - Servicios de alquiler o arrendamiento de licencias de software de computador | 81112500 - Servicios de alquiler o arrendamiento de licencias de software de computador | U52: Licencia de Software 02 de Noviembre de 2025 a 01 de Diciembre de 2025. Seremoni | Sistema de Transferencias y Pagos 02 de Noviembre de 2025 a 01 de Diciembre de 2 | Swappi 02 de Noviembre de 2025 a 01 de Diciembre de 2025. Seremonia Selva Tulum | W52: G03 - Gastos en general | AB52: CONDICIONES | AD52: VIGENTE | AF52: CANCELABLE CON ACEPTACIÓN | AJ52: MXN | AL52: 01 No aplica | AM52: PPD - Pago en Parcialidades o Diferido | AN52: 99 - Por definir | AO52: 0 | AP52: 2496 | AQ52: 0 | AR52: 399.36 | AS52: 0 | AT52: 0 | AU52: 0 | AV52: 0 | AW52: 0 | AX52: 0 | AY52: 0 | AZ52: 0 | BA52: 0 | BB52: 2895.36 | BC52: =+VLOOKUP(C52,CF!F:F,1,0) -> 1A0DAB75-AC65-5CCB-8944-7A31BF856918
A53: 11 | B53: 4.0 | C53: 5D8D3D4D-D763-5DC4-A712-EAAEE61561F9 | F53: 06700 | G53: C153051 | H53: 16802 | I53: I - Ingreso | J53: 2025-11-03 06:37:10 | K53: 2025-11-03 06:42:11 | L53: CVD110412TF6 | M53: 601 - General de Ley Personas Morales | N53: CFS1808284P2 | O53: COMUNIDAD FELIZ SERVICIOS TI | P53: XAXX010101000 | Q53: PUBLICO EN GENERAL | R53: 616 - Sin obligaciones fiscales | S53: 06700 | T53: 81112500 - Servicios de alquiler o arrendamiento de licencias de software de computador | 81112500 - Servicios de alquiler o arrendamiento de licencias de software de computador | U53: Licencia de Software 02 de Noviembre de 2025 a 01 de Diciembre de 2025. CONJUNTO | Sistema de Transferencias y Pagos 02 de Noviembre de 2025 a 01 de Diciembre de 2 | W53: S01 - Sin efectos fiscales | Y53: 01 | Z53: 11 Noviembre | AA53: 2025 | AB53: CONDICIONES | AD53: VIGENTE | AF53: CANCELABLE SIN ACEPTACIÓN | AJ53: MXN | AL53: 01 No aplica | AM53: PPD - Pago en Parcialidades o Diferido | AN53: 99 - Por definir | AO53: 0 | AP53: 4788 | AQ53: 0 | AR53: 766.08 | AS53: 0 | AT53: 0 | AU53: 0 | AV53: 0 | AW53: 0 | AX53: 0 | AY53: 0 | AZ53: 0 | BA53: 0 | BB53: 5554.08 | BC53: =+VLOOKUP(C53,CF!F:F,1,0) -> 5D8D3D4D-D763-5DC4-A712-EAAEE61561F9
A54: 11 | B54: 4.0 | C54: 5CD64A5F-99C0-5259-95C4-F0C31A9C2AFB | F54: 06700 | G54: C132505 | H54: 16803 | I54: I - Ingreso | J54: 2025-11-03 06:37:12 | K54: 2025-11-03 06:42:13 | L54: CVD110412TF6 | M54: 601 - General de Ley Personas Morales | N54: CFS1808284P2 | O54: COMUNIDAD FELIZ SERVICIOS TI | P54: HCO200713KF9 | Q54: HEI COMMUNITY | R54: 601 - General de Ley Personas Morales | S54: 44130 | T54: 81112500 - Servicios de alquiler o arrendamiento de licencias de software de computador | 81112500 - Servicios de alquiler o arrendamiento de licencias de software de computador | U54: Licencia de Software 02 de Noviembre de 2025 a 01 de Diciembre de 2025. TORRE ST | Sistema de Transferencias y Pagos 02 de Noviembre de 2025 a 01 de Diciembre de 2 | W54: G03 - Gastos en general | AB54: CONDICIONES | AD54: VIGENTE | AF54: CANCELABLE SIN ACEPTACIÓN | AJ54: MXN | AL54: 01 No aplica | AM54: PPD - Pago en Parcialidades o Diferido | AN54: 99 - Por definir | AO54: 0 | AP54: 357.58 | AQ54: 0 | AR54: 57.22 | AS54: 0 | AT54: 0 | AU54: 0 | AV54: 0 | AW54: 0 | AX54: 0 | AY54: 0 | AZ54: 0 | BA54: 0 | BB54: 414.8 | BC54: =+VLOOKUP(C54,CF!F:F,1,0) -> 5CD64A5F-99C0-5259-95C4-F0C31A9C2AFB
A55: 11 | B55: 4.0 | C55: 63745549-FD3E-518A-9AEF-945B6A623309 | F55: 06700 | G55: C119086 | H55: 16804 | I55: I - Ingreso | J55: 2025-11-03 06:37:14 | K55: 2025-11-03 06:42:15 | L55: CVD110412TF6 | M55: 601 - General de Ley Personas Morales | N55: CFS1808284P2 | O55: COMUNIDAD FELIZ SERVICIOS TI | P55: XAXX010101000 | Q55: PUBLICO EN GENERAL | R55: 616 - Sin obligaciones fiscales | S55: 06700 | T55: 81112500 - Servicios de alquiler o arrendamiento de licencias de software de computador | 81112500 - Servicios de alquiler o arrendamiento de licencias de software de computador | U55: Licencia de Software 02 de Noviembre de 2025 a 01 de Diciembre de 2025. GARDEN R | Sistema de Transferencias y Pagos 02 de Noviembre de 2025 a 01 de Diciembre de 2 | W55: S01 - Sin efectos fiscales | Y55: 01 | Z55: 11 Noviembre | AA55: 2025 | AB55: CONDICIONES | AD55: VIGENTE | AF55: CANCELABLE SIN ACEPTACIÓN | AJ55: MXN | AL55: 01 No aplica | AM55: PPD - Pago en Parcialidades o Diferido | AN55: 99 - Por definir | AO55: 0 | AP55: 792 | AQ55: 0 | AR55: 126.72 | AS55: 0 | AT55: 0 | AU55: 0 | AV55: 0 | AW55: 0 | AX55: 0 | AY55: 0 | AZ55: 0 | BA55: 0 | BB55: 918.72 | BC55: =+VLOOKUP(C55,CF!F:F,1,0) -> 63745549-FD3E-518A-9AEF-945B6A623309
A56: 11 | B56: 4.0 | C56: 123C92D0-AE9D-5A04-AE2A-4C57FF9E40F0 | F56: 06700 | G56: C116373 | H56: 16805 | I56: I - Ingreso | J56: 2025-11-03 06:37:16 | K56: 2025-11-03 06:42:17 | L56: CVD110412TF6 | M56: 601 - General de Ley Personas Morales | N56: CFS1808284P2 | O56: COMUNIDAD FELIZ SERVICIOS TI | P56: XAXX010101000 | Q56: PUBLICO EN GENERAL | R56: 616 - Sin obligaciones fiscales | S56: 06700 | T56: 81112500 - Servicios de alquiler o arrendamiento de licencias de software de computador | 81112500 - Servicios de alquiler o arrendamiento de licencias de software de computador | U56: Licencia de Software 02 de Noviembre de 2025 a 01 de Diciembre de 2025. DISTUM Y | Sistema de Transferencias y Pagos 02 de Noviembre de 2025 a 01 de Diciembre de 2 | W56: S01 - Sin efectos fiscales | Y56: 01 | Z56: 11 Noviembre | AA56: 2025 | AB56: CONDICIONES | AD56: VIGENTE | AF56: CANCELABLE SIN ACEPTACIÓN | AJ56: MXN | AL56: 01 No aplica | AM56: PPD - Pago en Parcialidades o Diferido | AN56: 99 - Por definir | AO56: 0 | AP56: 2835 | AQ56: 0 | AR56: 453.6 | AS56: 0 | AT56: 0 | AU56: 0 | AV56: 0 | AW56: 0 | AX56: 0 | AY56: 0 | AZ56: 0 | BA56: 0 | BB56: 3288.6 | BC56: =+VLOOKUP(C56,CF!F:F,1,0) -> 123C92D0-AE9D-5A04-AE2A-4C57FF9E40F0
A57: 11 | B57: 4.0 | C57: FC3A505C-D51F-51C7-8FDE-0993C6F3A1D2 | F57: 06700 | G57: C133614 | H57: 16806 | I57: I - Ingreso | J57: 2025-11-03 06:37:18 | K57: 2025-11-03 06:42:19 | L57: CVD110412TF6 | M57: 601 - General de Ley Personas Morales | N57: CFS1808284P2 | O57: COMUNIDAD FELIZ SERVICIOS TI | P57: CTC231013MDA | Q57: CONDOMINOS TORRE CENTRAL TOREO | R57: 603 - Personas Morales con Fines no Lucrativos | S57: 22044 | T57: 81112500 - Servicios de alquiler o arrendamiento de licencias de software de computador | 81112500 - Servicios de alquiler o arrendamiento de licencias de software de computador | U57: Sistema de Transferencias y Pagos 02 de Noviembre de 2025 a 01 de Diciembre de 2 | Licencia de Software 02 de Noviembre de 2025 a 01 de Diciembre de 2025. CENTRAL | W57: G03 - Gastos en general | AB57: CONDICIONES | AD57: VIGENTE | AF57: NO CANCELABLE | AJ57: MXN | AL57: 01 No aplica | AM57: PPD - Pago en Parcialidades o Diferido | AN57: 99 - Por definir | AO57: 0 | AP57: 3150 | AQ57: 0 | AR57: 504 | AS57: 0 | AT57: 0 | AU57: 0 | AV57: 0 | AW57: 0 | AX57: 0 | AY57: 0 | AZ57: 0 | BA57: 0 | BB57: 3654 | BC57: =+VLOOKUP(C57,CF!F:F,1,0) -> FC3A505C-D51F-51C7-8FDE-0993C6F3A1D2
A58: 11 | B58: 4.0 | C58: FDD72A6C-FB90-59BD-97E3-CB68D18F9D1B | F58: 06700 | G58: C128136 | H58: 16807 | I58: I - Ingreso | J58: 2025-11-03 06:37:42 | K58: 2025-11-03 06:42:43 | L58: CVD110412TF6 | M58: 601 - General de Ley Personas Morales | N58: CFS1808284P2 | O58: COMUNIDAD FELIZ SERVICIOS TI | P58: RDI170927729 | Q58: REGBAR DESARROLLOS INMOBILIARIOS | R58: 601 - General de Ley Personas Morales | S58: 54050 | T58: 81112500 - Servicios de alquiler o arrendamiento de licencias de software de computador | U58: Licencia de Software 02 de Noviembre de 2025 a 01 de Diciembre de 2025. COAHUILA | W58: G03 - Gastos en general | AB58: CONDICIONES | AD58: VIGENTE | AF58: CANCELABLE CON ACEPTACIÓN | AJ58: MXN | AL58: 01 No aplica | AM58: PPD - Pago en Parcialidades o Diferido | AN58: 99 - Por definir | AO58: 0 | AP58: 1000 | AQ58: 0 | AR58: 160 | AS58: 0 | AT58: 0 | AU58: 0 | AV58: 0 | AW58: 0 | AX58: 0 | AY58: 0 | AZ58: 0 | BA58: 0 | BB58: 1160 | BC58: =+VLOOKUP(C58,CF!F:F,1,0) -> FDD72A6C-FB90-59BD-97E3-CB68D18F9D1B
A59: 11 | B59: 4.0 | C59: 2301E361-8442-5A14-9071-655EBF01A48E | F59: 06700 | G59: C90006 | H59: 16808 | I59: I - Ingreso | J59: 2025-11-03 06:37:45 | K59: 2025-11-03 06:42:46 | L59: CVD110412TF6 | M59: 601 - General de Ley Personas Morales | N59: CFS1808284P2 | O59: COMUNIDAD FELIZ SERVICIOS TI | P59: XAXX010101000 | Q59: PUBLICO EN GENERAL | R59: 616 - Sin obligaciones fiscales | S59: 06700 | T59: 81112500 - Servicios de alquiler o arrendamiento de licencias de software de computador | U59: Licencia de Software 02 de Noviembre de 2025 a 01 de Diciembre de 2025. COMPLEJO | W59: S01 - Sin efectos fiscales | Y59: 01 | Z59: 11 Noviembre | AA59: 2025 | AB59: CONDICIONES | AD59: VIGENTE | AF59: CANCELABLE SIN ACEPTACIÓN | AJ59: MXN | AL59: 01 No aplica | AM59: PPD - Pago en Parcialidades o Diferido | AN59: 99 - Por definir | AO59: 0 | AP59: 741.38 | AQ59: 0 | AR59: 118.62 | AS59: 0 | AT59: 0 | AU59: 0 | AV59: 0 | AW59: 0 | AX59: 0 | AY59: 0 | AZ59: 0 | BA59: 0 | BB59: 860 | BC59: =+VLOOKUP(C59,CF!F:F,1,0) -> 2301E361-8442-5A14-9071-655EBF01A48E
A60: 11 | B60: 4.0 | C60: C004BC39-23E2-5129-9732-D2BC80A0CAD0 | F60: 06700 | G60: C56213 | H60: 16809 | I60: I - Ingreso | J60: 2025-11-03 06:37:47 | K60: 2025-11-03 06:42:48 | L60: CVD110412TF6 | M60: 601 - General de Ley Personas Morales | N60: CFS1808284P2 | O60: COMUNIDAD FELIZ SERVICIOS TI | P60: IIS190116DV4 | Q60: IMPLEMENTACION E INNOVACION EN SERVICIOS DE ADMINISTRACION | R60: 603 - Personas Morales con Fines no Lucrativos | S60: 52243 | T60: 81112500 - Servicios de alquiler o arrendamiento de licencias de software de computador | 81112500 - Servicios de alquiler o arrendamiento de licencias de software de computador | 81112500 - Servicios de alquiler o arrendamiento de licencias de software de computador | 81112500 - Servicios de alquiler o arrendamiento de licencias de software de computador | 81112500 - Servicios de alquiler o arrendamiento de licencias de software de computador | U60: Licencia de Software 02 de Noviembre de 2025 a 01 de Diciembre de 2025. Privada | Licencia de Software 02 de Noviembre de 2025 a 01 de Diciembre de 2025. Privada | Licencia de Software 02 de Noviembre de 2025 a 01 de Diciembre de 2025. Paseo de | Licencia de Software 02 de Noviembre de 2025 a 01 de Diciembre de 2025. Fraccion | Licencia de Software 02 de Noviembre de 2025 a 01 de Diciembre de 2025. Foresta | W60: G03 - Gastos en general | AB60: CONDICIONES | AD60: VIGENTE | AF60: CANCELABLE CON ACEPTACIÓN | AJ60: MXN | AL60: 01 No aplica | AM60: PPD - Pago en Parcialidades o Diferido | AN60: 99 - Por definir | AO60: 0 | AP60: 3303 | AQ60: 0 | AR60: 528.48 | AS60: 0 | AT60: 0 | AU60: 0 | AV60: 0 | AW60: 0 | AX60: 0 | AY60: 0 | AZ60: 0 | BA60: 0 | BB60: 3831.48 | BC60: =+VLOOKUP(C60,CF!F:F,1,0) -> C004BC39-23E2-5129-9732-D2BC80A0CAD0
A61: 11 | B61: 4.0 | C61: 4C2B729A-D0D3-539F-9BA6-FDE027FD3F0C | F61: 06700 | G61: C118983 | H61: 16810 | I61: I - Ingreso | J61: 2025-11-03 06:37:49 | K61: 2025-11-03 06:42:50 | L61: CVD110412TF6 | M61: 601 - General de Ley Personas Morales | N61: CFS1808284P2 | O61: COMUNIDAD FELIZ SERVICIOS TI | P61: XAXX010101000 | Q61: PUBLICO EN GENERAL | R61: 616 - Sin obligaciones fiscales | S61: 06700 | T61: 81112500 - Servicios de alquiler o arrendamiento de licencias de software de computador | U61: Licencia de Software 02 de Noviembre de 2025 a 01 de Diciembre de 2025. SUBCONDO | W61: S01 - Sin efectos fiscales | Y61: 01 | Z61: 11 Noviembre | AA61: 2025 | AB61: CONDICIONES | AD61: VIGENTE | AF61: CANCELABLE SIN ACEPTACIÓN | AJ61: MXN | AL61: 01 No aplica | AM61: PPD - Pago en Parcialidades o Diferido | AN61: 99 - Por definir | AO61: 0 | AP61: 1453.5 | AQ61: 0 | AR61: 232.56 | AS61: 0 | AT61: 0 | AU61: 0 | AV61: 0 | AW61: 0 | AX61: 0 | AY61: 0 | AZ61: 0 | BA61: 0 | BB61: 1686.06 | BC61: =+VLOOKUP(C61,CF!F:F,1,0) -> 4C2B729A-D0D3-539F-9BA6-FDE027FD3F0C
A62: 11 | B62: 4.0 | C62: 38325883-7B8D-5004-93BC-0EF2A9689C50 | F62: 06700 | G62: C119108 | H62: 16811 | I62: I - Ingreso | J62: 2025-11-03 06:37:51 | K62: 2025-11-03 06:42:52 | L62: CVD110412TF6 | M62: 601 - General de Ley Personas Morales | N62: CFS1808284P2 | O62: COMUNIDAD FELIZ SERVICIOS TI | P62: XAXX010101000 | Q62: PUBLICO EN GENERAL | R62: 616 - Sin obligaciones fiscales | S62: 06700 | T62: 81112500 - Servicios de alquiler o arrendamiento de licencias de software de computador | U62: Licencia de Software 02 de Noviembre de 2025 a 01 de Diciembre de 2025. Condomin | W62: S01 - Sin efectos fiscales | Y62: 01 | Z62: 11 Noviembre | AA62: 2025 | AB62: CONDICIONES | AD62: VIGENTE | AF62: CANCELABLE SIN ACEPTACIÓN | AJ62: MXN | AL62: 01 No aplica | AM62: PPD - Pago en Parcialidades o Diferido | AN62: 99 - Por definir | AO62: 0 | AP62: 102.15 | AQ62: 0 | AR62: 16.34 | AS62: 0 | AT62: 0 | AU62: 0 | AV62: 0 | AW62: 0 | AX62: 0 | AY62: 0 | AZ62: 0 | BA62: 0 | BB62: 118.49 | BC62: =+VLOOKUP(C62,CF!F:F,1,0) -> 38325883-7B8D-5004-93BC-0EF2A9689C50
A63: 11 | B63: 4.0 | C63: A7932736-1B50-5A9A-8C2A-56F786098C99 | F63: 06700 | G63: C118106 | H63: 16812 | I63: I - Ingreso | J63: 2025-11-03 06:37:53 | K63: 2025-11-03 06:42:54 | L63: CVD110412TF6 | M63: 601 - General de Ley Personas Morales | N63: CFS1808284P2 | O63: COMUNIDAD FELIZ SERVICIOS TI | P63: RDI170927729 | Q63: REGBAR DESARROLLOS INMOBILIARIOS | R63: 601 - General de Ley Personas Morales | S63: 54050 | T63: 81112500 - Servicios de alquiler o arrendamiento de licencias de software de computador | U63: Licencia de Software 02 de Noviembre de 2025 a 01 de Diciembre de 2025. SUBCONDO | W63: G03 - Gastos en general | AB63: CONDICIONES | AD63: VIGENTE | AF63: CANCELABLE CON ACEPTACIÓN | AJ63: MXN | AL63: 01 No aplica | AM63: PPD - Pago en Parcialidades o Diferido | AN63: 99 - Por definir | AO63: 0 | AP63: 1419.5 | AQ63: 0 | AR63: 227.12 | AS63: 0 | AT63: 0 | AU63: 0 | AV63: 0 | AW63: 0 | AX63: 0 | AY63: 0 | AZ63: 0 | BA63: 0 | BB63: 1646.62 | BC63: =+VLOOKUP(C63,CF!F:F,1,0) -> A7932736-1B50-5A9A-8C2A-56F786098C99
A64: 11 | B64: 4.0 | C64: E4261C6B-F777-5E7F-A6D5-B80CABF514F6 | F64: 06700 | G64: C109936 | H64: 16813 | I64: I - Ingreso | J64: 2025-11-03 06:37:55 | K64: 2025-11-03 06:42:56 | L64: CVD110412TF6 | M64: 601 - General de Ley Personas Morales | N64: CFS1808284P2 | O64: COMUNIDAD FELIZ SERVICIOS TI | P64: CCP0710161C8 | Q64: 405 PALMAZ | R64: 603 - Personas Morales con Fines no Lucrativos | S64: 72197 | T64: 81112500 - Servicios de alquiler o arrendamiento de licencias de software de computador | U64: Licencia de Software 02 de Noviembre de 2025 a 01 de Diciembre de 2025. Torre 1, | W64: G03 - Gastos en general | AB64: CONDICIONES | AD64: VIGENTE | AF64: CANCELABLE CON ACEPTACIÓN | AJ64: MXN | AL64: 01 No aplica | AM64: PPD - Pago en Parcialidades o Diferido | AN64: 99 - Por definir | AO64: 0 | AP64: 1000 | AQ64: 0 | AR64: 160 | AS64: 0 | AT64: 0 | AU64: 0 | AV64: 0 | AW64: 0 | AX64: 0 | AY64: 0 | AZ64: 0 | BA64: 0 | BB64: 1160 | BC64: =+VLOOKUP(C64,CF!F:F,1,0) -> E4261C6B-F777-5E7F-A6D5-B80CABF514F6
A65: 11 | B65: 4.0 | C65: 6110B282-F0A9-5B02-9675-8E655E93F70B | F65: 06700 | G65: C128137 | H65: 16814 | I65: I - Ingreso | J65: 2025-11-03 06:37:57 | K65: 2025-11-03 06:42:58 | L65: CVD110412TF6 | M65: 601 - General de Ley Personas Morales | N65: CFS1808284P2 | O65: COMUNIDAD FELIZ SERVICIOS TI | P65: RDI170927729 | Q65: REGBAR DESARROLLOS INMOBILIARIOS | R65: 601 - General de Ley Personas Morales | S65: 54050 | T65: 81112500 - Servicios de alquiler o arrendamiento de licencias de software de computador | U65: Licencia de Software 02 de Noviembre de 2025 a 01 de Diciembre de 2025. ZAMORA 8 | W65: G03 - Gastos en general | AB65: CONDICIONES | AD65: VIGENTE | AF65: CANCELABLE CON ACEPTACIÓN | AJ65: MXN | AL65: 01 No aplica | AM65: PPD - Pago en Parcialidades o Diferido | AN65: 99 - Por definir | AO65: 0 | AP65: 1000 | AQ65: 0 | AR65: 160 | AS65: 0 | AT65: 0 | AU65: 0 | AV65: 0 | AW65: 0 | AX65: 0 | AY65: 0 | AZ65: 0 | BA65: 0 | BB65: 1160 | BC65: =+VLOOKUP(C65,CF!F:F,1,0) -> 6110B282-F0A9-5B02-9675-8E655E93F70B
A66: 11 | B66: 4.0 | C66: F891BFF7-961F-59C1-89A8-9192B33D2F51 | F66: 06700 | G66: C107197 | H66: 16815 | I66: I - Ingreso | J66: 2025-11-03 06:38:00 | K66: 2025-11-03 06:43:00 | L66: CVD110412TF6 | M66: 601 - General de Ley Personas Morales | N66: CFS1808284P2 | O66: COMUNIDAD FELIZ SERVICIOS TI | P66: XAXX010101000 | Q66: PUBLICO EN GENERAL | R66: 616 - Sin obligaciones fiscales | S66: 06700 | T66: 81112500 - Servicios de alquiler o arrendamiento de licencias de software de computador | U66: Licencia de Software 02 de Noviembre de 2025 a 01 de Diciembre de 2025. Grand Co | W66: S01 - Sin efectos fiscales | Y66: 01 | Z66: 11 Noviembre | AA66: 2025 | AB66: CONDICIONES | AD66: VIGENTE | AF66: CANCELABLE SIN ACEPTACIÓN | AJ66: MXN | AL66: 01 No aplica | AM66: PPD - Pago en Parcialidades o Diferido | AN66: 99 - Por definir | AO66: 0 | AP66: 835.24 | AQ66: 0 | AR66: 133.64 | AS66: 0 | AT66: 0 | AU66: 0 | AV66: 0 | AW66: 0 | AX66: 0 | AY66: 0 | AZ66: 0 | BA66: 0 | BB66: 968.88 | BC66: =+VLOOKUP(C66,CF!F:F,1,0) -> F891BFF7-961F-59C1-89A8-9192B33D2F51
A67: 11 | B67: 4.0 | C67: 726CFF2A-0186-5F7C-905F-D9DE11DF4A8F | F67: 06700 | G67: C122229 | H67: 16816 | I67: I - Ingreso | J67: 2025-11-03 06:38:02 | K67: 2025-11-03 06:43:02 | L67: CVD110412TF6 | M67: 601 - General de Ley Personas Morales | N67: CFS1808284P2 | O67: COMUNIDAD FELIZ SERVICIOS TI | P67: XAXX010101000 | Q67: PUBLICO EN GENERAL | R67: 616 - Sin obligaciones fiscales | S67: 06700 | T67: 81112500 - Servicios de alquiler o arrendamiento de licencias de software de computador | U67: Licencia de Software 02 de Noviembre de 2025 a 01 de Diciembre de 2025. Bosques | W67: S01 - Sin efectos fiscales | Y67: 01 | Z67: 11 Noviembre | AA67: 2025 | AB67: CONDICIONES | AD67: VIGENTE | AF67: CANCELABLE SIN ACEPTACIÓN | AJ67: MXN | AL67: 01 No aplica | AM67: PPD - Pago en Parcialidades o Diferido | AN67: 99 - Por definir | AO67: 0 | AP67: 357.5 | AQ67: 0 | AR67: 57.2 | AS67: 0 | AT67: 0 | AU67: 0 | AV67: 0 | AW67: 0 | AX67: 0 | AY67: 0 | AZ67: 0 | BA67: 0 | BB67: 414.7 | BC67: =+VLOOKUP(C67,CF!F:F,1,0) -> 726CFF2A-0186-5F7C-905F-D9DE11DF4A8F
A68: 11 | B68: 4.0 | C68: 92D29802-59F8-5434-AD18-B26F60FFDE3A | F68: 06700 | G68: C66937 | H68: 16818 | I68: I - Ingreso | J68: 2025-11-03 06:38:52 | K68: 2025-11-03 06:43:53 | L68: CVD110412TF6 | M68: 601 - General de Ley Personas Morales | N68: CFS1808284P2 | O68: COMUNIDAD FELIZ SERVICIOS TI | P68: CCP190219H67 | Q68: CENTRALIA CUN PLAZA Y OFICINAS | R68: 603 - Personas Morales con Fines no Lucrativos | S68: 77560 | T68: 81112500 - Servicios de alquiler o arrendamiento de licencias de software de computador | U68: Licencia de Software 03 de Noviembre de 2025 a 02 de Diciembre de 2025. Centrali | W68: G03 - Gastos en general | AB68: CONDICIONES | AD68: VIGENTE | AF68: NO CANCELABLE | AJ68: MXN | AL68: 01 No aplica | AM68: PPD - Pago en Parcialidades o Diferido | AN68: 99 - Por definir | AO68: 0 | AP68: 1109.48 | AQ68: 0 | AR68: 177.52 | AS68: 0 | AT68: 0 | AU68: 0 | AV68: 0 | AW68: 0 | AX68: 0 | AY68: 0 | AZ68: 0 | BA68: 0 | BB68: 1287 | BC68: =+VLOOKUP(C68,CF!F:F,1,0) -> 92D29802-59F8-5434-AD18-B26F60FFDE3A
A69: 11 | B69: 4.0 | C69: 89949BFA-8A92-5395-BA48-B6F317406531 | F69: 06700 | G69: C68421 | H69: 16819 | I69: I - Ingreso | J69: 2025-11-03 06:38:55 | K69: 2025-11-03 06:43:55 | L69: CVD110412TF6 | M69: 601 - General de Ley Personas Morales | N69: CFS1808284P2 | O69: COMUNIDAD FELIZ SERVICIOS TI | P69: RAC180608663 | Q69: RG ADMINISTRACIONES Y CONSULTORIA | R69: 603 - Personas Morales con Fines no Lucrativos | S69: 53950 | T69: 81112500 - Servicios de alquiler o arrendamiento de licencias de software de computador | U69: Licencia de Software 03 de Noviembre de 2025 a 02 de Diciembre de 2025. City Blu | W69: G03 - Gastos en general | AB69: CONDICIONES | AD69: VIGENTE | AF69: NO CANCELABLE | AJ69: MXN | AL69: 01 No aplica | AM69: PPD - Pago en Parcialidades o Diferido | AN69: 99 - Por definir | AO69: 0 | AP69: 2612.07 | AQ69: 0 | AR69: 417.93 | AS69: 0 | AT69: 0 | AU69: 0 | AV69: 0 | AW69: 0 | AX69: 0 | AY69: 0 | AZ69: 0 | BA69: 0 | BB69: 3030 | BC69: =+VLOOKUP(C69,CF!F:F,1,0) -> 89949BFA-8A92-5395-BA48-B6F317406531
A70: 11 | B70: 4.0 | C70: A71BBC0E-C87D-5FC0-92D8-8F5040703D7D | F70: 06700 | G70: C21792 | H70: 16820 | I70: I - Ingreso | J70: 2025-11-03 06:38:57 | K70: 2025-11-03 06:43:57 | L70: CVD110412TF6 | M70: 601 - General de Ley Personas Morales | N70: CFS1808284P2 | O70: COMUNIDAD FELIZ SERVICIOS TI | P70: PETV5905211U4 | Q70: VIRGINIA PEÑA TENORIO | R70: 612 - Personas Físicas con Actividades Empresariales y Profesionales | S70: 03100 | T70: 81112500 - Servicios de alquiler o arrendamiento de licencias de software de computador | U70: Licencia de Software 03 de Noviembre de 2025 a 02 de Diciembre de 2025. ZARAGOZA | W70: G03 - Gastos en general | AB70: CONDICIONES | AD70: VIGENTE | AF70: CANCELABLE SIN ACEPTACIÓN | AJ70: MXN | AL70: 01 No aplica | AM70: PPD - Pago en Parcialidades o Diferido | AN70: 99 - Por definir | AO70: 0 | AP70: 278.41 | AQ70: 0 | AR70: 44.55 | AS70: 0 | AT70: 0 | AU70: 0 | AV70: 0 | AW70: 0 | AX70: 0 | AY70: 0 | AZ70: 0 | BA70: 0 | BB70: 322.96 | BC70: =+VLOOKUP(C70,CF!F:F,1,0) -> A71BBC0E-C87D-5FC0-92D8-8F5040703D7D
A71: 11 | B71: 4.0 | C71: AAC070E0-D161-52A6-9651-855D94DB9218 | F71: 06700 | G71: C118607 | H71: 16821 | I71: I - Ingreso | J71: 2025-11-03 06:38:59 | K71: 2025-11-03 06:43:59 | L71: CVD110412TF6 | M71: 601 - General de Ley Personas Morales | N71: CFS1808284P2 | O71: COMUNIDAD FELIZ SERVICIOS TI | P71: CCU231027P35 | Q71: COTO 4 | R71: 603 - Personas Morales con Fines no Lucrativos | S71: 45138 | T71: 81112500 - Servicios de alquiler o arrendamiento de licencias de software de computador | U71: Licencia de Software 03 de Noviembre de 2025 a 02 de Diciembre de 2025. ALVA RES | W71: G03 - Gastos en general | AB71: CONDICIONES | AD71: VIGENTE | AF71: CANCELABLE CON ACEPTACIÓN | AJ71: MXN | AL71: 01 No aplica | AM71: PPD - Pago en Parcialidades o Diferido | AN71: 99 - Por definir | AO71: 0 | AP71: 1523.95 | AQ71: 0 | AR71: 243.83 | AS71: 0 | AT71: 0 | AU71: 0 | AV71: 0 | AW71: 0 | AX71: 0 | AY71: 0 | AZ71: 0 | BA71: 0 | BB71: 1767.78 | BC71: =+VLOOKUP(C71,CF!F:F,1,0) -> AAC070E0-D161-52A6-9651-855D94DB9218
A72: 11 | B72: 4.0 | C72: BCD961A0-5CE8-5643-899E-60A42492671B | F72: 06700 | G72: C77035 | H72: 16822 | I72: I - Ingreso | J72: 2025-11-03 06:39:01 | K72: 2025-11-03 06:44:02 | L72: CVD110412TF6 | M72: 601 - General de Ley Personas Morales | N72: CFS1808284P2 | O72: COMUNIDAD FELIZ SERVICIOS TI | P72: ACL1801248Z0 | Q72: ASOCIACION DE COLONOS DE LAGO ESMERALDA PUERTA ESPAÑA | R72: 603 - Personas Morales con Fines no Lucrativos | S72: 52989 | T72: 81112500 - Servicios de alquiler o arrendamiento de licencias de software de computador | U72: Licencia de Software 03 de Noviembre de 2025 a 02 de Diciembre de 2025. ASOC. DE | W72: G03 - Gastos en general | AB72: CONDICIONES | AD72: VIGENTE | AF72: NO CANCELABLE | AJ72: MXN | AL72: 01 No aplica | AM72: PPD - Pago en Parcialidades o Diferido | AN72: 99 - Por definir | AO72: 0 | AP72: 689.82 | AQ72: 0 | AR72: 110.37 | AS72: 0 | AT72: 0 | AU72: 0 | AV72: 0 | AW72: 0 | AX72: 0 | AY72: 0 | AZ72: 0 | BA72: 0 | BB72: 800.19 | BC72: Anular
A73: 11 | B73: 4.0 | C73: F878610D-B1E6-5E4F-A958-ABB65B121214 | F73: 06700 | G73: C49479 | H73: 16823 | I73: I - Ingreso | J73: 2025-11-03 06:39:03 | K73: 2025-11-03 06:44:04 | L73: CVD110412TF6 | M73: 601 - General de Ley Personas Morales | N73: CFS1808284P2 | O73: COMUNIDAD FELIZ SERVICIOS TI | P73: LOSC770906370 | Q73: CLAUDIA LOPEZ SOLIS | R73: 626 - Régimen Simplificado de Confianza | S73: 15900 | T73: 81112500 - Servicios de alquiler o arrendamiento de licencias de software de computador | U73: Licencia de Software 03 de Noviembre de 2025 a 02 de Diciembre de 2025. Condomin | W73: G03 - Gastos en general | AB73: CONDICIONES | AD73: VIGENTE | AF73: NO CANCELABLE | AJ73: MXN | AL73: 01 No aplica | AM73: PPD - Pago en Parcialidades o Diferido | AN73: 99 - Por definir | AO73: 0 | AP73: 600.95 | AQ73: 0 | AR73: 96.15 | AS73: 0 | AT73: 0 | AU73: 0 | AV73: 0 | AW73: 0 | AX73: 0 | AY73: 0 | AZ73: 0 | BA73: 0 | BB73: 697.1 | BC73: =+VLOOKUP(C73,CF!F:F,1,0) -> F878610D-B1E6-5E4F-A958-ABB65B121214
A74: 11 | B74: 4.0 | C74: 4707D0FD-44C8-5109-B93F-658CBCD87734 | F74: 06700 | G74: C128367 | H74: 16824 | I74: I - Ingreso | J74: 2025-11-03 06:39:05 | K74: 2025-11-03 06:44:06 | L74: CVD110412TF6 | M74: 601 - General de Ley Personas Morales | N74: CFS1808284P2 | O74: COMUNIDAD FELIZ SERVICIOS TI | P74: ACA230629AZ8 | Q74: ADMINISTRACION DE CONDOMINIOS ADMMEX | R74: 626 - Régimen Simplificado de Confianza | S74: 78130 | T74: 81112500 - Servicios de alquiler o arrendamiento de licencias de software de computador | U74: Licencia de Software 03 de Noviembre de 2025 a 02 de Diciembre de 2025. Condomin | W74: G03 - Gastos en general | AB74: CONDICIONES | AD74: VIGENTE | AF74: CANCELABLE CON ACEPTACIÓN | AJ74: MXN | AL74: 01 No aplica | AM74: PPD - Pago en Parcialidades o Diferido | AN74: 99 - Por definir | AO74: 0 | AP74: 1000 | AQ74: 0 | AR74: 160 | AS74: 0 | AT74: 0 | AU74: 0 | AV74: 0 | AW74: 0 | AX74: 0 | AY74: 0 | AZ74: 0 | BA74: 0 | BB74: 1160 | BC74: =+VLOOKUP(C74,CF!F:F,1,0) -> 4707D0FD-44C8-5109-B93F-658CBCD87734
A75: 11 | B75: 4.0 | C75: 287EC6CA-168E-521E-B051-7E972204FF49 | F75: 06700 | G75: C116877 | H75: 16825 | I75: I - Ingreso | J75: 2025-11-03 06:39:07 | K75: 2025-11-03 06:44:08 | L75: CVD110412TF6 | M75: 601 - General de Ley Personas Morales | N75: CFS1808284P2 | O75: COMUNIDAD FELIZ SERVICIOS TI | P75: CUC2208233G1 | Q75: CELESTA UC | R75: 603 - Personas Morales con Fines no Lucrativos | S75: 76230 | T75: 81112500 - Servicios de alquiler o arrendamiento de licencias de software de computador | U75: Licencia de Software 03 de Noviembre de 2025 a 02 de Diciembre de 2025. CELESTA | W75: G03 - Gastos en general | AB75: CONDICIONES | AD75: VIGENTE | AF75: CANCELABLE CON ACEPTACIÓN | AJ75: MXN | AL75: 01 No aplica | AM75: PPD - Pago en Parcialidades o Diferido | AN75: 99 - Por definir | AO75: 0 | AP75: 1482 | AQ75: 0 | AR75: 237.12 | AS75: 0 | AT75: 0 | AU75: 0 | AV75: 0 | AW75: 0 | AX75: 0 | AY75: 0 | AZ75: 0 | BA75: 0 | BB75: 1719.12 | BC75: =+VLOOKUP(C75,CF!F:F,1,0) -> 287EC6CA-168E-521E-B051-7E972204FF49
A76: 11 | B76: 4.0 | C76: 13B86D3A-E741-5D0B-92C2-0FF269E63014 | F76: 06700 | G76: C119125 | H76: 16826 | I76: I - Ingreso | J76: 2025-11-03 06:39:09 | K76: 2025-11-03 06:44:10 | L76: CVD110412TF6 | M76: 601 - General de Ley Personas Morales | N76: CFS1808284P2 | O76: COMUNIDAD FELIZ SERVICIOS TI | P76: XAXX010101000 | Q76: PUBLICO EN GENERAL | R76: 616 - Sin obligaciones fiscales | S76: 06700 | T76: 81112500 - Servicios de alquiler o arrendamiento de licencias de software de computador | 81112500 - Servicios de alquiler o arrendamiento de licencias de software de computador | U76: Sistema de Transferencias y Pagos 03 de Noviembre de 2025 a 02 de Diciembre de 2 | Licencia de Software 03 de Noviembre de 2025 a 02 de Diciembre de 2025. Los Enci | W76: S01 - Sin efectos fiscales | Y76: 01 | Z76: 11 Noviembre | AA76: 2025 | AB76: CONDICIONES | AD76: VIGENTE | AF76: CANCELABLE SIN ACEPTACIÓN | AJ76: MXN | AL76: 01 No aplica | AM76: PPD - Pago en Parcialidades o Diferido | AN76: 99 - Por definir | AO76: 0 | AP76: 1400 | AQ76: 0 | AR76: 224 | AS76: 0 | AT76: 0 | AU76: 0 | AV76: 0 | AW76: 0 | AX76: 0 | AY76: 0 | AZ76: 0 | BA76: 0 | BB76: 1624 | BC76: =+VLOOKUP(C76,CF!F:F,1,0) -> 13B86D3A-E741-5D0B-92C2-0FF269E63014
A77: 11 | B77: 4.0 | C77: 4639D16C-029E-5AA1-ADA4-7F91DEA4A130 | F77: 06700 | G77: C56431 | H77: 16827 | I77: I - Ingreso | J77: 2025-11-03 06:39:11 | K77: 2025-11-03 06:44:12 | L77: CVD110412TF6 | M77: 601 - General de Ley Personas Morales | N77: CFS1808284P2 | O77: COMUNIDAD FELIZ SERVICIOS TI | P77: RDI170927729 | Q77: REGBAR DESARROLLOS INMOBILIARIOS | R77: 601 - General de Ley Personas Morales | S77: 54050 | T77: 81112500 - Servicios de alquiler o arrendamiento de licencias de software de computador | 81112500 - Servicios de alquiler o arrendamiento de licencias de software de computador | U77: Licencia de Software 03 de Noviembre de 2025 a 02 de Diciembre de 2025. Cosmopol | Licencia de Software 03 de Noviembre de 2025 a 02 de Diciembre de 2025. Lote Méx | W77: G03 - Gastos en general | AB77: CONDICIONES | AD77: VIGENTE | AF77: CANCELABLE CON ACEPTACIÓN | AJ77: MXN | AL77: 01 No aplica | AM77: PPD - Pago en Parcialidades o Diferido | AN77: 99 - Por definir | AO77: 0 | AP77: 2949 | AQ77: 0 | AR77: 471.84 | AS77: 0 | AT77: 0 | AU77: 0 | AV77: 0 | AW77: 0 | AX77: 0 | AY77: 0 | AZ77: 0 | BA77: 0 | BB77: 3420.84 | BC77: =+VLOOKUP(C77,CF!F:F,1,0) -> 4639D16C-029E-5AA1-ADA4-7F91DEA4A130
A78: 11 | B78: 4.0 | C78: 881FBFB6-5313-53EC-B49F-9F0EE9429A70 | F78: 06700 | G78: C14307 | H78: 16828 | I78: I - Ingreso | J78: 2025-11-03 06:39:13 | K78: 2025-11-03 06:44:14 | L78: CVD110412TF6 | M78: 601 - General de Ley Personas Morales | N78: CFS1808284P2 | O78: COMUNIDAD FELIZ SERVICIOS TI | P78: PETV5905211U4 | Q78: VIRGINIA PEÑA TENORIO | R78: 612 - Personas Físicas con Actividades Empresariales y Profesionales | S78: 03100 | T78: 81112500 - Servicios de alquiler o arrendamiento de licencias de software de computador | U78: Licencia de Software 03 de Noviembre de 2025 a 02 de Diciembre de 2025. CONDOMIN | W78: G03 - Gastos en general | AB78: CONDICIONES | AD78: VIGENTE | AF78: NO CANCELABLE | AJ78: MXN | AL78: 01 No aplica | AM78: PPD - Pago en Parcialidades o Diferido | AN78: 99 - Por definir | AO78: 0 | AP78: 276.94 | AQ78: 0 | AR78: 44.31 | AS78: 0 | AT78: 0 | AU78: 0 | AV78: 0 | AW78: 0 | AX78: 0 | AY78: 0 | AZ78: 0 | BA78: 0 | BB78: 321.25 | BC78: =+VLOOKUP(C78,CF!F:F,1,0) -> 881FBFB6-5313-53EC-B49F-9F0EE9429A70
A79: 11 | B79: 4.0 | C79: FDC6448D-99BD-5AAE-ABED-9531EAAAF317 | F79: 06700 | G79: C118693 | H79: 16829 | I79: I - Ingreso | J79: 2025-11-03 06:39:15 | K79: 2025-11-03 06:44:16 | L79: CVD110412TF6 | M79: 601 - General de Ley Personas Morales | N79: CFS1808284P2 | O79: COMUNIDAD FELIZ SERVICIOS TI | P79: XAXX010101000 | Q79: PUBLICO EN GENERAL | R79: 616 - Sin obligaciones fiscales | S79: 06700 | T79: 81112500 - Servicios de alquiler o arrendamiento de licencias de software de computador | U79: Licencia de Software 03 de Noviembre de 2025 a 02 de Diciembre de 2025. CONDOMIN | W79: S01 - Sin efectos fiscales | Y79: 01 | Z79: 11 Noviembre | AA79: 2025 | AB79: CONDICIONES | AD79: VIGENTE | AF79: NO CANCELABLE | AJ79: MXN | AL79: 01 No aplica | AM79: PPD - Pago en Parcialidades o Diferido | AN79: 99 - Por definir | AO79: 0 | AP79: 1365 | AQ79: 0 | AR79: 218.4 | AS79: 0 | AT79: 0 | AU79: 0 | AV79: 0 | AW79: 0 | AX79: 0 | AY79: 0 | AZ79: 0 | BA79: 0 | BB79: 1583.4 | BC79: =+VLOOKUP(C79,CF!F:F,1,0) -> FDC6448D-99BD-5AAE-ABED-9531EAAAF317
A80: 11 | B80: 4.0 | C80: BFAD2854-42B2-54B8-8D01-0F50453DC14C | F80: 06700 | G80: C65134 | H80: 16831 | I80: I - Ingreso | J80: 2025-11-03 06:39:20 | K80: 2025-11-03 06:44:21 | L80: CVD110412TF6 | M80: 601 - General de Ley Personas Morales | N80: CFS1808284P2 | O80: COMUNIDAD FELIZ SERVICIOS TI | P80: URA230503CY1 | Q80: UNION DE RESIDENTES AYUTLA | R80: 603 - Personas Morales con Fines no Lucrativos | S80: 24157 | T80: 81112500 - Servicios de alquiler o arrendamiento de licencias de software de computador | U80: Licencia de Software 03 de Noviembre de 2025 a 02 de Diciembre de 2025. Conjunto | W80: G03 - Gastos en general | AB80: CONDICIONES | AD80: VIGENTE | AF80: CANCELABLE CON ACEPTACIÓN | AJ80: MXN | AL80: 01 No aplica | AM80: PPD - Pago en Parcialidades o Diferido | AN80: 99 - Por definir | AO80: 0 | AP80: 2736.62 | AQ80: 0 | AR80: 437.86 | AS80: 0 | AT80: 0 | AU80: 0 | AV80: 0 | AW80: 0 | AX80: 0 | AY80: 0 | AZ80: 0 | BA80: 0 | BB80: 3174.48 | BC80: =+VLOOKUP(C80,CF!F:F,1,0) -> BFAD2854-42B2-54B8-8D01-0F50453DC14C
A81: 11 | B81: 4.0 | C81: 7EC3610E-D45D-55A6-A761-53E700621DCE | F81: 06700 | G81: C115656 | H81: 16832 | I81: I - Ingreso | J81: 2025-11-03 06:39:22 | K81: 2025-11-03 06:44:23 | L81: CVD110412TF6 | M81: 601 - General de Ley Personas Morales | N81: CFS1808284P2 | O81: COMUNIDAD FELIZ SERVICIOS TI | P81: XAXX010101000 | Q81: PUBLICO EN GENERAL | R81: 616 - Sin obligaciones fiscales | S81: 06700 | T81: 81112500 - Servicios de alquiler o arrendamiento de licencias de software de computador | 81112500 - Servicios de alquiler o arrendamiento de licencias de software de computador | U81: Licencia de Software 03 de Noviembre de 2025 a 02 de Diciembre de 2025. CONJUNTO | Licencia de Software 03 de Noviembre de 2025 a 02 de Diciembre de 2025. Hacienda | W81: S01 - Sin efectos fiscales | Y81: 01 | Z81: 11 Noviembre | AA81: 2025 | AB81: CONDICIONES | AD81: VIGENTE | AF81: CANCELABLE SIN ACEPTACIÓN | AJ81: MXN | AL81: 01 No aplica | AM81: PPD - Pago en Parcialidades o Diferido | AN81: 99 - Por definir | AO81: 0 | AP81: 768 | AQ81: 0 | AR81: 122.88 | AS81: 0 | AT81: 0 | AU81: 0 | AV81: 0 | AW81: 0 | AX81: 0 | AY81: 0 | AZ81: 0 | BA81: 0 | BB81: 890.88 | BC81: =+VLOOKUP(C81,CF!F:F,1,0) -> 7EC3610E-D45D-55A6-A761-53E700621DCE
A82: 11 | B82: 4.0 | C82: E0CC84B8-0804-59BB-9F23-E504E41EE84F | F82: 06700 | G82: C118504 | H82: 16834 | I82: I - Ingreso | J82: 2025-11-03 06:39:26 | K82: 2025-11-03 06:44:27 | L82: CVD110412TF6 | M82: 601 - General de Ley Personas Morales | N82: CFS1808284P2 | O82: COMUNIDAD FELIZ SERVICIOS TI | P82: CDD211014MI2 | Q82: CONDOMINIO 2 (DOS) DEL FRACCIONAMIENTO TERRA VISTA RESIDENCIAL | R82: 603 - Personas Morales con Fines no Lucrativos | S82: 45200 | T82: 81112500 - Servicios de alquiler o arrendamiento de licencias de software de computador | 81112500 - Servicios de alquiler o arrendamiento de licencias de software de computador | U82: Sistema de Transferencias y Pagos 03 de Noviembre de 2025 a 02 de Diciembre de 2 | Licencia de Software 03 de Noviembre de 2025 a 02 de Diciembre de 2025. CONDOMIN | W82: G03 - Gastos en general | AB82: CONDICIONES | AD82: VIGENTE | AF82: CANCELABLE CON ACEPTACIÓN | AJ82: MXN | AL82: 01 No aplica | AM82: PPD - Pago en Parcialidades o Diferido | AN82: 99 - Por definir | AO82: 0 | AP82: 10217 | AQ82: 0 | AR82: 1634.72 | AS82: 0 | AT82: 0 | AU82: 0 | AV82: 0 | AW82: 0 | AX82: 0 | AY82: 0 | AZ82: 0 | BA82: 0 | BB82: 11851.72 | BC82: =+VLOOKUP(C82,CF!F:F,1,0) -> E0CC84B8-0804-59BB-9F23-E504E41EE84F
A83: 11 | B83: 4.0 | C83: EE99DAC5-AD9B-5ADB-9A57-26BA5E9FC348 | F83: 06700 | G83: C104260 | H83: 16835 | I83: I - Ingreso | J83: 2025-11-03 06:39:28 | K83: 2025-11-03 06:44:29 | L83: CVD110412TF6 | M83: 601 - General de Ley Personas Morales | N83: CFS1808284P2 | O83: COMUNIDAD FELIZ SERVICIOS TI | P83: XAXX010101000 | Q83: PUBLICO EN GENERAL | R83: 616 - Sin obligaciones fiscales | S83: 06700 | T83: 81112500 - Servicios de alquiler o arrendamiento de licencias de software de computador | 81112500 - Servicios de alquiler o arrendamiento de licencias de software de computador | U83: Licencia de Software 03 de Noviembre de 2025 a 02 de Diciembre de 2025. Jardines | Sistema de Transferencias y Pagos 03 de Noviembre de 2025 a 02 de Diciembre de 2 | W83: S01 - Sin efectos fiscales | Y83: 01 | Z83: 11 Noviembre | AA83: 2025 | AB83: CONDICIONES | AD83: VIGENTE | AF83: NO CANCELABLE | AJ83: MXN | AL83: 01 No aplica | AM83: PPD - Pago en Parcialidades o Diferido | AN83: 99 - Por definir | AO83: 0 | AP83: 4914 | AQ83: 0 | AR83: 786.24 | AS83: 0 | AT83: 0 | AU83: 0 | AV83: 0 | AW83: 0 | AX83: 0 | AY83: 0 | AZ83: 0 | BA83: 0 | BB83: 5700.24 | BC83: =+VLOOKUP(C83,CF!F:F,1,0) -> EE99DAC5-AD9B-5ADB-9A57-26BA5E9FC348
A84: 11 | B84: 4.0 | C84: B02DED26-D7CB-5CD6-90DF-159716E60097 | F84: 06700 | G84: C153549 | H84: 16836 | I84: I - Ingreso | J84: 2025-11-03 06:39:31 | K84: 2025-11-03 06:44:31 | L84: CVD110412TF6 | M84: 601 - General de Ley Personas Morales | N84: CFS1808284P2 | O84: COMUNIDAD FELIZ SERVICIOS TI | P84: XAXX010101000 | Q84: PUBLICO EN GENERAL | R84: 616 - Sin obligaciones fiscales | S84: 06700 | T84: 81112500 - Servicios de alquiler o arrendamiento de licencias de software de computador | U84: Licencia de Software 03 de Noviembre de 2025 a 02 de Diciembre de 2025. ARGENTIN | W84: S01 - Sin efectos fiscales | Y84: 01 | Z84: 11 Noviembre | AA84: 2025 | AB84: CONDICIONES | AD84: VIGENTE | AF84: CANCELABLE SIN ACEPTACIÓN | AJ84: MXN | AL84: 01 No aplica | AM84: PPD - Pago en Parcialidades o Diferido | AN84: 99 - Por definir | AO84: 0 | AP84: 1374.61 | AQ84: 0 | AR84: 219.94 | AS84: 0 | AT84: 0 | AU84: 0 | AV84: 0 | AW84: 0 | AX84: 0 | AY84: 0 | AZ84: 0 | BA84: 0 | BB84: 1594.55 | BC84: =+VLOOKUP(C84,CF!F:F,1,0) -> B02DED26-D7CB-5CD6-90DF-159716E60097
A85: 11 | B85: 4.0 | C85: 6862B5FF-4C2E-5909-908A-DCBE18592872 | F85: 06700 | G85: C99153 | H85: 16837 | I85: I - Ingreso | J85: 2025-11-03 06:39:33 | K85: 2025-11-03 06:44:33 | L85: CVD110412TF6 | M85: 601 - General de Ley Personas Morales | N85: CFS1808284P2 | O85: COMUNIDAD FELIZ SERVICIOS TI | P85: XAXX010101000 | Q85: PUBLICO EN GENERAL | R85: 616 - Sin obligaciones fiscales | S85: 06700 | T85: 81112500 - Servicios de alquiler o arrendamiento de licencias de software de computador | U85: Licencia de Software 03 de Noviembre de 2025 a 02 de Diciembre de 2025. Palmas R | W85: S01 - Sin efectos fiscales | Y85: 01 | Z85: 11 Noviembre | AA85: 2025 | AB85: CONDICIONES | AD85: VIGENTE | AF85: CANCELABLE SIN ACEPTACIÓN | AJ85: MXN | AL85: 01 No aplica | AM85: PPD - Pago en Parcialidades o Diferido | AN85: 99 - Por definir | AO85: 0 | AP85: 1000 | AQ85: 0 | AR85: 160 | AS85: 0 | AT85: 0 | AU85: 0 | AV85: 0 | AW85: 0 | AX85: 0 | AY85: 0 | AZ85: 0 | BA85: 0 | BB85: 1160 | BC85: =+VLOOKUP(C85,CF!F:F,1,0) -> 6862B5FF-4C2E-5909-908A-DCBE18592872
A86: 11 | B86: 4.0 | C86: 57240050-AACC-5A85-8743-F0B4E2C3E1D6 | F86: 06700 | G86: C55518 | H86: 16844 | I86: I - Ingreso | J86: 2025-11-03 08:45:10 | K86: 2025-11-03 08:50:11 | L86: CVD110412TF6 | M86: 601 - General de Ley Personas Morales | N86: CFS1808284P2 | O86: COMUNIDAD FELIZ SERVICIOS TI | P86: CGT250526238 | Q86: CONDOMINIO GREEN 3 TRES | R86: 603 - Personas Morales con Fines no Lucrativos | S86: 77710 | T86: 81112500 - Servicios de alquiler o arrendamiento de licencias de software de computador | U86: Licencia de Software 07 de Octubre de 2025 a 06 de Noviembre de 2025. CONDOMINIO | W86: G03 - Gastos en general | AB86: CONDICIONES | AD86: VIGENTE | AF86: NO CANCELABLE | AJ86: MXN | AL86: 01 No aplica | AM86: PPD - Pago en Parcialidades o Diferido | AN86: 99 - Por definir | AO86: 0 | AP86: 600 | AQ86: 0 | AR86: 96 | AS86: 0 | AT86: 0 | AU86: 0 | AV86: 0 | AW86: 0 | AX86: 0 | AY86: 0 | AZ86: 0 | BA86: 0 | BB86: 696 | BC86: =+VLOOKUP(C86,CF!F:F,1,0) -> 57240050-AACC-5A85-8743-F0B4E2C3E1D6
A87: 11 | B87: 4.0 | C87: 5ED4445E-2867-5EC4-85A6-FE1852170793 | F87: 06700 | G87: C58243 | H87: 16845 | I87: I - Ingreso | J87: 2025-11-03 09:11:09 | K87: 2025-11-03 09:16:10 | L87: CVD110412TF6 | M87: 601 - General de Ley Personas Morales | N87: CFS1808284P2 | O87: COMUNIDAD FELIZ SERVICIOS TI | P87: XAXX010101000 | Q87: PUBLICO EN GENERAL | R87: 616 - Sin obligaciones fiscales | S87: 06700 | T87: 81112500 - Servicios de alquiler o arrendamiento de licencias de software de computador | U87: Licencia de Software 30 de octubre de 2025 a 29 de noviembre de 2025. Racine Tow | W87: S01 - Sin efectos fiscales | Y87: 01 | Z87: 11 Noviembre | AA87: 2025 | AB87: CONDICIONES | AD87: VIGENTE | AF87: CANCELABLE SIN ACEPTACIÓN | AJ87: MXN | AL87: 01 No aplica | AM87: PPD - Pago en Parcialidades o Diferido | AN87: 99 - Por definir | AO87: 0 | AP87: 760 | AQ87: 0 | AR87: 121.6 | AS87: 0 | AT87: 0 | AU87: 0 | AV87: 0 | AW87: 0 | AX87: 0 | AY87: 0 | AZ87: 0 | BA87: 0 | BB87: 881.6 | BC87: =+VLOOKUP(C87,CF!F:F,1,0) -> 5ED4445E-2867-5EC4-85A6-FE1852170793
A88: 11 | B88: 4.0 | C88: C9866177-0FCB-5C70-8A2D-BBE3CC84543E | F88: 06700 | G88: C139686 | H88: 16846 | I88: I - Ingreso | J88: 2025-11-03 09:56:09 | K88: 2025-11-03 10:01:10 | L88: CVD110412TF6 | M88: 601 - General de Ley Personas Morales | N88: CFS1808284P2 | O88: COMUNIDAD FELIZ SERVICIOS TI | P88: XAXX010101000 | Q88: PUBLICO EN GENERAL | R88: 616 - Sin obligaciones fiscales | S88: 06700 | T88: 81112500 - Servicios de alquiler o arrendamiento de licencias de software de computador | U88: Licencia de Software 01 de noviembre de 2025 a 30 de noviembre de 2025. Tu Espac | W88: S01 - Sin efectos fiscales | Y88: 01 | Z88: 11 Noviembre | AA88: 2025 | AB88: CONDICIONES | AD88: VIGENTE | AF88: CANCELABLE SIN ACEPTACIÓN | AJ88: MXN | AL88: 01 No aplica | AM88: PPD - Pago en Parcialidades o Diferido | AN88: 99 - Por definir | AO88: 0 | AP88: 844.83 | AQ88: 0 | AR88: 135.17 | AS88: 0 | AT88: 0 | AU88: 0 | AV88: 0 | AW88: 0 | AX88: 0 | AY88: 0 | AZ88: 0 | BA88: 0 | BB88: 980 | BC88: =+VLOOKUP(C88,CF!F:F,1,0) -> C9866177-0FCB-5C70-8A2D-BBE3CC84543E
A89: 11 | B89: 4.0 | C89: EB10E25E-F23B-5DE3-81D7-AE2290D94E9C | F89: 06700 | G89: C153513 | H89: 16848 | I89: I - Ingreso | J89: 2025-11-03 12:43:09 | K89: 2025-11-03 12:48:10 | L89: CVD110412TF6 | M89: 601 - General de Ley Personas Morales | N89: CFS1808284P2 | O89: COMUNIDAD FELIZ SERVICIOS TI | P89: GUAE870529PX8 | Q89: EDUARDO HERMINIO GUTIERREZ ARTEAGA | R89: 626 - Régimen Simplificado de Confianza | S89: 77760 | T89: 81112500 - Servicios de alquiler o arrendamiento de licencias de software de computador | 81112500 - Servicios de alquiler o arrendamiento de licencias de software de computador | 81112500 - Servicios de alquiler o arrendamiento de licencias de software de computador | 81112500 - Servicios de alquiler o arrendamiento de licencias de software de computador | 81112500 - Servicios de alquiler o arrendamiento de licencias de software de computador | 81112500 - Servicios de alquiler o arrendamiento de licencias de software de computador | U89: Licencia de Software 03 de noviembre de 2025 a 02 de diciembre de 2025. Kaabin J | Sistema de Transferencias y Pagos 03 de noviembre de 2025 a 02 de diciembre de 2 | Sistema de Transferencias y Pagos 03 de noviembre de 2025 a 02 de diciembre de 2 | Licencia de Software 03 de noviembre de 2025 a 02 de diciembre de 2025. Edificio | Sistema de Transferencias y Pagos 03 de noviembre de 2025 a 02 de diciembre de 2 | Licencia de Software 03 de noviembre de 2025 a 02 de diciembre de 2025. Tulum | W89: G03 - Gastos en general | AB89: CONDICIONES | AD89: VIGENTE | AF89: CANCELABLE CON ACEPTACIÓN | AJ89: MXN | AL89: 01 No aplica | AM89: PPD - Pago en Parcialidades o Diferido | AN89: 99 - Por definir | AO89: 0 | AP89: 1311.88 | AQ89: 0 | AR89: 209.9 | AS89: 0 | AT89: 0 | AU89: 0 | AV89: 0 | AW89: 0 | AX89: 0 | AY89: 0 | AZ89: 0 | BA89: 0 | BB89: 1521.78 | BC89: =+VLOOKUP(C89,CF!F:F,1,0) -> EB10E25E-F23B-5DE3-81D7-AE2290D94E9C
A90: 11 | B90: 4.0 | C90: 2ADAEB89-6AA8-53B5-A4C2-06950B619484 | F90: 06700 | G90: C160179 | H90: 16849 | I90: I - Ingreso | J90: 2025-11-03 19:26:00 | K90: 2025-11-03 19:31:01 | L90: CVD110412TF6 | M90: 601 - General de Ley Personas Morales | N90: CFS1808284P2 | O90: COMUNIDAD FELIZ SERVICIOS TI | P90: MSX1311294L1 | Q90: MIRADOR SAN XAVIER | R90: 603 - Personas Morales con Fines no Lucrativos | S90: 76148 | T90: 81112500 - Servicios de alquiler o arrendamiento de licencias de software de computador | 81112500 - Servicios de alquiler o arrendamiento de licencias de software de computador | U90: Sistema de Transferencias y Pagos 03 de noviembre de 2025 a 02 de diciembre de 2 | Licencia de Software 03 de noviembre de 2025 a 02 de diciembre de 2025. CONDOMIN | W90: G03 - Gastos en general | AB90: CONDICIONES | AD90: VIGENTE | AF90: CANCELABLE CON ACEPTACIÓN | AJ90: MXN | AL90: 01 No aplica | AM90: PUE - Pago en Una sola Exhibición | AN90: 03 - Transferencia electrónica de fondos | AO90: 0 | AP90: 2478 | AQ90: 0 | AR90: 396.48 | AS90: 0 | AT90: 0 | AU90: 0 | AV90: 0 | AW90: 0 | AX90: 0 | AY90: 0 | AZ90: 0 | BA90: 0 | BB90: 2874.48 | BC90: =+VLOOKUP(C90,CF!F:F,1,0) -> 2ADAEB89-6AA8-53B5-A4C2-06950B619484
A91: 11 | B91: 4.0 | C91: 0D0A81F4-E4EB-5A7E-A903-459A5B29E215 | F91: 06700 | G91: C160183 | H91: 16850 | I91: I - Ingreso | J91: 2025-11-03 20:09:09 | K91: 2025-11-03 20:14:10 | L91: CVD110412TF6 | M91: 601 - General de Ley Personas Morales | N91: CFS1808284P2 | O91: COMUNIDAD FELIZ SERVICIOS TI | P91: ACF870120RX9 | Q91: ASOCIACION DE COLONOS DEL FRACCIONAMIENTO LOS GAVILANES ORIENTE | R91: 603 - Personas Morales con Fines no Lucrativos | S91: 45645 | T91: 81112500 - Servicios de alquiler o arrendamiento de licencias de software de computador | 81112500 - Servicios de alquiler o arrendamiento de licencias de software de computador | 81112500 - Servicios de alquiler o arrendamiento de licencias de software de computador | U91: Licencia de Software 03 de noviembre de 2025 a 02 de diciembre de 2025. ASOCIACI | Sistema de Transferencias y Pagos 03 de noviembre de 2025 a 02 de diciembre de 2 | Facturación CFDI 4.0 | W91: G03 - Gastos en general | AB91: CONDICIONES | AD91: VIGENTE | AF91: CANCELABLE CON ACEPTACIÓN | AJ91: MXN | AL91: 01 No aplica | AM91: PUE - Pago en Una sola Exhibición | AN91: 03 - Transferencia electrónica de fondos | AO91: 0 | AP91: 9430 | AQ91: 0 | AR91: 1508.8 | AS91: 0 | AT91: 0 | AU91: 0 | AV91: 0 | AW91: 0 | AX91: 0 | AY91: 0 | AZ91: 0 | BA91: 0 | BB91: 10938.8 | BC91: =+VLOOKUP(C91,CF!F:F,1,0) -> 0D0A81F4-E4EB-5A7E-A903-459A5B29E215
A92: 11 | B92: 4.0 | C92: AA06F8CC-5EB7-58E9-99D1-5411BC913C00 | F92: 06700 | G92: C159882 | H92: 16851 | I92: I - Ingreso | J92: 2025-11-04 06:18:13 | K92: 2025-11-04 06:23:14 | L92: CVD110412TF6 | M92: 601 - General de Ley Personas Morales | N92: CFS1808284P2 | O92: COMUNIDAD FELIZ SERVICIOS TI | P92: TPS210716ED2 | Q92: TORRE PANORAMA SANTA FE | R92: 603 - Personas Morales con Fines no Lucrativos | S92: 05348 | T92: 81112500 - Servicios de alquiler o arrendamiento de licencias de software de computador | 81112500 - Servicios de alquiler o arrendamiento de licencias de software de computador | 81112500 - Servicios de alquiler o arrendamiento de licencias de software de computador | U92: Licencia de Software 30 de octubre de 2025 a 29 de noviembre de 2025. TORRE PANO | Sistema de Transferencias y Pagos 30 de octubre de 2025 a 29 de noviembre de 202 | Facturación CFDI 4.0 | W92: G03 - Gastos en general | AB92: CONDICIONES | AD92: VIGENTE | AF92: NO CANCELABLE | AJ92: MXN | AL92: 01 No aplica | AM92: PPD - Pago en Parcialidades o Diferido | AN92: 99 - Por definir | AO92: 0 | AP92: 2300 | AQ92: 0 | AR92: 368 | AS92: 0 | AT92: 0 | AU92: 0 | AV92: 0 | AW92: 0 | AX92: 0 | AY92: 0 | AZ92: 0 | BA92: 0 | BB92: 2668 | BC92: =+VLOOKUP(C92,CF!F:F,1,0) -> AA06F8CC-5EB7-58E9-99D1-5411BC913C00
A93: 11 | B93: 4.0 | C93: 5E280EF3-2E57-5ED1-A7E2-1F306B3932E8 | F93: 06700 | G93: C116875 | H93: 16852 | I93: I - Ingreso | J93: 2025-11-04 06:18:35 | K93: 2025-11-04 06:23:36 | L93: CVD110412TF6 | M93: 601 - General de Ley Personas Morales | N93: CFS1808284P2 | O93: COMUNIDAD FELIZ SERVICIOS TI | P93: CCC1505059V0 | Q93: COLONOS DEL CONDOMINIO LA COLONIA | R93: 603 - Personas Morales con Fines no Lucrativos | S93: 76235 | T93: 81112500 - Servicios de alquiler o arrendamiento de licencias de software de computador | 81112500 - Servicios de alquiler o arrendamiento de licencias de software de computador | U93: Licencia de Software 04 de Noviembre de 2025 a 03 de Diciembre de 2025. Colonos | Facturación CFDI 4.0 | W93: G03 - Gastos en general | AB93: CONDICIONES | AD93: VIGENTE | AF93: NO CANCELABLE | AJ93: MXN | AL93: 01 No aplica | AM93: PPD - Pago en Parcialidades o Diferido | AN93: 99 - Por definir | AO93: 0 | AP93: 1136 | AQ93: 0 | AR93: 181.76 | AS93: 0 | AT93: 0 | AU93: 0 | AV93: 0 | AW93: 0 | AX93: 0 | AY93: 0 | AZ93: 0 | BA93: 0 | BB93: 1317.76 | BC93: =+VLOOKUP(C93,CF!F:F,1,0) -> 5E280EF3-2E57-5ED1-A7E2-1F306B3932E8
A94: 11 | B94: 4.0 | C94: 08430796-88C0-57A7-87D6-803D0931C77C | F94: 06700 | G94: C117954 | H94: 16853 | I94: I - Ingreso | J94: 2025-11-04 06:18:38 | K94: 2025-11-04 06:23:39 | L94: CVD110412TF6 | M94: 601 - General de Ley Personas Morales | N94: CFS1808284P2 | O94: COMUNIDAD FELIZ SERVICIOS TI | P94: XAXX010101000 | Q94: PUBLICO EN GENERAL | R94: 616 - Sin obligaciones fiscales | S94: 06700 | T94: 81112500 - Servicios de alquiler o arrendamiento de licencias de software de computador | U94: Licencia de Software 04 de Noviembre de 2025 a 03 de Diciembre de 2025. Punta Sa | W94: S01 - Sin efectos fiscales | Y94: 01 | Z94: 11 Noviembre | AA94: 2025 | AB94: CONDICIONES | AD94: VIGENTE | AF94: CANCELABLE SIN ACEPTACIÓN | AJ94: MXN | AL94: 01 No aplica | AM94: PPD - Pago en Parcialidades o Diferido | AN94: 99 - Por definir | AO94: 0 | AP94: 1041.38 | AQ94: 0 | AR94: 166.62 | AS94: 0 | AT94: 0 | AU94: 0 | AV94: 0 | AW94: 0 | AX94: 0 | AY94: 0 | AZ94: 0 | BA94: 0 | BB94: 1208 | BC94: =+VLOOKUP(C94,CF!F:F,1,0) -> 08430796-88C0-57A7-87D6-803D0931C77C
A95: 11 | B95: 4.0 | C95: 4B602C4F-66F6-54BF-8AA4-10EEF6D36FB5 | F95: 06700 | G95: C147309 | H95: 16854 | I95: I - Ingreso | J95: 2025-11-04 06:18:40 | K95: 2025-11-04 06:23:41 | L95: CVD110412TF6 | M95: 601 - General de Ley Personas Morales | N95: CFS1808284P2 | O95: COMUNIDAD FELIZ SERVICIOS TI | P95: XAXX010101000 | Q95: PUBLICO EN GENERAL | R95: 616 - Sin obligaciones fiscales | S95: 06700 | T95: 81112500 - Servicios de alquiler o arrendamiento de licencias de software de computador | U95: Licencia de Software 04 de Noviembre de 2025 a 03 de Diciembre de 2025. PLAYA TE | W95: S01 - Sin efectos fiscales | Y95: 01 | Z95: 11 Noviembre | AA95: 2025 | AB95: CONDICIONES | AD95: VIGENTE | AF95: CANCELABLE SIN ACEPTACIÓN | AJ95: MXN | AL95: 01 No aplica | AM95: PPD - Pago en Parcialidades o Diferido | AN95: 99 - Por definir | AO95: 0 | AP95: 468 | AQ95: 0 | AR95: 74.88 | AS95: 0 | AT95: 0 | AU95: 0 | AV95: 0 | AW95: 0 | AX95: 0 | AY95: 0 | AZ95: 0 | BA95: 0 | BB95: 542.88 | BC95: =+VLOOKUP(C95,CF!F:F,1,0) -> 4B602C4F-66F6-54BF-8AA4-10EEF6D36FB5
A96: 11 | B96: 4.0 | C96: 74C1082E-124E-5C32-971D-86CA270D638E | F96: 06700 | G96: C146649 | H96: 16855 | I96: I - Ingreso | J96: 2025-11-04 06:18:42 | K96: 2025-11-04 06:23:43 | L96: CVD110412TF6 | M96: 601 - General de Ley Personas Morales | N96: CFS1808284P2 | O96: COMUNIDAD FELIZ SERVICIOS TI | P96: XAXX010101000 | Q96: PUBLICO EN GENERAL | R96: 616 - Sin obligaciones fiscales | S96: 06700 | T96: 81112500 - Servicios de alquiler o arrendamiento de licencias de software de computador | U96: Licencia de Software 04 de Noviembre de 2025 a 03 de Diciembre de 2025. Residenc | W96: S01 - Sin efectos fiscales | Y96: 01 | Z96: 11 Noviembre | AA96: 2025 | AB96: CONDICIONES | AD96: VIGENTE | AF96: CANCELABLE SIN ACEPTACIÓN | AJ96: MXN | AL96: 01 No aplica | AM96: PPD - Pago en Parcialidades o Diferido | AN96: 99 - Por definir | AO96: 0 | AP96: 995.69 | AQ96: 0 | AR96: 159.31 | AS96: 0 | AT96: 0 | AU96: 0 | AV96: 0 | AW96: 0 | AX96: 0 | AY96: 0 | AZ96: 0 | BA96: 0 | BB96: 1155 | BC96: =+VLOOKUP(C96,CF!F:F,1,0) -> 74C1082E-124E-5C32-971D-86CA270D638E
A97: 11 | B97: 4.0 | C97: DEC11B7B-2056-5AED-BC52-73212B0625D6 | F97: 06700 | G97: C117982 | H97: 16856 | I97: I - Ingreso | J97: 2025-11-04 06:18:44 | K97: 2025-11-04 06:23:45 | L97: CVD110412TF6 | M97: 601 - General de Ley Personas Morales | N97: CFS1808284P2 | O97: COMUNIDAD FELIZ SERVICIOS TI | P97: XAXX010101000 | Q97: PUBLICO EN GENERAL | R97: 616 - Sin obligaciones fiscales | S97: 06700 | T97: 81112500 - Servicios de alquiler o arrendamiento de licencias de software de computador | U97: Licencia de Software 04 de Noviembre de 2025 a 03 de Diciembre de 2025. Mar de G | W97: S01 - Sin efectos fiscales | Y97: 01 | Z97: 11 Noviembre | AA97: 2025 | AB97: CONDICIONES | AD97: VIGENTE | AF97: CANCELABLE SIN ACEPTACIÓN | AJ97: MXN | AL97: 01 No aplica | AM97: PPD - Pago en Parcialidades o Diferido | AN97: 99 - Por definir | AO97: 0 | AP97: 820 | AQ97: 0 | AR97: 131.2 | AS97: 0 | AT97: 0 | AU97: 0 | AV97: 0 | AW97: 0 | AX97: 0 | AY97: 0 | AZ97: 0 | BA97: 0 | BB97: 951.2 | BC97: =+VLOOKUP(C97,CF!F:F,1,0) -> DEC11B7B-2056-5AED-BC52-73212B0625D6
A98: 11 | B98: 4.0 | C98: AA92F248-09BB-5F3B-A038-8762B0034F79 | F98: 06700 | G98: C119120 | H98: 16857 | I98: I - Ingreso | J98: 2025-11-04 06:18:46 | K98: 2025-11-04 06:23:47 | L98: CVD110412TF6 | M98: 601 - General de Ley Personas Morales | N98: CFS1808284P2 | O98: COMUNIDAD FELIZ SERVICIOS TI | P98: PHR191011N8A | Q98: PUNTO HORIZONTE RESIDENCIAL | R98: 603 - Personas Morales con Fines no Lucrativos | S98: 72830 | T98: 81112500 - Servicios de alquiler o arrendamiento de licencias de software de computador | U98: Licencia de Software 04 de Noviembre de 2025 a 03 de Diciembre de 2025. PUNTO HO | W98: G03 - Gastos en general | AB98: CONDICIONES | AD98: VIGENTE | AF98: CANCELABLE CON ACEPTACIÓN | AJ98: MXN | AL98: 01 No aplica | AM98: PPD - Pago en Parcialidades o Diferido | AN98: 99 - Por definir | AO98: 0 | AP98: 1690 | AQ98: 0 | AR98: 270.4 | AS98: 0 | AT98: 0 | AU98: 0 | AV98: 0 | AW98: 0 | AX98: 0 | AY98: 0 | AZ98: 0 | BA98: 0 | BB98: 1960.4 | BC98: =+VLOOKUP(C98,CF!F:F,1,0) -> AA92F248-09BB-5F3B-A038-8762B0034F79
A99: 11 | B99: 4.0 | C99: 5F11AAB1-F2B8-5D26-9FED-2CCF3A649BFB | F99: 06700 | G99: C67242 | H99: 16858 | I99: I - Ingreso | J99: 2025-11-04 06:18:48 | K99: 2025-11-04 06:23:49 | L99: CVD110412TF6 | M99: 601 - General de Ley Personas Morales | N99: CFS1808284P2 | O99: COMUNIDAD FELIZ SERVICIOS TI | P99: XAXX010101000 | Q99: PUBLICO EN GENERAL | R99: 616 - Sin obligaciones fiscales | S99: 06700 | T99: 81112500 - Servicios de alquiler o arrendamiento de licencias de software de computador | U99: Licencia de Software 04 de Noviembre de 2025 a 03 de Diciembre de 2025. San Agus | W99: S01 - Sin efectos fiscales | Y99: 01 | Z99: 11 Noviembre | AA99: 2025 | AB99: CONDICIONES | AD99: VIGENTE | AF99: CANCELABLE SIN ACEPTACIÓN | AJ99: MXN | AL99: 01 No aplica | AM99: PPD - Pago en Parcialidades o Diferido | AN99: 99 - Por definir | AO99: 0 | AP99: 938.08 | AQ99: 0 | AR99: 150.09 | AS99: 0 | AT99: 0 | AU99: 0 | AV99: 0 | AW99: 0 | AX99: 0 | AY99: 0 | AZ99: 0 | BA99: 0 | BB99: 1088.17 | BC99: =+VLOOKUP(C99,CF!F:F,1,0) -> 5F11AAB1-F2B8-5D26-9FED-2CCF3A649BFB
A100: 11 | B100: 4.0 | C100: 5A68E512-F6C3-545F-89C5-B0A9D99761B6 | F100: 06700 | G100: C117619 | H100: 16859 | I100: I - Ingreso | J100: 2025-11-04 06:18:50 | K100: 2025-11-04 06:23:51 | L100: CVD110412TF6 | M100: 601 - General de Ley Personas Morales | N100: CFS1808284P2 | O100: COMUNIDAD FELIZ SERVICIOS TI | P100: IVV200220PE3 | Q100: INNOVACIONES 20 VEINTE | R100: 601 - General de Ley Personas Morales | S100: 03330 | T100: 81112500 - Servicios de alquiler o arrendamiento de licencias de software de computador | 81112500 - Servicios de alquiler o arrendamiento de licencias de software de computador | U100: Licencia de Software 04 de Noviembre de 2025 a 03 de Diciembre de 2025. CASA COL | Sistema de Transferencias y Pagos 04 de Noviembre de 2025 a 03 de Diciembre de 2 | W100: G03 - Gastos en general | AB100: CONDICIONES | AD100: VIGENTE | AF100: CANCELABLE CON ACEPTACIÓN | AJ100: MXN | AL100: 01 No aplica | AM100: PPD - Pago en Parcialidades o Diferido | AN100: 99 - Por definir | AO100: 0 | AP100: 1592 | AQ100: 0 | AR100: 254.72 | AS100: 0 | AT100: 0 | AU100: 0 | AV100: 0 | AW100: 0 | AX100: 0 | AY100: 0 | AZ100: 0 | BA100: 0 | BB100: 1846.72 | BC100: =+VLOOKUP(C100,CF!F:F,1,0) -> 5A68E512-F6C3-545F-89C5-B0A9D99761B6
A101: 11 | B101: 4.0 | C101: 57C39F3D-DC7A-58F4-80E6-327786460A7F | F101: 06700 | G101: C119122 | H101: 16860 | I101: I - Ingreso | J101: 2025-11-04 06:18:53 | K101: 2025-11-04 06:23:53 | L101: CVD110412TF6 | M101: 601 - General de Ley Personas Morales | N101: CFS1808284P2 | O101: COMUNIDAD FELIZ SERVICIOS TI | P101: VHO180510SV1 | Q101: THE VILLAS HOA | R101: 603 - Personas Morales con Fines no Lucrativos | S101: 23473 | T101: 81112500 - Servicios de alquiler o arrendamiento de licencias de software de computador | 81112500 - Servicios de alquiler o arrendamiento de licencias de software de computador | 81112500 - Servicios de alquiler o arrendamiento de licencias de software de computador | U101: Facturación CFDI 4.0 | Licencia de Software 04 de Noviembre de 2025 a 03 de Diciembre de 2025. The Vill | Sistema de Transferencias y Pagos 04 de Noviembre de 2025 a 03 de Diciembre de 2 | W101: G03 - Gastos en general | AB101: CONDICIONES | AD101: VIGENTE | AF101: CANCELABLE CON ACEPTACIÓN | AJ101: MXN | AL101: 01 No aplica | AM101: PPD - Pago en Parcialidades o Diferido | AN101: 99 - Por definir | AO101: 0 | AP101: 1650 | AQ101: 0 | AR101: 264 | AS101: 0 | AT101: 0 | AU101: 0 | AV101: 0 | AW101: 0 | AX101: 0 | AY101: 0 | AZ101: 0 | BA101: 0 | BB101: 1914 | BC101: =+VLOOKUP(C101,CF!F:F,1,0) -> 57C39F3D-DC7A-58F4-80E6-327786460A7F
...

Sheet CF
A1: ID Invoice | B1: Fecha creación | C1: ID Account | D1: País | E1: Monto | F1: factura | G1: Descripción | H1: Nombre Comunidad | I1: ID Comunidad | J1: mes inicial | K1: mes final | L1: package_type | M1: row_num
A2: 289443 | B2: 45891.56 | C2: 126684 | D2: México | E2: 2867.52 | F2: 000AF201-F180-50C8-AF5B-8DE688224AF8 | G2: Licencia de Software 22 de agosto de 2025 a 21 de septiembre de 2025. CONDOMINIO TRES LAS TORRES | H2: CONDOMINIO TRES LAS TORRES | I2: 123006 | J2: 45870 | K2: 45870 | L2: Gasto Común | M2: 1
A3: 282975 | B3: 45876.557 | C3: 76969 | D3: México | E3: 1159.97 | F3: 001A8D03-4025-5454-9E88-AD45CE32C66A | G3: Licencia de Software 07 de agosto de 2025 a 06 de septiembre de 2025. Villa Residencial Tamarindo A.C. | H3: Villa Residencial Tamarindo A.C. | I3: 78429 | J3: 45870 | K3: 45870 | M3: 1
A4: 289753 | B4: 45894.564 | C4: 134077 | D4: México | E4: 250.56 | F4: 001B56A2-5365-559A-820B-5675CDE37D38 | G4: Licencia de Software 24 de agosto de 2025 a 23 de septiembre de 2025. CERRADA CARLOTA | H4: CERRADA CARLOTA | I4: 133768 | J4: 45870 | K4: 45870 | M4: 1
A5: 243694 | B5: 45719.621 | C5: 32781 | D5: México | E5: 14743.65 | F5: 00203BFD-C832-5F7D-9A62-E3F9E0932A80 | G5: Licencia de Software 03 de marzo de 2025 a 02 de abril de 2025. Fraccionamiento Residencial Capital Sur AC | H5: Fraccionamiento Residencial Capital Sur AC | I5: 33119 | J5: 45717 | K5: 45717 | M5: 1
A6: 272166 | B6: 45838.603 | C6: 116592 | D6: México | E6: 1786.4 | F6: 002AFA5F-26DF-5F2E-AD5F-1E4D78774AF1 | G6: Facturación CFDI 4.0 | H6: Unión de Condóminos Central Plaza Durango | I6: 113909 | J6: 45809 | K6: 45809 | M6: 1
A7: 299544 | B7: 45918.911 | C7: 117007 | D7: México | E7: 1795.6 | F7: 00305288-8322-50AA-8AB9-E8392C65F79D | G7: Sistema de Transferencias y Pagos 18 de septiembre de 2025 a 17 de octubre de 2025. RESIDENCIAL ZETERO, A.C. | H7: RESIDENCIAL ZETERO, A.C. | I7: 114207 | J7: 45901 | K7: 45901 | M7: 1
A8: 248651 | B8: 45756.898 | C8: 104062 | D8: México | E8: 1786.39 | F8: 0050F6D4-A21D-54D0-BA30-420D18A9040A | G8: 1.82% dcto. Desde 01/04/2025 | H8: Bosques Aile | I8: 103666 | J8: 45748 | K8: 45748 | M8: 1
A9: 271364 | B9: 45833.62 | C9: 108715 | D9: México | E9: 2793.78 | F9: 005AFAA1-619D-5729-AEFB-10786CAEB340 | G9: Licencia de Software 25 de junio de 2025 a 24 de julio de 2025. Residencial Quetzalcóatl | H9: Residencial Quetzalcóatl | I9: 107494 | J9: 45809 | K9: 45809 | M9: 1
A10: 290858 | B10: 45897.688 | C10: 145791 | D10: México | E10: 3166.8 | F10: 007BCB9D-DAF7-5808-BB03-26AF07304BF1 | G10: Licencia de Software 28 de agosto de 2025 a 27 de septiembre de 2025. Hir Botanik | H10: Hir Botanik | I10: 141255 | J10: 45870 | K10: 45870 | M10: 1
A11: 239239 | B11: 45681.565 | C11: 83075 | D11: México | E11: 1160 | F11: 00810A8B-7A5B-54EC-8E9D-743795FD737C | G11: Licencia de Software 24 de enero de 2025 a 23 de febrero de 2025. Privada Rio Rucueva | H11: Privada Rio Rucueva | I11: 84731 | J11: 45658 | K11: 45658 | M11: 1
A12: 235801 | B12: 45670.563 | C12: 106273 | D12: México | E12: 890.88 | F12: 00835A57-734F-5A34-8D92-B7D8CA65063B | G12: Licencia de Software 12 de enero de 2025 a 11 de febrero de 2025. CONDOMINIO 3 TRES MAESTRO PUNTO SUR | H12: CONDOMINIO MAESTRO PUNTO SUR 724 Torre 1 | I12: 105448 | J12: 45658 | K12: 45658 | M12: 1
A13: 239732 | B13: 45695.621 | C13: 115947 | D13: México | E13: 1339.8 | F13: 00896418-C4C6-513B-85EE-31F76A6F86AB | G13: Facturación CFDI 4.0 | H13: Boskia sur residencial | I13: 113450 | J13: 45689 | K13: 45689 | M13: 1
A14: 293436 | B14: 45908.561 | C14: 76969 | D14: México | E14: 1159.97 | F14: 009C35B8-81C2-59EE-8236-34BFAE0F6879 | G14: Licencia de Software 07 de septiembre de 2025 a 06 de octubre de 2025. Villa Residencial Tamarindo A.C. | H14: Villa Residencial Tamarindo A.C. | I14: 78429 | J14: 45901 | K14: 45901 | M14: 1
A15: 255826 | B15: 45782.597 | C15: 117681 | D15: México | E15: 7434.44 | F15: 00A76957-DC73-5A2D-88EC-9C613956818E | G15: Licencia de Software 01 de mayo de 2025 a 31 de mayo de 2025. Garza Sada | H15: Garza Sada | I15: 114745 | J15: 45778 | K15: 45778 | L15: Gasto Común | M15: 1
A16: 270604 | B16: 45831.586 | C16: 127047 | D16: México | E16: 5762.88 | F16: 00B0E36F-31DE-5633-8859-422B1653A1FB | G16: Facturación CFDI 4.0 | H16: MACGRIPI HORIZONTES | I16: 123303 | J16: 45809 | K16: 45809 | M16: 1
A17: 320864 | B17: 45980.574 | C17: 115785 | D17: México | E17: 1067.2 | F17: 00B466B6-0E94-543C-B281-7A1AEA279699 | G17: Sistema de Transferencias y Pagos 19 de Noviembre de 2025 a 18 de Diciembre de 2025. Mi Plaza Los Ángeles | H17: Mi Plaza Los Ángeles | I17: 113332 | J17: 45962 | K17: 45962 | M17: 1
A18: 300513 | B18: 45924.541 | C18: 116207 | D18: México | E18: 2267.36 | F18: 00BABFBD-3115-5243-A127-53079CC3C415 | G18: Facturación CFDI 4.0 | H18: Monte Alban | I18: 113639 | J18: 45901 | K18: 45901 | M18: 1
A19: 247471 | B19: 45740.542 | C19: 72486 | D19: México | E19: 3174.92 | F19: 00BC8F23-736E-56BD-803A-D66918419D96 | G19: Licencia de Software 24 de marzo de 2025 a 23 de abril de 2025. CONDOMINIO CALABRIA AC | H19: CONDOMINIO CALABRIA AC | I19: 73549 | J19: 45717 | K19: 45717 | M19: 1
A20: 323991 | B20: 45992.533 | C20: 98822 | D20: México | E20: 1995.2 | F20: 00BF6638-9918-5097-8628-6A9ED3F5681D | G20: Licencia de Software 01 de Diciembre de 2025 a 31 de Diciembre de 2025. CONDOMINO SAN JERONIMO ARBOLEDA, A.C. | H20: CONDOMINO SAN JERONIMO ARBOLEDA, A.C. | I20: 99394 | J20: 45992 | K20: 45992 | M20: 1
A21: 255845 | B21: 45782.597 | C21: 118504 | D21: México | E21: 11851.72 | F21: 00D37667-28B2-54B4-B9A2-42737B2D4FB8 | G21: Sistema de Transferencias y Pagos 03 de mayo de 2025 a 02 de junio de 2025. TERRA VISTA RESIDENCIAL | H21: CONDOMINIO 2 (DOS) DEL FRACCIONAMIENTO TERRA VISTA RESIDENCIAL | I21: 89029 | J21: 45778 | K21: 45778 | M21: 1
A22: 291495 | B22: 45901.551 | C22: 116608 | D22: México | E22: 1158.66 | F22: 00E0A3FF-D7E2-5C4C-BB31-06104C26AA06 | G22: Licencia de Software 01 de septiembre de 2025 a 30 de septiembre de 2025. El Vergel Residencial | H22: El Vergel Residencial | I22: 113922 | J22: 45901 | K22: 45901 | M22: 1
A23: 274143 | B23: 45847.686 | C23: 67774 | D23: México | E23: 329.45 | F23: 00FBC90C-BDF5-5B73-840C-02F327695880 | G23: Licencia de Software 09 de julio de 2025 a 08 de agosto de 2025. Nogal-Las Ceibas | H23: Nogal-Las Ceibas | I23: 60651 | J23: 45839 | K23: 45839 | M23: 1
A24: 264462 | B24: 45813.595 | C24: 117902 | D24: México | E24: 1545.12 | F24: 0114CD79-C489-54F2-A3FE-2D12F8347F08 | G24: Licencia de Software 05 de junio de 2025 a 04 de julio de 2025. ASOCIACIÓN DE COLONOS TERRASOLES | H24: ASOCIACIÓN DE COLONOS TERRASOLES | I24: 114926 | J24: 45809 | K24: 45809 | M24: 1
A25: 231734 | B25: 45632.779 | C25: 116209 | D25: México | E25: 2537.6 | F25: 0119EA6A-673B-5134-94B9-9D61792DBC98 | G25: Sistema de Transferencias y Pagos 25 de diciembre de 2024 a 24 de enero de 2025. | H25: Reserva de Palmillas | I25: 113641 | J25: 45627 | K25: 45627 | M25: 1
A26: 262577 | B26: 45803.601 | C26: 117853 | D26: México | E26: 6164 | F26: 011AA9BA-6C7E-50FA-90AC-072E9A071AD9 | G26: Sistema de Transferencias y Pagos 25 de mayo de 2025 a 24 de junio de 2025. BOLONGO RESORT VISION PATRIMONIAL | H26: BOLONGO RESORT VISION PATRIMONIAL | I26: 114889 | J26: 45778 | K26: 45778 | M26: 1
A27: 274907 | B27: 45852.587 | C27: 15991 | D27: México | E27: 1352.7 | F27: 011CF016-9748-519F-A7ED-7F37B28B7C31 | G27: Licencia de Software 12 de julio de 2025 a 11 de agosto de 2025. CONDOMINIO COVE HAUS | H27: CONDOMINIO COVE HAUS | I27: 16163 | J27: 45839 | K27: 45839 | M27: 1
A28: 232018 | B28: 45656.689 | C28: 54252 | D28: México | E28: 81900 | F28: 01233254-3BAC-5FCA-A11D-439EC403D7A6 | G28: Licencia de Software 12 de diciembre de 2024 a 11 de diciembre de 2025. Asociación del Desarrollo Entorno Habitacional Camino Real Jesús Maria | H28: Asociación del Desarrollo Entorno Habitacional Camino Real Jesús Maria | I28: 54555 | J28: 45627 | K28: 45962 | L28: Gasto Común | M28: 1
A29: 261241 | B29: 45793.615 | C29: 78024 | D29: México | E29: 2654.08 | F29: 0124E7CD-8562-5A1D-BAE5-BFD15A833ECC | G29: Licencia de Software 16 de mayo de 2025 a 15 de junio de 2025. Residencial Fuentes de Santa Elena | H29: Residencial Fuentes de Santa Elena | I29: 79550 | J29: 45778 | K29: 45778 | M29: 1
A30: 314140 | B30: 45968.52 | C30: 116671 | D30: México | E30: 1600.8 | F30: 01263635-7225-508F-942F-0E3D0990F48C | G30: Licencia de Software 07 de Noviembre de 2025 a 06 de Diciembre de 2025. Vista Alta | H30: Vista Alta | I30: 113959 | J30: 45962 | K30: 45962 | M30: 1
A31: 231716 | B31: 45632.782 | C31: 116524 | D31: México | E31: 1159.9 | F31: 01372829-3D43-58FC-97E6-0B686E1BFAE0 | G31: Licencia de Software 30 de diciembre de 2024 a 29 de enero de 2025. | H31: Residencial San Pedro de los Pinos | I31: 113890 | J31: 45627 | K31: 45627 | M31: 1
A32: 247418 | B32: 45740.541 | C32: 32154 | D32: México | E32: 2016.08 | F32: 01379CFD-05E2-5668-BC01-013D850DBA90 | G32: Licencia de Software 22 de marzo de 2025 a 21 de abril de 2025. RESIDENCIAL CIMA AZCAPOTZALCO | H32: RESIDENCIAL CIMA AZCAPOTZALCO | I32: 74105 | J32: 45717 | K32: 45717 | M32: 1
A33: 299867 | B33: 45922.627 | C33: 72513 | D33: México | E33: 696 | F33: 0140079C-5457-567C-9CA1-D357BA2DCC87 | G33: Licencia de Software 20 de septiembre de 2025 a 19 de octubre de 2025. Zacatecas 123 | H33: Zacatecas 123 | I33: 73610 | J33: 45901 | K33: 45901 | M33: 1
A34: 314155 | B34: 45968.52 | C34: 39579 | D34: México | E34: 1206.4 | F34: 014422DC-5C52-5453-AB51-84F5B0DE0523 | G34: Licencia de Software 07 de Noviembre de 2025 a 06 de Diciembre de 2025. Residentes High Gardens AC | H34: Residentes High Gardens AC | I34: 39950 | J34: 45962 | K34: 45962 | M34: 1
A35: 284064 | B35: 45882.566 | C35: 117879 | D35: México | E35: 4721.2 | F35: 01586A59-C5F9-5F8A-B1AB-992446C61798 | G35: Licencia de Software 13 de agosto de 2025 a 12 de septiembre de 2025. QUINTA LOMA REAL | H35: QUINTA LOMA REAL | I35: 121621 | J35: 45870 | K35: 45870 | M35: 1
A36: 323561 | B36: 45989.502 | C36: 115846 | D36: México | E36: 2052.88 | F36: 015BBA1D-52D1-5594-8B6E-1CC649784883 | G36: Licencia de Software 28 de Noviembre de 2025 a 27 de Diciembre de 2025. Coto Tehuantepec P. en C. | H36: Coto Tehuantepec P. en C. | I36: 113379 | J36: 45962 | K36: 45962 | M36: 1
A37: 283807 | B37: 45881.565 | C37: 54401 | D37: México | E37: 1969.68 | F37: 0163C574-55CC-50D8-86A4-68D80AFCB9D9 | G37: Facturación CFDI 4.0 | H37: VALLE DE LOS CLAVELES P EN C | I37: 54673 | J37: 45870 | K37: 45870 | M37: 1
A38: 231454 | B38: 45628.587 | C38: 107197 | D38: México | E38: 968.88 | F38: 017C6F6D-8317-556E-AE64-3B061FB3CADE | G38: Licencia de Software 02 de diciembre de 2024 a 01 de enero de 2025. Grand Cousin | H38: Grand Cousin | I38: 106207 | J38: 45627 | K38: 45627 | M38: 1
A39: 288514 | B39: 45888.555 | C39: 142854 | D39: México | E39: 1828.16 | F39: 018F4ED9-BDC5-5783-A93A-6CFB37C4D476 | G39: Licencia de Software 14 de agosto de 2025 a 13 de septiembre de 2025. CONDOMINIOS ALTAVISTA NORTE TIJUANA | H39: CONDOMINIOS ALTAVISTA NORTE TIJUANA | I39: 138252 | J39: 45870 | K39: 45870 | M39: 1
A40: 288383 | B40: 45887.757 | C40: 143360 | D40: México | E40: 464 | F40: 01939BFE-4512-5AFB-9B3C-2593D18495AD | G40: Licencia de Software 17 de agosto de 2025 a 16 de septiembre de 2025. ASOCIACION DE INDUSTRIALES DEL FRACC INDUSTRIAL LOGISTIC AEROPUERTO AC | H40: ASOCIACION DE INDUSTRIALES DEL FRACC INDUSTRIAL LOGISTIC AEROPUERTO AC | I40: 138721 | J40: 45870 | K40: 45870 | M40: 1
... A42: 311420 | B42: 45957.509 | C42: 115848 | D42: México | E42: 1075.32 | F42: 01AD3E2F-1BC8-5551-9351-736176B2227A | G42: Licencia de Software 27 de Octubre de 2025 a 26 de Noviembre de 2025. ASOCIACIÓN DE COLONOS PUNTA MANANTIAL, A.C. | H42: ASOCIACIÓN DE COLONOS PUNTA MANANTIAL, A.C. | I42: 113380 | J42: 45931 | K42: 45931 | M42: 1
A43: 305445 | B43: 45945.572 | C43: 32781 | D43: México | E43: 3480 | F43: 01BC874C-2300-5348-BF73-5D52FF5284FB | G43: Control de acceso mes 10/2025. Fraccionamiento Residencial Capital Sur AC | H43: Fraccionamiento Residencial Capital Sur AC | I43: 33119 | J43: 45931 | K43: 45931 | L43: Control de acceso | M43: 1
A44: 273670 | B44: 45845.876 | C44: 6514 | D44: México | E44: 696 | F44: 01C1EA87-8ECC-5462-AAA9-0438CA7BADC3 | G44: Licencia de Software 07 de julio de 2025 a 06 de agosto de 2025. Asociación de Condominos de Borgo Frassino A.C. | H44: Asociación de Condominos de Borgo Frassino A.C. | I44: 6687 | J44: 45839 | K44: 45839 | M44: 1
A45: 320230 | B45: 45978.517 | C45: 59382 | D45: México | E45: 301.6 | F45: 01CCE73E-9EBD-5F88-BD73-0EF68118148D | G45: Licencia de Software 16 de Noviembre de 2025 a 15 de Diciembre de 2025. EDIFICIO PALMA NOVA | H45: EDIFICIO PALMA NOVA | I45: 59654 | J45: 45962 | K45: 45962 | M45: 1
A46: 290739 | B46: 45897.621 | C46: 139028 | D46: México | E46: 1160 | F46: 01D33A3C-0DF5-59F7-965C-F75095C4B65E | G46: Licencia de Software 28 de agosto de 2025 a 27 de septiembre de 2025. CENTRO COMERCIAL LA HERRADURA | H46: CENTRO COMERCIAL LA HERRADURA | I46: 134888 | J46: 45870 | K46: 45870 | M46: 1
A47: 279087 | B47: 45855.622 | C47: 118560 | D47: México | E47: 1392 | F47: 01D6776B-F2A8-5935-8626-B7284B405CC6 | G47: Licencia de Software 17 de julio de 2025 a 16 de agosto de 2025. FRACCIONAMIENTO LA ILUSIÓN CASAS | H47: FRACCIONAMIENTO LA ILUSIÓN CASAS | I47: 115455 | J47: 45839 | K47: 45839 | M47: 1
A48: 231896 | B48: 45632.628 | C48: 87792 | D48: México | E48: 696 | F48: 01D8BA9C-ADF4-5BA6-A4DF-A6789B8144D3 | G48: Licencia de Software 07 de diciembre de 2024 a 06 de enero de 2025. | H48: TORRES REAL VIZCAYA | I48: 88922 | J48: 45627 | K48: 45627 | L48: Gasto Común | M48: 1
A49: 262526 | B49: 45803.601 | C49: 117815 | D49: México | E49: 1172.55 | F49: 01E6411E-9389-5995-90E3-79176FA60D4A | G49: Licencia de Software 25 de mayo de 2025 a 24 de junio de 2025. CONDOMINIO MARROQUÍ CENTRO HISTÓRICO A.C. | H49: CONDOMINIO MARROQUÍ CENTRO HISTÓRICO A.C. | I49: 24442 | J49: 45778 | K49: 45778 | L49: Gasto Común | M49: 1
A50: 269429 | B50: 45824.78 | C50: 57050 | D50: México | E50: 826.6 | F50: 01FDDE5A-A326-5592-A158-EF548E17F124 | G50: Licencia de Software 16 de junio de 2025 a 15 de julio de 2025. Fuente De Cibeles | H50: Fuente De Cibeles | I50: 57322 | J50: 45809 | K50: 45809 | M50: 1
A51: 239733 | B51: 45695.621 | C51: 93831 | D51: México | E51: 1160 | F51: 0210D35C-DF50-54A0-892F-2CF467ADB4E6 | G51: Licencia de Software 07 de febrero de 2025 a 06 de marzo de 2025. ZIBÁ Condos & Suites Huatulco | H51: ZIBÁ Condos & Suites Huatulco | I51: 95159 | J51: 45689 | K51: 45689 | M51: 1
A52: 239493 | B52: 45686.558 | C52: 115836 | D52: México | E52: 918.72 | F52: 0211D5B3-FF41-5DD3-B879-8B9850B8219E | G52: Sistema de Transferencias y Pagos 28 de enero de 2025 a 27 de febrero de 2025. Mayapan | H52: Mayapan | I52: 113371 | J52: 45658 | K52: 45658 | M52: 1
A53: 296333 | B53: 45915.62 | C53: 136092 | D53: México | E53: 2996.28 | F53: 021B7381-5BD1-5809-8A2C-202B33439E95 | G53: Sistema de Transferencias y Pagos 14 de septiembre de 2025 a 13 de octubre de 2025. Condominio Amani Torre A A.C. | H53: Condominio Amani Torre A A.C. | I53: 131786 | J53: 45901 | K53: 45901 | M53: 1
A54: 232028 | B54: 45638.703 | C54: 117988 | D54: México | E54: 696 | F54: 022EE8A0-C76C-5D89-BF1F-7A621911D876 | G54: Licencia de Software 14 de diciembre de 2024 a 13 de enero de 2025. | H54: Residencial Zempoala 8 | I54: 69288 | J54: 45627 | K54: 45627 | L54: Gasto Común | M54: 1
A55: 243220 | B55: 45709.604 | C55: 72513 | D55: México | E55: 696 | F55: 0234C3A3-B45C-5ACE-B4D8-9861AC9AD9D9 | G55: Licencia de Software 20 de febrero de 2025 a 19 de marzo de 2025. Zacatecas 123 | H55: Zacatecas 123 | I55: 73610 | J55: 45689 | K55: 45689 | M55: 1
A56: 260934 | B56: 45792.591 | C56: 89112 | D56: México | E56: 835.2 | F56: 02352224-BBC5-57F6-A62E-B286D239DCF4 | G56: Licencia de Software 15 de mayo de 2025 a 14 de junio de 2025. Tu Espacio Eje Central 78 - Torre H | H56: Tu Espacio Eje Central 78 - Torre H | I56: 90440 | J56: 45778 | K56: 45778 | M56: 1
A57: 249063 | B57: 45761.608 | C57: 54401 | D57: México | E57: 1969.68 | F57: 02355BAF-C04B-51DE-8FB7-74662CEFD427 | G57: Facturación CFDI 4.0 | H57: VALLE DE LOS CLAVELES P EN C | I57: 54673 | J57: 45748 | K57: 45748 | L57: Factura CFDI 4.0 | M57: 1
A58: 231698 | B58: 45632.718 | C58: 106076 | D58: México | E58: 278.4 | F58: 023B85D4-43FF-5647-B08E-2383D195F899 | G58: Licencia de Software 13 de diciembre de 2024 a 12 de enero de 2025. | H58: LUNATERRA | I58: 105251 | J58: 45627 | K58: 45627 | M58: 1
A59: 288555 | B59: 45888.556 | C59: 118904 | D59: México | E59: 1392 | F59: 0253C331-35F3-567B-A413-6BC623FFDC4D | G59: Licencia de Software 19 de agosto de 2025 a 18 de septiembre de 2025. FRACCIONAMIENTO LA ILUSIÓN TORRE | H59: FRACCIONAMIENTO LA ILUSIÓN TORRE | I59: 115727 | J59: 45870 | K59: 45870 | M59: 1
A60: 303106 | B60: 45936.575 | C60: 140379 | D60: México | E60: 452.4 | F60: 026067A1-52EB-5A0B-B799-79F7B85E10AC | G60: Licencia de Software 05 de Octubre de 2025 a 04 de Noviembre de 2025. Privada Framboyanes | H60: Privada Framboyanes | I60: 135942 | J60: 45931 | K60: 45931 | M60: 1
A61: 278684 | B61: 45853.694 | C61: 116395 | D61: México | E61: 696 | F61: 026DCEA8-EA97-5968-A0EC-A539659D3C0D | G61: Licencia de Software 15 de julio de 2025 a 14 de agosto de 2025. LUZ MARIA V | H61: LUZ MARIA V | I61: 113776 | J61: 45839 | K61: 45839 | M61: 1
A62: 299882 | B62: 45922.627 | C62: 106411 | D62: México | E62: 588.12 | F62: 029C17F8-3231-5126-AA0B-E6A8542F3D39 | G62: Licencia de Software 20 de septiembre de 2025 a 19 de octubre de 2025. BUREA APARTMENTS | H62: BUREA APARTMENTS | I62: 105552 | J62: 45901 | K62: 45901 | M62: 1
A63: 272149 | B63: 45838.604 | C63: 90731 | D63: México | E63: 2171.52 | F63: 02AB9C76-DE04-5FE1-ACC5-F5C451589353 | G63: Licencia de Software 28 de junio de 2025 a 27 de julio de 2025. FUENTE CIBELES | H63: FUENTE CIBELES | I63: 91960 | J63: 45809 | K63: 45809 | M63: 1
A64: 231791 | B64: 45632.763 | C64: 116353 | D64: México | E64: 1494.8 | F64: 02AE6B11-7479-54A8-80FC-B4B3A594E363 | G64: Licencia de Software 15 de diciembre de 2024 a 14 de enero de 2025. | H64: REAL DE SAN ANTÓN | I64: 113734 | J64: 45627 | K64: 45627 | M64: 1
A65: 312045 | B65: 45959.615 | C65: 80764 | D65: México | E65: 7749 | F65: 02B5E94B-8E65-5E6F-A952-63D7F76CE890 | G65: Swappi 15 de octubre de 2025 a 14 de noviembre de 2025. ASOCIACION CONDOMINAL DE DISTRITO COZUMEL CENTRO | H65: ASOCIACION CONDOMINAL DE DISTRITO COZUMEL CENTRO | I65: 82553 | J65: 45931 | K65: 45931 | M65: 1
A66: 289306 | B66: 45890.852 | C66: 142496 | D66: México | E66: 696 | F66: 02D731BD-3AE5-5892-8AF0-12F89570A867 | G66: Licencia de Software 15 de agosto de 2025 a 14 de septiembre de 2025. Benjamin Franklin 180 | H66: Benjamin Franklin 180 | I66: 137955 | J66: 45870 | K66: 45870 | M66: 1
A67: 231890 | B67: 45632.628 | C67: 105217 | D67: México | E67: 696 | F67: 02D8812D-BF77-5F25-9B17-B98C648783E2 | G67: Licencia de Software 07 de diciembre de 2024 a 06 de enero de 2025. | H67: CONDOMINIO ORIZABA 203 | I67: 104557 | J67: 45627 | K67: 45627 | M67: 1
A68: 261235 | B68: 45793.615 | C68: 108517 | D68: México | E68: 4176 | F68: 02ECF7D8-6695-5691-AA28-94173449641B | G68: Licencia de Software 16 de mayo de 2025 a 15 de junio de 2025. Residencial CC | H68: Residencial CC | I68: 101816 | J68: 45778 | K68: 45778 | M68: 1
A69: 262497 | B69: 45803.601 | C69: 120810 | D69: México | E69: 2820 | F69: 0316C784-25CD-585F-B47F-7D2CD20845E0 | G69: Swappi 25 de mayo de 2025 a 24 de junio de 2025. RESIDENCIAL ZETERO, A.C. | H69: RESIDENCIAL ZETERO, A.C. | I69: 114207 | J69: 45778 | K69: 45778 | M69: 1
... A82: 273672 | B82: 45845.876 | C82: 103765 | D82: México | E82: 2561.28 | F82: 03ABDE3C-0886-5F61-BD02-54579D0F1269 | G82: Sistema de Transferencias y Pagos 07 de julio de 2025 a 06 de agosto de 2025. Quinta Los Sabinos | H82: Quinta Los Sabinos | I82: 103468 | J82: 45839 | K82: 45839 | M82: 1
A83: 261718 | B83: 45796.919 | C83: 117853 | D83: México | E83: 3480 | F83: 03C1113E-2CB9-5443-A79F-82CEE052F945 | G83: Control de Acceso mes 19 de mayo de 2025. BOLONGO RESORT VISION PATRIMONIAL | H83: BOLONGO RESORT VISION PATRIMONIAL | I83: 114889 | J83: 45778 | K83: 45778 | L83: Control de acceso | M83: 1
A84: 323067 | B84: 45987.532 | C84: 101819 | D84: México | E84: 1832.8 | F84: 03C5D9D8-C1A2-5844-A1F9-BCBBCC2558F9 | G84: Licencia de Software 26 de Noviembre de 2025 a 25 de Diciembre de 2025. Castaño | H84: Castaño | I84: 102874 | J84: 45962 | K84: 45962 | M84: 1
A85: 263589 | B85: 45810.602 | C85: 98551 | D85: México | E85: 1160 | F85: 03C65D6A-E57E-5B50-86AF-47AD9D844B3E | G85: Licencia de Software 01 de junio de 2025 a 30 de junio de 2025. Condominio Casa Pairo | H85: Condominio Casa Pairo | I85: 99226 | J85: 45809 | K85: 45809 | M85: 1
A86: 284068 | B86: 45882.566 | C86: 124935 | D86: México | E86: 1642.56 | F86: 03CACC0A-53A5-5D18-9E2C-24EB6413398F | G86: Licencia de Software 13 de agosto de 2025 a 12 de septiembre de 2025. QUINTA LAS BUGAMBILIAS | H86: QUINTA LAS BUGAMBILIAS | I86: 121521 | J86: 45870 | K86: 45870 | M86: 1
A87: 239540 | B87: 45688.59 | C87: 117525 | D87: México | E87: 995.28 | F87: 03CB9EA9-39F9-536C-A77D-4004BB59F957 | G87: Licencia de Software 09 de enero de 2025 a 08 de febrero de 2025. Condominos Punta Ambar | H87: Condominos Punta Ambar | I87: 114614 | J87: 45658 | K87: 45658 | M87: 1
A88: 265790 | B88: 45820.622 | C88: 61260 | D88: México | E88: 1438.4 | F88: 03E91DD9-B6EA-5DB6-A5B5-23F10C6B3702 | G88: Licencia de Software 12 de junio de 2025 a 11 de julio de 2025. Palma Kentia | H88: Palma Kentia | I88: 61664 | J88: 45809 | K88: 45809 | M88: 1
A89: 311236 | B89: 45957.502 | C89: 117853 | D89: México | E89: 9644 | F89: 0429B145-2681-5704-9FDD-3AE14746CF52 | G89: Control de Acceso mes 25 de Octubre de 2025. BOLONGO RESORT VISION PATRIMONIAL | H89: BOLONGO RESORT VISION PATRIMONIAL | I89: 114889 | J89: 45931 | K89: 45931 | M89: 1
A90: 263832 | B90: 45810.962 | C90: 116762 | D90: México | E90: 15541.4 | F90: 042AD223-6552-59BE-925C-D9D6F4BCE7EA | G90: Sistema de Transferencias y Pagos 22 de mayo de 2025 a 21 de mayo de 2026. El Famoso | H90: El Famoso | I90: 114017 | J90: 45778 | K90: 46113 | M90: 1
A91: 259782 | B91: 45791.585 | C91: 117505 | D91: México | E91: 880.44 | F91: 042CBEF7-07F6-5ABA-8C84-72AC1F2EA8CD | G91: Facturación CFDI 4.0 | H91: Larissa 2 | I91: 114615 | J91: 45778 | K91: 45778 | M91: 1
A92: 289448 | B92: 45891.561 | C92: 42452 | D92: México | E92: 975.52 | F92: 043553CC-3637-50F0-BDCC-9098DCB9B1C5 | G92: Licencia de Software 22 de agosto de 2025 a 21 de septiembre de 2025. Wit Apartments | H92: Wit Apartments | I92: 78330 | J92: 45870 | K92: 45870 | M92: 1
A93: 270669 | B93: 45831.586 | C93: 81326 | D93: México | E93: 1948.8 | F93: 04389F1B-7E6C-5D88-A063-3FE0797DA6DE | G93: Facturación CFDI 4.0 | H93: CONDOMINIO SABAIA | I93: 83149 | J93: 45809 | K93: 45809 | M93: 1
A94: 273407 | B94: 45842.899 | C94: 119160 | D94: México | E94: 1264.4 | F94: 044DFBCF-640F-50E6-824F-98E066B5F24E | G94: Sistema de Transferencias y Pagos 04 de julio de 2025 a 03 de agosto de 2025. ASOCIACION DE CONDOMINOS THE ESTATES | H94: ASOCIACION DE CONDOMINOS THE ESTATES | I94: 116241 | J94: 45839 | K94: 45839 | M94: 1
A95: 253738 | B95: 45770.567 | C95: 72750 | D95: México | E95: 812 | F95: 04524BEB-F26A-5C91-9361-8651FF70A17C | G95: Licencia de Software 23 de abril de 2025 a 22 de mayo de 2025. Mirage IV AC | H95: Mirage IV AC | I95: 73841 | J95: 45748 | K95: 45748 | M95: 1
... A104: 231709 | B104: 45632.625 | C104: 116343 | D104: México | E104: 710 | F104: 04D42657-5B0B-5692-A779-36FE26F53E61 | G104: Licencia de Software 07 de diciembre de 2024 a 06 de enero de 2025. | H104: TORRE NORTE CALICANTOS | I104: 113728 | J104: 45627 | K104: 45627 | M104: 1
A105: 270941 | B105: 45832.599 | C105: 89409 | D105: México | E105: 769.08 | F105: 04D99D72-43FE-59EF-8AF9-A7A75B778154 | G105: Licencia de Software 24 de junio de 2025 a 23 de julio de 2025. Camarones 408 | H105: Camarones 408 | I105: 92124 | J105: 45809 | K105: 45809 | L105: Gasto Común | M105: 1
A106: 247877 | B106: 45749.577 | C106: 107197 | D106: México | E106: 968.88 | F106: 04E0B868-6CDB-56D3-BE21-D1266ED4E190 | G106: Licencia de Software 02 de abril de 2025 a 01 de mayo de 2025. Grand Cousin | H106: Grand Cousin | I106: 106207 | J106: 45748 | K106: 45748 | M106: 1
A107: 282015 | B107: 45873.664 | C107: 115656 | D107: México | E107: 890.88 | F107: 04F6EED0-1940-5AC2-B219-191C0A024B77 | G107: Licencia de Software 03 de agosto de 2025 a 02 de septiembre de 2025. Hacienda La Galia | H107: Hacienda La Galia | I107: 113246 | J107: 45870 | K107: 45870 | M107: 1
A108: 255978 | B108: 45782.795 | C108: 123285 | D108: México | E108: 64566.18 | F108: 04F9621D-827D-5F6E-93AA-8244957A4669 | G108: Licencia de Software 15 de abril de 2025 a 14 de abril de 2026. Unidad Condominal La Isla A.C. | H108: Unidad Condominal La Isla A.C. | I108: 106109 | J108: 45748 | K108: 46082 | M108: 1
A109: 239593 | B109: 45692.523 | C109: 99153 | D109: México | E109: 1160 | F109: 04FA8259-FC2E-562D-9D13-79FD38982316 | G109: Licencia de Software 03 de febrero de 2025 a 02 de marzo de 2025. Palmas Residencial | H109: Palmas Residencial | I109: 99692 | J109: 45689 | K109: 45689 | M109: 1
A110: 231786 | B110: 45632.625 | C110: 22585 | D110: México | E110: 2419.16 | F110: 0537F2E5-5A4F-5329-A9CF-CC62E66FA102 | G110: Facturación CFDI 4.0 | H110: CONDOMINOS LOMAS IV AC | I110: 22857 | J110: 45627 | K110: 45627 | M110: 1
A111: 269473 | B111: 45824.78 | C111: 130454 | D111: México | E111: 144.83 | F111: 053B3534-7C4F-5FB5-9D03-5A880FCC721F | G111: Licencia de Software 16 de junio de 2025 a 15 de julio de 2025. Condominio IGUANA | H111: Condominio IGUANA | I111: 126637 | J111: 45809 | K111: 45809 | M111: 1
A112: 264663 | B112: 45814.2 | C112: 127972 | D112: México | E112: 22944.8 | F112: 054DC730-80B8-595A-828C-0E48D1EEE15E | G112: Sistema de Transferencias y Pagos 06 de junio de 2025 a 05 de junio de 2026. Taheima Cluster A.C | H112: TAHEIMA CLUSTER B | I112: 124228 | J112: 45809 | K112: 46143 | M112: 1
A113: 253543 | B113: 45769.617 | C113: 90039 | D113: México | E113: 1846.72 | F113: 0561A7C7-D287-5744-8F77-F740A23F8154 | G113: Sistema de Transferencias y Pagos 22 de abril de 2025 a 21 de mayo de 2025. Condominio CEIBA 141 AC | H113: Condominio CEIBA 141 AC | I113: 91301 | J113: 45748 | K113: 45748 | M113: 1
A114: 283104 | B114: 45876.637 | C114: 136257 | D114: México | E114: 801 | F114: 0562DA6A-2859-5A3B-BB9C-AB42EA294FBD | G114: Swappi 14 de julio de 2025 a 13 de agosto de 2025. Palma Mexicana | H114: Palma Mexicana | I114: 122022 | J114: 45839 | K114: 45839 | M114: 1
A115: 315845 | B115: 45974.507 | C115: 118539 | D115: México | E115: 1160 | F115: 0566D723-5F1A-57A2-8D90-AA9D4CFEB39F | G115: Licencia de Software 13 de Noviembre de 2025 a 12 de Diciembre de 2025. TORRE 25 | H115: TORRE 25 | I115: 115441 | J115: 45962 | K115: 45962 | M115: 1
A116: 248723 | B116: 45757.579 | C116: 118193 | D116: México | E116: 1440.8 | F116: 056E6C57-778F-5AC9-98B2-77568AF5A0BC | G116: Sistema de Transferencias y Pagos 10 de abril de 2025 a 09 de mayo de 2025. CONDOMINIO CATANIA | H116: CONDOMINIO CATANIA | I116: 115141 | J116: 45748 | K116: 45748 | M116: 1
A117: 255812 | B117: 45782.596 | C117: 66213 | D117: México | E117: 1774.63 | F117: 05811D2E-89E1-5FAE-AF27-D7701C95F412 | G117: Licencia de Software 02 de mayo de 2025 a 01 de junio de 2025. SIE7E BY COSMOPOLITAN | H117: SIE7E BY COSMOPOLITAN | I117: 66716 | J117: 45778 | K117: 45778 | M117: 1
... A129: 243268 | B129: 45709.604 | C129: 115796 | D129: México | E129: 2014.56 | F129: 060B7CD7-666A-5CDD-B9FD-64B069DF8FAC | G129: Sistema de Transferencias y Pagos 21 de febrero de 2025 a 20 de marzo de 2025. Fraccionamiento Privanzas | H129: Fraccionamiento Privanzas | I129: 113341 | J129: 45689 | K129: 45689 | M129: 1
A130: 282980 | B130: 45881.566 | C130: 108583 | D130: México | E130: 1160 | F130: 060C6FE3-A37E-5FDD-9758-FCCEFE46108B | G130: Licencia de Software 07 de agosto de 2025 a 06 de septiembre de 2025. EJE CENTRAL SUB6 TORRE F | H130: EJE CENTRAL SUB6 TORRE F | I130: 86448 | J130: 45870 | K130: 45870 | L130: Gasto Común | M130: 1
A131: 261492 | B131: 45796.602 | C131: 121107 | D131: México | E131: 696 | F131: 06145F9C-537D-5AF7-99CB-5043861A06B6 | G131: Licencia de Software 17 de mayo de 2025 a 16 de junio de 2025. CONDOMINIO PLAZA TLALPAN, AC | H131: CONDOMINIO PLAZA TLALPAN (HISTORICO) | I131: 117957 | J131: 45778 | K131: 45778 | M131: 1
A132: 280997 | B132: 45866.606 | C132: 59173 | D132: México | E132: 3845.3 | F132: 061524C2-8EA3-5746-83C2-FB161ABD6CFB | G132: Licencia de Software 28 de julio de 2025 a 27 de agosto de 2025. CONDOMINIO ORIZABA 203 | H132: CONDOMINIO ORIZABA 203 | I132: 104557 | J132: 45839 | K132: 45839 | L132: Gasto Común | M132: 1
...
